Workbook

Sheet Desejos e Cancelamentos
A1: SKU | B1: Produto | C1: Precisa de Certificação? | D1: Qual Certificação? | E1: Por que precisa certificar? | F1: NCM | G1: FAT | H1: Quando foi cancelado? | I1: Por que foi cancelado?
B2: Squishy Toy | C2: Não | F2: NOVA
B3: Apontador Elétrico | C3: Não | E3: Possui motor | F3: NOVA
B4: Patins IMG | C4: Não | F4: NOVA
B5: Patins Puket | C5: Sim | D5: INMETRO Brinquedos | E5: Destinado para Crianças | F5: NOVA
A6: PI4662Y | B6: MASCARA ANTI-IDADE | C6: Sim | D6: ANVISA Correlatos | E6: Produto para Saúde | F6: NOVA | G6: FAT 2 / 2021 | H6: 44074 | I6: Não possuímos uma AFE para produtos de saúde (correlatos), assim como não temos estimado a compra de produtos que entrem neste escopo num futuro próximo, desta forma os custos para obtenção da AFE de importação e distribuição, assim como os custos para ensaios (onde já tinhamos um problema do fornecedor não garantir a eficácia do produto), e também os custos para registro na ANVISA superavam os 30k, inviabilizando a compra deste produto
B7: Carregador luminaria dobrável | F7: NOVA | H7: 44063 | I7: Produto não tinha ISO 9001
B8: Maquina de Bolha de sabão | C8: Sim | D8: INMETRO Brinquedos | E8: Destinado para Crianças | F8: NOVA
B9: Termometro | C9: Não | F9: NOVA
B10: Pistola de dinheiro (impressora | C10: Sim | D10: INMETRO Brinquedos | F10: NOVA
B11: Cofre Eletronico Mario? | C11: Não | F11: NOVA | G11: 2021 - FAT04
B12: Chaveiro e placa yoshi mario ver como é o produto | C12: Não | F12: NOVA | G12: 2021 - FAT04
A13: PI4746Y | B13: Caneta com mensagem amor proprio | C13: Sim | D13: INMETRO Artigos Escolares | E13: Destinado para Crianças | F13: NOVA | G13: 2021 - FAT04 | H13: 44111 | I13: Produto precisava de de certificação, com isso seu valor não fechava mais. (Foi considerado como sem certificação por ter custo acima de 0,50 USD por peça, porém esta regra é a do dumping, não da certificação)
B14: BOLSA TÉRMICA HP COM TAG CUSTOMIZÁVEL | C14: Não | F14: NOVA | G14: 2021 - FAT04
A15: PI4799Y | B15: PUFE COM SPEAKER MARIO | C15: Sim | D15: ANATEL MÓDULO BLUETOOTH/WIFI | E15: Bluetooth | F15: NOVA | G15: 2021 - FAT05 | H15: 44138 | I15: Todos projetos da linha MARIO foram cancelados em 03/11, email do Daniel Zhu
A16: PI4783Y | B16: CHAVEIRO DIY MARIO | C16: Sim | D16: INMETRO SISTEMA 7 (LOTE) - PORTARIA 321 | E16: Destinado para Crianças | F16: NOVA | G16: 2021 - FAT05 | H16: 44138 | I16: Todos projetos da linha MARIO foram cancelados em 03/11, email do Daniel Zhu
A17: PI4784Y | B17: CHAVEIRO DIY MARIO | C17: Sim | D17: INMETRO SISTEMA 7 (LOTE) - PORTARIA 321 | E17: Destinado para Crianças | F17: NOVA | G17: 2021 - FAT05 | H17: 44138 | I17: Todos projetos da linha MARIO foram cancelados em 03/11, email do Daniel Zhu
A18: PI4814Y | B18: ESTOJO MARIO | C18: Sim | D18: INMETRO SISTEMA 5 (FABRICA) - PORTARIA 563 | E18: Destinado para Crianças | F18: NOVA | G18: 2021 - FAT05 | H18: 44138 | I18: Todos projetos da linha MARIO foram cancelados em 03/11, email do Daniel Zhu
A19: PI4792Y | B19: HEADPHONE MARIO | C19: Sim | D19: ANATEL MÓDULO BLUETOOTH/WIFI | E19: Bluetooth | F19: NOVA | G19: 2021 - FAT05 | H19: 44138 | I19: Todos projetos da linha MARIO foram cancelados em 03/11, email do Daniel Zhu
A20: PI4793Y | B20: Kit Pipoca Mario | C20: Sim | D20: INMETRO SISTEMA 5 (FABRICA) - PORTARIA 563 | E20: Destinado para Crianças | F20: NOVA | G20: 2021 - FAT05 | H20: 44138 | I20: Todos projetos da linha MARIO foram cancelados em 03/11, email do Daniel Zhu
A21: PI4808Y | B21: almofada biefing livre mario | C21: Sim | D21: INMETRO SISTEMA 5 (FABRICA) - PORTARIA 563 | E21: Destinado para Crianças | F21: NOVA | G21: 2021 - FAT05 | H21: 44138 | I21: Todos projetos da linha MARIO foram cancelados em 03/11, email do Daniel Zhu
B22: Capacete de Bicicleta | C22: Não | D22: Não | E22: OBS | F22: NOVA | G22: 2021 - FAT06 e 7 | I22: A certificação compulsória das bicicletas infantis não contempla itens auxiliares (joelheiras, capacetes, luvas, etc.), limitando-se apenas à bicicleta infantil. Para os itens auxiliares, a certificação é voluntária. Somente capacetes de uso adulto para motocicletas são certificados compulsoriamente no Inmetro. Porém, componentes esportivos para brincadeira, que simulam os de uso profissional, com dimensões diferentes das medidas padrões, são considerados brinquedos.
A23: N/A | B23: Headphone Esquenta Orelha (PI5234Y) | C23: Sim | D23: ANATEL MÓDULO BLUETOOTH/WIFI | E23: Bluetooth | F23: NOVA | G23: 2021 - FAT 05 | H23: 44470 | I23: Corte na verba para compras de itens 2021/2022.
A24: PI5234Y | B24: Carregador wireless neutro (PI5244Y) | C24: Sim | D24: ANATEL MÓDULO BLUETOOTH/WIFI | E24: Carregador | F24: NOVA | G24: 2021 - FAT 05 | H24: 44470 | I24: Corte na verba para compras de itens 2021/2022.
A25: PI5245Y | B25: LuminárIa Carregador wireless Namorados (PI5245Y) | C25: Sim | D25: ANATEL MÓDULO BLUETOOTH/WIFI | E25: Carregador | F25: NOVA | G25: 2021 - FAT 05 | H25: 44470 | I25: Corte na verba para compras de itens 2021/2022.
A26: PI5264Y | B26: Speaker com Alexa (PI5264Y) | C26: Sim | D26: ANATEL MÓDULO BLUETOOTH/WIFI | E26: Bluetooth | F26: NOVA | G26: 2021 - FAT 05 | H26: 44470 | I26: Corte na verba para compras de itens 2021/2022.
A27: PI5279Y | B27: Wireless speaker (PI5279Y) | C27: Sim | D27: ANATEL MÓDULO BLUETOOTH/WIFI | E27: Bluetooth | F27: NOVA | G27: 2021 - FAT 05 | H27: 44470 | I27: Corte na verba para compras de itens 2021/2022.
A28: PI5193Y | B28: Vitrola feminino adulto (PI5193Y) | C28: Sim | D28: ANATEL MÓDULO BLUETOOTH/WIFI | E28: Bluetooth | F28: NOVA | H28: 44470 | I28: Revisão de verba, estratégia e sortimento em loja.
A29: PI5308Y | B29: Fone por Condução ossea (PI5308Y) | C29: Sim | D29: ANATEL MÓDULO BLUETOOTH/WIFI | E29: Bluetooth | F29: NOVA | G29: 2022 - FAT06 | H29: 44529
A30: PI5327Y | B30: Vitrola Movel Retro (PI5327Y) | C30: Sim | D30: ANATEL MÓDULO BLUETOOTH/WIFI | E30: Bluetooth | F30: NOVA | G30: 2022 - FAT06 | H30: 44529
A31: PI5295Y | B31: LUMINARIA WIRELESS URSINHOS CARINHOS | C31: Sim | D31: ANATEL CELULARES | E31: Carregador | F31: NOVA | G31: 2022 - FAT07 | H31: 44529
A32: PI5136Y | B32: SPEAKER E LUMINARIA COM ALCA FITDANCE | C32: Sim | D32: ANATEL MÓDULO BLUETOOTH/WIFI | E32: Bluetooth | F32: NOVA | G32: 2021 - FAT 12 | H32: 44529
A33: PI4006Y | B33: CARREGADOR PORTATIL FRIENDS MOLDURA | C33: Sim | D33: Acessório para Telefone Móvel Celular do tipo Bateria Auxiliar | E33: Power Bank | F33: 8507.60.00 | G33: 2019 - FAT11 | H33: 44501 | I33: Cancelamos os testes, pois ocorreu falha duas vezes e seria obrigatório fazer os ensaios completos novamente, gerando um custo de R$ 4800.
A34: PI5380Y | B34: MINI LUMINARIA OUTROS PERSONAGENS II HP | C34: Sim | D34: INMETRO BRINQUEDOS SISTEMA 5 (FÁBRICA) - PORTARIA 302 | E34: Destinado para Crianças | F34: NOVA | G34: 2021 - FAT 08 | H34: 44593 | I34: Curadoria/Letícia: Devido ao prazo de desenvolvimento e prazo de certificação não vamos conseguir lançar esse item em fat 08 e perderemos a campanha de HP.
A35: PI5399Y | B35: MINI LUMINARIA PERSONAGEM I HP | C35: Sim | D35: INMETRO BRINQUEDOS SISTEMA 5 (FÁBRICA) - PORTARIA 302 | E35: Destinado para Crianças | F35: NOVA | G35: 2021 - FAT 08 | H35: 44593 | I35: Curadoria/Letícia: Devido ao prazo de desenvolvimento e prazo de certificação não vamos conseguir lançar esse item em fat 08 e perderemos a campanha de HP.
A36: PI5414Y | B36: LUMINARIA POMO DE OURO HP | C36: Sim | D36: INMETRO BRINQUEDOS SISTEMA 5 (FÁBRICA) - PORTARIA 302 | E36: Destinado para Crianças | F36: NOVA | G36: 2021 - FAT 08 | H36: 44593
A37: PI5370Y | B37: CHAVEIRO SILICONE UC | C37: Sim | D37: INMETRO BRINQUEDOS SISTEMA 5 (FÁBRICA) - PORTARIA 302 | E37: Destinado para Crianças | F37: NOVA | G37: 2021 - FAT 08 | H37: 44593 | I37: Cancelado - Chaveiro era 3D na parte de cima e de acordo com o OCP, demandaria Certificação como Brinquedos. O Inmetro ainda não retornou nossa consulta.
A38: PI5549Y | B38: JOGO DE DOMINO | C38: Sim | D38: INMETRO BRINQUEDOS SISTEMA 5 (FÁBRICA) - PORTARIA 302 | E38: Destinado para Crianças | F38: NOVA | G38: 2021 - FAT 08 | H38: 44713 | I38: Cancelado - não conseguimos enviar a arte dentro do prazo e não encontramos nenhuma op no catálogo do fornecedor que atendesse nossas expectativas de formato e preço.
A39: CS2160 | B39: JOGO STARTER PACK DO BRASILEIRO | C39: Sim | D39: INMETRO BRINQUEDOS SISTEMA 1b - (LOTE) - PORTARIA 302 | E39: Destinado para Crianças | F39: NOVA | G39: 2021 - FAT 11 | H39: 44805 | I39: Cancelado - Estávamos com o cmv acima da meta e ainda tivemos mais o custo de certificação e isso inviabilizou o produto.
A40: CS2192 | B40: QUEBRA CABECA MAES | C40: Sim | D40: INMETRO BRINQUEDOS SISTEMA 5 (FÁBRICA) - PORTARIA 302 | E40: Destinado para Crianças | F40: NOVA | G40: 2023 - FAT03 | H40: 44805 | I40: Cancelado - motivos de revisão de estratégia de lançamento.
A41: PI6249Y
A42: PI6228Y
A43: 100400420 | B43: MICROPHONE BLUETOOTH UNI MUSIC | G43: INVERNO 23 | I43: 15/07 - Item cancelado. -- Aprovação Qualidade: 22/06 TP & Artworks before deadline Jun/25
A44: 100400421 | B44: MICROFONE KARAOKE BLUETOOTH TUBA | G44: INVERNO 23 | I44: 15/07 - Item cancelado. -- Aprovação Qualidade: 22/06 TP & Artworks before deadline Jun/25
A45: 50403295 | B45: CHAVEIRO PELUCIA GATA | G45: ALTO VERAO 2023 | I45: 04/08 - Item cancelado. 25/07 - Testes finalizados, aguardando finalização da arte da embalagem para recebimento dos laudos dos ensaios. 11/07 - Novas amostras (5 unidades Uni - 050403293) estão prontas para coleta. 04/07 - Novas amostras ficarão prontas na próxima semana. Relatório de Amostragem será enviado hoje para Brics China.
A46: CS2160 | B46: JOGO STARTER PACK DO BRASILEIRO | G46: 2022 - FAT 10 | I46: 02/09 - Item cancelado. 22/08 - Retornamos para a Curadoria quanto a necessidade de certificação, aguardando definição para avançar. 16/08 - Enviado o custo de certificação no ERP (R$ 2.000,00). 12/08 - Colorgraf informou que não possui a certificação para o item.
A47: CS2192 | B47: QC NOSSO FORMATO 100PCS | G47: 2023 - FAT04 | I47: 06/09 - Produto cancelado. 17/08 - Compra confirmada, aguardando envio do projeto
A48: PI5864Y | B48: PORTA PIJAMAS 1 | G48: 2023 - FAT 04 | I48: 11/11 - Projeto cancelado. Pelo cronograma de certificação esse item já seria fat 06 porque atrasamos o envio do projeto e ainda vamos pedir o ajuste no tamanho e não achamos que esse item coordenaria com os itens deste FAT. 27/10 - Amostra será recebida até quinta-feira. 25/10 - Compra não foi confirmada ainda. 18/10 - Recebemos o memorial da China, abrindo o processo com a Brics. Chegada CD schedule atual: 19/04. 07/10 - Retorno Brics: produto passível de certificação. 03/10 - Projeto recebido e enviado para consulta. 12/09 - Prazo para envio do projeto: 17/09. 26/08 - Sourcing: aguardando envio do projeto. 17/08 - Compra confirmada, aguardando envio do projeto
A49: PI5865Y | B49: TRAVESSEIRO COM GRAVADOR MIX DE EMOCOES | G49: 2023 - FAT04 | I49: 10/10 - Retorno Brics: produto não é passível de certificação. 09/10 - Projeto enviado para análise da Brics. 12/09 - Prazo para envio do projeto: 22/09. 26/08 - Sourcing: aguardando envio do projeto. 17/08 - Compra confirmada, aguardando envio do projeto
A50: PI5890Y | B50: KIT ORGANIZADOR PAPELARIA POSSIBILIDADES | G50: 2023 - FAT05 | I50: 27/09 - A caneta será trocada por uma de metal, e a borracha, por clipes. Não será necessário certificar o kit. 15/09 - Ju: vão tentar caneta com corpo metálico e mais clipes, para fugir da certificação. 12/09 - Prazo para envio do projeto: 19/09. 05/09 - Projeto não enviado, Vincent vai verificar em paralelo quanto à certificação (documentos e amostras). 17/08 - Compra confirmada, aguardando envio do projeto
A51: PI5891Y | B51: KIT CANETAS DE MARCAR COPOS E TACAS BORA | G51: 2023 - FAT05 | I51: 25/10 - Inmetro retornou e o entendimento é de que o produto não necessita de certificação. 29/09 - Documentos recebidos. Liberação 13/03 considerando início de produção após os testes. 27/09 - Amostras ficarão prontas em 10/10. 20/09 - Projeto recebido, encaminhamos para a Brics. Consulta feita ao Inmetro, aguardando retorno. 13/09 - Prazo para desenvolvimento: 19/09. Informado quantidade de amostras para a China e solicitados os documentos. 05/09 - Cobrado sobre data estimada para finalização da arte. Projeto não enviado ainda, Vincent vai verificar em paralelo quanto à certificação (documentos e amostras). 22/08 - Solicitadas maiores informações para realizar a consulta direta com o Inmetro. 18/08 - Aguardando retorno da China quanto aos questionamentos do OCP, para definir se item é certificado. 17/08 - Compra confirmada, aguardando envio do projeto.
A52: CS2207 | B52: QC NOSSO FORMATO I 100PCS | G52: 2023 - FAT 04 | I52: 17/11 - Produto cancelado, não conseguimos viabilizar no nacional, vamos desenvolver com a China. (500+ pçs). 25/10 - Sem atualização. 27/09 - Cotação com a Gráfica Rocha em andamento, definição até 15/10. 21/09 - Prazo criação da arte: 01/12. 31/08 - Andréia está cotando com outro fornecedor. 17/08 - Compra confirmada, aguardando envio do projeto
A53: CS2208 | B53: QC NOSSO FORMATO ANIVERSARIO 100PCS | G53: 2023 - FAT 04 | I53: 17/11 - Produto cancelado, não conseguimos viabilizar no nacional, vamos desenvolver com a China. (500+ pçs). 25/10 - Sem atualização. 27/09 - Cotação com a Gráfica Rocha em andamento, definição até 15/10. 21/09 - Prazo criação da arte: 01/12. 31/08 - Andréia está cotando com outro fornecedor. 17/08 - Compra confirmada, aguardando envio do projeto
A54: CS2209 | B54: QC NOSSO FORMATO II 100PCS | G54: 2023 - FAT 04 | I54: 17/11 - Produto cancelado, não conseguimos viabilizar no nacional, vamos desenvolver com a China. (500+ pçs). 25/10 - Sem atualização. 27/09 - Cotação com a Gráfica Rocha em andamento, definição até 15/10. 21/09 - Prazo criação da arte: 01/12. 31/08 - Andréia está cotando com outro fornecedor. 17/08 - Compra confirmada, aguardando envio do projeto
A55: CS2210 | B55: QC NOSSO FORMATO III 100PCS | G55: 2023 - FAT 04 | I55: 17/11 - Produto cancelado, não conseguimos viabilizar no nacional, vamos desenvolver com a China. (500+ pçs). 25/10 - Sem atualização. 27/09 - Cotação com a Gráfica Rocha em andamento, definição até 15/10. 21/09 - Prazo criação da arte: 01/12. 31/08 - Andréia está cotando com outro fornecedor. 17/08 - Compra confirmada, aguardando envio do projeto
A56: PI5951Y | B56: BORRACHA FUN 01 | G56: 2023 - FAT 05 | I56: 02/12 - Item cancelado. 08/10 - Item em standby: vamos escolher modelos prontos do fornecedor. 31/10 - Sourcing enviou opções de marca-textos da Joy Rain para o time de produto avaliar. 14/10 - Projeto enviado, aguardando cotações. 28/09 - Aguardando confirmação da China se a fábrica será a mesma do certificado anterior.
A57: PI5952Y | B57: MARCA TEXTO FUN 01 | G57: 2023 - FAT 05 | I57: 02/12 - Item cancelado. 08/10 - Item em standby: vamos escolher modelos prontos do fornecedor. 31/10 - Sourcing enviou opções de marca-textos da Joy Rain para o time de produto avaliar. 14/10 - Projeto enviado, aguardando cotações. 28/09 - Aguardando confirmação da China se a fábrica será a mesma do certificado anterior.
... A62: (900900751) TI27 | B62: CARREGADOR VEICULAR TIPO C USB 38W PRETO | G62: 2023 - FAT 05 | I62: 13/02 - Cancelado no laboratório. 24/01 - Stand-by. 13/01 - Início dos testes: 18/01. Data prevista para o relatório: 17/03. 09/01 - Aguardando retorno do laboratório quanto à agenda.
B63: SHELL DE MADEIRA DE GRAVACAO PORTATIL | G63: 2023 - FAT 06 | I63: 07/12 - Item cancelado, revisão de OTB. 29/11 - Solicitadas as amostras e documentos para a certificação Anatel no ERP. 25/11 - Vitrola que vão seguir será o modelo enviado pelo Vincent.
B64: CANETA MULTIUSO PARAFUSADA CINZA | G64: 2023 - FAT06 | I64: 02/11 - Sourcing: Caneta é de metal.
B65: BINGO KIT DE JOGO SOL | G65: 2023 - FAT 06 | I65: 24/02 - Projeto cancelado. 06/02 - Aguardando confirmação da área de Produto, se o projeto será mantido. 19/01 - Custo de certificação não estava incluso no cálculo do item. Foi refeito e informado p/ Fernanda. 10/01 - Aguardando retorno da Brics quanto à necessidade de certificação.
B66: CAIXA BARALHO 153 | G66: 2023 - FAT06 | I66: 16/12 - Produto cancelado. 02/12 - Possibilidade de vir o baralho junto.
B67: CONJUNTO DE MARCA TEXTO | G67: 2023 - FAT 07 | I67: 07/12 - Item cancelado, revisão de OTB. VALOR DE CRÉDITO PROCESSO BRICS: R$ 405,24. 02/12 - Item com risco de cancelamento, a inclusão ainda está pendente. 31/10 - Sourcing enviou as referências de produto.
B68: UMIDIFICADOR GATINHO | G68: 2023 - FAT09 | I68: 17/01 - Questionamos na task de QC se o produto terá baterias internas. 10/01 - Entendimento sobre a certificação mudou, vamos avaliar com o Produto se vão seguir com o produto desta forma. 03/01 - O produto não necessitará certificação, pois sua fonte de alimentação é USB.
B69: RELÓGIO COM PALAVRAS | G69: 2023 - FAT 09 | I69: 26/04 - Item cancelado por conta de problemas com Qualidade. 06/02 - Cobramos atualizações. 11/01 - Questionei sobre o prazo de definição de novo fornecedor. Fred retornou que terão definição somente após CNY. 10/01 - Fred informou que será dado andamento no desenvolvimento do produto, porém o fornecedor atual está com o preço muito alto, e avaliarão outros fornecedores. Informou que a certificação irá ficar em stand-by por enquanto. 10/01 - Cobrei os documentos e as amostras. 05/01 - Sourcing informou que enviará as informações na próxima semana.
B70: TESOURA COM CASE | G70: 2023 - FAT 09 | I70: Item cancelado 06/02 - Cobramos atualizações. 10/01 - A fábrica já está fechada para o CNY, documentos e amostras serão enviados no retorno. 09/01 - Confirmamos a necessidade de certificação, foram solicitados os documentos e as amostras.
B71: KARAOKE | G71: 2023 - FAT 09 | I71: 24/02 - Produto cancelado, optado pela recompra do item PI5558Y no lugar em FAT 07. 15/02 - Amostras ficarão prontas dia 20/02. 24/01 - Confirmando se vem com fonte. 18/01 - Enviados os documentos para o OCD. 10/01 - Leadtime de produção: 60 dias. Previsão de chegada CD: 18/09. 09/01 - Sourcing informou que o forncedor está preparando os documentos, enviará até 13/1. Amostras estarão prontas apenas após CNY, 13/2.
B72: CAIXA DE SOM COM ESTAMPA | G72: 2023 - FAT09 | I72: 30/01 - Produto cancelado. 11/01 - Enviei o schedule considerando o recebimento da amostra até a terceira semana de fevereiro. Chegada CD: 18/09. 10/01 - Vincent informou que o leadtime de produção deve ser em torno de 60 dias (padrão). 09/01 - Sourcing informou que ainda não temos definição com qual modelo seguiremos. Assim que possível enviará o schedule das amostras.
B73: CHAVEIRO JOGOS | G73: 2023 - FAT09 | I73: 04/04 - Item cancelado. O motivo é que devido ao custo de certificação, os chaveiros teriam que ser vendidos a um preço ponta muito alto. 29/09 - Enviado sobre o pai de família e quantidade de amostras, Vincent informou que ainda estão definindo qual será o fornecedor final. 06/03 - Sourcing enviou o memorial descritivo final, encaminhei para a Brics e solicitei a proposta de certificação. 06/02 - Cobramos atualizações. 11/01 - Enviado o schedule para o Sourcing, questionando sobre a data de recebimento das amostras e leadtime do fabricante. 09/01 - Solicitados os documentos e as amostras.
B74: CHAVEIRO MEMORIA | G74: 2023 - FAT09 | I74: 04/04 - Item cancelado. O motivo é que devido ao custo de certificação, os chaveiros teriam que ser vendidos a um preço ponta muito alto. 29/09 - Enviado sobre o pai de família e quantidade de amostras, Vincent informou que ainda estão definindo qual será o fornecedor final. 06/03 - Sourcing enviou o memorial descritivo final, encaminhei para a Brics e solicitei a proposta de certificação. 06/02 - Cobramos atualizações. 11/01 - Enviado o schedule para o Sourcing, questionando sobre a data de recebimento das amostras e leadtime do fabricante. 09/01 - Solicitados os documentos e as amostras.
... B76: CHAVEIRO JOGO DE ENCAIXE | G76: 2023 - FAT09 | I76: 04/04 - Item cancelado. O motivo é que devido ao custo de certificação, os chaveiros teriam que ser vendidos a um preço ponta muito alto. 29/09 - Enviado sobre o pai de família e quantidade de amostras, Vincent informou que ainda estão definindo qual será o fornecedor final. 06/03 - Sourcing enviou o memorial descritivo final, encaminhei para a Brics e solicitei a proposta de certificação. 06/02 - Cobramos atualizações. 11/01 - Enviado o schedule para o Sourcing, questionando sobre a data de recebimento das amostras e leadtime do fabricante. 09/01 - Solicitados os documentos e as amostras.

Sheet Imaginarium
A1: MARCA | B1: IMAGEM | C1: CÓDIGO | D1: COLEÇÃO | E1: Fornecedor | F1: NOME | G1: NEGÓCIO | H1: TIPO DE CERTIFICAÇÃO | I1: AMOSTRAS NECESSÁRIAS | J1: STATUS | K1: DATA ÚLTIMA ATUALIZAÇÃO (INICIAL, MANUTENÇÃO OU ENCERRAMENTO) | L1: ROTULAGEM | M1: FABRICANTE | N1: Validade da Certificação | O1: Início Manutenção | P1: Número Certificado | Q1: Número Registro / Homologação | R1: OCP / OCD | S1: Possui ISO 9001? | T1: CHEGADA CD | U1: SITUAÇÃO | V1: Descrição E-commerce | W1: Prazo Final Venda
A2: IMAGINARIUM | B2: =HYPERLINK("https://imagens.imgnet.com.br/f/imaginarium/"&C2&";"&C2,image("https://imagens.imgnet.com.br/f/imaginarium/"&C2&"))")) | C2: PI4206Y | D2: 2020 - FAT01 | E2: Greatchip | F2: MALA USB SMART LOCKER CARREGANDO VIAGEM | H2: ANATEL CATEGORIA 2 - MÓDULO BLUETOOTH | I2: 2 unidades | J2: 15/06/21 - Certificado de homologação emitido. | L2: Produto + Manual (ANATEL) | N2: 45070 | O2: =N2-90 -> 44980 | P2: MT-5343/2021 | Q2: 06107-21-12659 | S2: FALSE | T2: =IFERROR(__xludf.DUMMYFUNCTION("IFERROR(VLOOKUP(C2,IMPORTRANGE(""https://docs.google.com/spreadsheets/d/1RmEXtNg60OGvqZjyMxiYNPJ6S_kcz01v57qrHugDWVc/edit#gid=0"",""Chegadas!E:AQ""),19,0),"""")"),"") | U2: Encerrado | W2: =N2 -> 45070
A3: IMAGINARIUM | B3: =HYPERLINK("https://imagens.imgnet.com.br/f/imaginarium/"&C3&";"&C3,image("https://imagens.imgnet.com.br/f/imaginarium/"&C3&"))")) | C3: PI4145Y | D3: 2020 - FAT01 | E3: PETKIT | F3: COMEDOURO SMART PETKIT BRANCO | G3: TECH - HOME TECH | H3: ANATEL CATEGORIA 2 - MÓDULO BLUETOOTH | I3: 2 unidades | J3: 01/06/23 - Certificado suspenso. - 24/06 - Certificado de Homologação emitido. 01/06/21 - Processo cadastrado na Anatel. 31/05/21 - Aprovado o CCT. | L3: Produto + Manual (ANATEL) | N3: 45077 | O3: =N3-90 -> 44987 | P3: MT-5348/2021 | Q3: 07697-21-11541 | S3: FALSE | T3: =IFERROR(__xludf.DUMMYFUNCTION("IFERROR(VLOOKUP(C3,IMPORTRANGE(""https://docs.google.com/spreadsheets/d/1RmEXtNg60OGvqZjyMxiYNPJ6S_kcz01v57qrHugDWVc/edit#gid=0"",""Chegadas!E:AQ""),19,0),"""")"),"") | U3: Encerrado | W3: =N3 -> 45077
A4: IMAGINARIUM | B4: =HYPERLINK("https://imagens.imgnet.com.br/f/imaginarium/"&C4&";"&C4,image("https://imagens.imgnet.com.br/f/imaginarium/"&C4&"))")) | C4: PI3875Y | D4: 2019 - FAT09 | E4: DOULEX | F4: AMPLIFICADOR BLUETOOTH ESTRELA GENIUS | G4: TECH - MUSIC | H4: ANATEL CATEGORIA 2 - MÓDULO BLUETOOTH | I4: 2 unidades | J4: 31/01/2023 -O certificado não será renovado. - 16/06/21 - Certificado de Homologação emitido. | L4: Produto + Manual (ANATEL) | N4: 45072 | O4: =N4-90 -> 44982 | P4: MT-5342/2021 | Q4: 06106-21-12406 | S4: FALSE | T4: =IFERROR(__xludf.DUMMYFUNCTION("IFERROR(VLOOKUP(C4,IMPORTRANGE(""https://docs.google.com/spreadsheets/d/1RmEXtNg60OGvqZjyMxiYNPJ6S_kcz01v57qrHugDWVc/edit#gid=0"",""Chegadas!E:AQ""),19,0),"""")"),"") | U4: Encerrado | W4: =N4 -> 45072
A5: IMAGINARIUM | B5: =HYPERLINK("https://imagens.imgnet.com.br/f/imaginarium/"&C5&";"&C5,image("https://imagens.imgnet.com.br/f/imaginarium/"&C5&"))")) | C5: PI4077Y | D5: 2020 - FAT02 | E5: Hesen | F5: ALMOFADA COELHA VEM QUE TEM | G5: CASA E DECORAÇÃO | H5: INMETRO SISTEMA 5 (FABRICA) - PORTARIA 563 | I5: 36 unidades | J5: Finalizado | L5: Produto + Embalagem (INMETRO) | N5: Certificado encerrado, validade do estoque do produto até 06/07/2023 | P5: IP-BRI-9435-2019-4 | Q5: 001343/2020 | S5: FALSE | T5: =IFERROR(__xludf.DUMMYFUNCTION("IFERROR(VLOOKUP(C5,IMPORTRANGE(""https://docs.google.com/spreadsheets/d/1RmEXtNg60OGvqZjyMxiYNPJ6S_kcz01v57qrHugDWVc/edit#gid=0"",""Chegadas!E:AQ""),19,0),"""")"),"") | U5: Encerrado | V5: Certificação INMETRO:Produto certificado por INNAC OCP 0061 Nº Registro 001343/2020 | W5: =N5 -> Certificado encerrado, validade do estoque do produto até 06/07/2023
A6: IMAGINARIUM | B6: =HYPERLINK("https://imagens.imgnet.com.br/f/imaginarium/"&C6&";"&C6,image("https://imagens.imgnet.com.br/f/imaginarium/"&C6&"))")) | C6: PI4074Y | D6: 2020 - FAT02 | E6: Remember | F6: MALETA DE MAQUIAGEM COM SPEAKER SHOW | G6: TECH | H6: ANATEL CATEGORIA 2 - MÓDULO BLUETOOTH | I6: 2 Amostras completas + 1 Amostra teste lab (Placa PCB com entradas de cabo de RF e Software) | J6: Finalizado | L6: Produto + Manual (ANATEL) | N6: Item não certificado | O6: Homologação ANATEL - Sem necessidade de Auditoria | P6: NA | Q6: NA | S6: FALSE | T6: =IFERROR(__xludf.DUMMYFUNCTION("IFERROR(VLOOKUP(C6,IMPORTRANGE(""https://docs.google.com/spreadsheets/d/1RmEXtNg60OGvqZjyMxiYNPJ6S_kcz01v57qrHugDWVc/edit#gid=0"",""Chegadas!E:AQ""),19,0),"""")"),"") | U6: Encerrado | V6: N/A | W6: =N6 -> Item não certificado
A7: IMAGINARIUM | B7: =HYPERLINK("https://imagens.imgnet.com.br/f/imaginarium/"&C7&";"&C7,image("https://imagens.imgnet.com.br/f/imaginarium/"&C7&"))")) | C7: PI4229Y | D7: 2020 - FAT03 | E7: BAITE | F7: COELHO DE PASCOA INFLAVEL | G7: CASA E DECORAÇÃO | H7: INMETRO SISTEMA 7 (LOTE) - PORTARIA 321 | I7: Aguardando RAM | J7: Finalizado | L7: Produto + Embalagem (INMETRO) | N7: Até o final do lote | O7: Novo desenvolvimento - Analise documental somente das informações de SAC - Sem necessidade de input da ASTEC até manutenção | P7: 5237-2019-BRI -1 | Q7: NA | R7: BRICS OCP 0098 | S7: FALSE | T7: =IFERROR(__xludf.DUMMYFUNCTION("IFERROR(VLOOKUP(C7,IMPORTRANGE(""https://docs.google.com/spreadsheets/d/1RmEXtNg60OGvqZjyMxiYNPJ6S_kcz01v57qrHugDWVc/edit#gid=0"",""Chegadas!E:AQ""),19,0),"""")"),"") | U7: Encerrado | V7: Certificação INMETRO:Produto certificado por BRICS OCP 0098 CE-BRI/BRICS 001180-20 | W7: =N7 -> Até o final do lote
A8: IMAGINARIUM | B8: =HYPERLINK("https://imagens.imgnet.com.br/f/imaginarium/"&C8&";"&C8,image("https://imagens.imgnet.com.br/f/imaginarium/"&C8&"))")) | C8: PI4127Y | D8: 2020 - FAT03 | E8: IPS | F8: MARMITA ELETRICA QUENTE VIU 127V | G8: COMES E BEBES | H8: INMETRO SISTEMA 5 (FABRICA) - PORTARIA 371 | I8: 2 Amostras completas | J8: Finalizado | L8: Produto + Embalagem (INMETRO) | N8: 43892 | P8: 5168/2019-ELE-1 | Q8: NA | R8: BRICS OCP 0098 | S8: TRUE | T8: =IFERROR(__xludf.DUMMYFUNCTION("IFERROR(VLOOKUP(C8,IMPORTRANGE(""https://docs.google.com/spreadsheets/d/1RmEXtNg60OGvqZjyMxiYNPJ6S_kcz01v57qrHugDWVc/edit#gid=0"",""Chegadas!E:AQ""),19,0),"""")"),"") | U8: Encerrado | V8: Certificação INMETRO:Produto certificado por BRICS OCP 0098 Nº Certificado 5168/2019-ELE-1 | W8: =N8 -> 43892
A9: IMAGINARIUM | B9: =HYPERLINK("https://imagens.imgnet.com.br/f/imaginarium/"&C9&";"&C9,image("https://imagens.imgnet.com.br/f/imaginarium/"&C9&"))")) | C9: PI4246Y | D9: 2020 - FAT03 | E9: IPS | F9: MARMITA ELETRICA QUENTE VIU 220V | G9: COMES E BEBES | H9: INMETRO SISTEMA 5 (FABRICA) - PORTARIA 371 | I9: 2 Amostras completas | J9: Finalizado | L9: Produto + Embalagem (INMETRO) | N9: 43892 | P9: 5168/2019-ELE-1 | Q9: NA | R9: BRICS OCP 0098 | S9: TRUE | T9: =IFERROR(__xludf.DUMMYFUNCTION("IFERROR(VLOOKUP(C9,IMPORTRANGE(""https://docs.google.com/spreadsheets/d/1RmEXtNg60OGvqZjyMxiYNPJ6S_kcz01v57qrHugDWVc/edit#gid=0"",""Chegadas!E:AQ""),19,0),"""")"),"") | U9: Encerrado | V9: Certificação INMETRO:Produto certificado por BRICS OCP 0098 Nº Certificado 5168/2019-ELE-1 | W9: =N9 -> 43892
A10: IMAGINARIUM | B10: =HYPERLINK("https://imagens.imgnet.com.br/f/imaginarium/"&C10&";"&C10,image("https://imagens.imgnet.com.br/f/imaginarium/"&C10&"))")) | C10: PI4183Y | D10: 2020 - FAT03 | E10: ED origin | F10: AROMATIZADOR SPEAKER MAE AMOR | G10: COMES E BEBES | H10: INMETRO SISTEMA 5 (FABRICA) - PORTARIA 371 + ANATEL MÓDULO BLUETOOTH | I10: 2 Amostras completas - INMETRO 2 Amostras completas + 1 Amostra teste lab (Placa PCB com entradas de cabo de RF e Software) - ANATEL | J10: Finalizado | L10: Produto + Embalagem + Manual (INMETRO & ANATEL) | N10: 44266 | P10: 5169-2019-ELE-1 | Q10: NA | R10: BRICS OCP 0098 | S10: TRUE | T10: =IFERROR(__xludf.DUMMYFUNCTION("IFERROR(VLOOKUP(C10,IMPORTRANGE(""https://docs.google.com/spreadsheets/d/1RmEXtNg60OGvqZjyMxiYNPJ6S_kcz01v57qrHugDWVc/edit#gid=0"",""Chegadas!E:AQ""),19,0),"""")"),"") | U10: Encerrado | V10: Certificação INMETRO:Produto certificado por BRICS OCP 0098 Nº Certificado 5169-2019-ELE | W10: =N10 -> 44266
A11: IMAGINARIUM | B11: =HYPERLINK("https://imagens.imgnet.com.br/f/imaginarium/"&C11&";"&C11,image("https://imagens.imgnet.com.br/f/imaginarium/"&C11&"))")) | C11: PI4129Y | D11: 2020 - FAT03 | E11: ED origin | F11: AROMATIZADOR SPEAKER MUSICA INSPIRA | G11: CASA E DECORAÇÃO | H11: INMETRO SISTEMA 5 (FABRICA) - PORTARIA 371 + ANATEL MÓDULO BLUETOOTH | I11: 2 Amostras completas - INMETRO 2 Amostras completas + 1 Amostra teste lab (Placa PCB com entradas de cabo de RF e Software) - ANATEL | J11: Finalizado | L11: Produto + Embalagem + Manual (INMETRO & ANATEL) | N11: 44266 | P11: 5169-2019-ELE-1 | Q11: NA | R11: BRICS OCP 0098 | S11: TRUE | T11: =IFERROR(__xludf.DUMMYFUNCTION("IFERROR(VLOOKUP(C11,IMPORTRANGE(""https://docs.google.com/spreadsheets/d/1RmEXtNg60OGvqZjyMxiYNPJ6S_kcz01v57qrHugDWVc/edit#gid=0"",""Chegadas!E:AQ""),19,0),"""")"),"") | U11: Encerrado | V11: Certificação INMETRO:Produto certificado por BRICS OCP 0098 Nº Certificado 5169-2019-ELE | W11: =N11 -> 44266
A12: IMAGINARIUM | B12: =HYPERLINK("https://imagens.imgnet.com.br/f/imaginarium/"&C12&";"&C12,image("https://imagens.imgnet.com.br/f/imaginarium/"&C12&"))")) | C12: PI4219Y | D12: 2020 - FAT04 | E12: TOYLAND | F12: ALMOFADA TE AMO ALIEN DO UNIVERSO | G12: CASA E DECORAÇÃO | H12: INMETRO SISTEMA 7 (LOTE) - PORTARIA 321 | I12: Aguardando RAM | J12: Certificado emitido | L12: Produto ou Embalagem (INMETRO) | N12: Até o final do lote | O12: Novo desenvolvimento - Analise documental somente das informações de SAC - Sem necessidade de input da ASTEC até manutenção | P12: 5269/2020-BRI-1 | Q12: NA | R12: BRICS OCP 0098 | S12: TRUE | T12: =IFERROR(__xludf.DUMMYFUNCTION("IFERROR(VLOOKUP(C12,IMPORTRANGE(""https://docs.google.com/spreadsheets/d/1RmEXtNg60OGvqZjyMxiYNPJ6S_kcz01v57qrHugDWVc/edit#gid=0"",""Chegadas!E:AQ""),19,0),"""")"),"") | U12: Encerrado | V12: Certificação INMETRO:Produto certificado por BRICS OCP 0098 CE-BRI/BRICS 001180-20 | W12: =N12 -> Até o final do lote
A13: IMAGINARIUM | B13: =HYPERLINK("https://imagens.imgnet.com.br/f/imaginarium/"&C13&";"&C13,image("https://imagens.imgnet.com.br/f/imaginarium/"&C13&"))")) | C13: PI4207Y | D13: 2021 - FAT06 | E13: ANC China | F13: LOCALIZADOR DE CHAVE PRETO | G13: TECH | H13: ANATEL CATEGORIA 2 - MÓDULO BLUETOOTH | I13: 2 Amostras completas + 1 Amostra teste lab (Placa PCB com entradas de cabo de RF e Software) | J13: 22/12 - Não teremos venda sell-in e nem recompra desses itens. Certificado não será renovado. - Finalizado | L13: Produto + Manual (ANATEL) | N13: 45021 | O13: Homologação ANATEL - Sem necessidade de Auditoria | P13: MT-5263/2021 | Q13: 03511-21-12855 | S13: FALSE | T13: =IFERROR(__xludf.DUMMYFUNCTION("IFERROR(VLOOKUP(C13,IMPORTRANGE(""https://docs.google.com/spreadsheets/d/1RmEXtNg60OGvqZjyMxiYNPJ6S_kcz01v57qrHugDWVc/edit#gid=0"",""Chegadas!E:AQ""),19,0),"""")"),"") | U13: Encerrado | V13: Produto homologado pela Anatel: Nº Homologação 03511-21-12855 | W13: =N13 -> 45021
A14: IMAGINARIUM | B14: =HYPERLINK("https://imagens.imgnet.com.br/f/imaginarium/"&C14&";"&C14,image("https://imagens.imgnet.com.br/f/imaginarium/"&C14&"))")) | C14: PI4257Y | D14: 2020 - FAT04 | E14: Donghao | F14: KARAOKE PORTATIL FAZ AO VIVO | G14: TECH | H14: ANATEL CATEGORIA 2 - MÓDULO BLUETOOTH | I14: 2 Amostras completas + 1 Amostra teste lab (Placa PCB com entradas de cabo de RF e Software) | J14: Finalizado | L14: Produto + Manual (ANATEL) | N14: 44247 | O14: Homologação ANATEL - Sem necessidade de Auditoria | P14: NA | Q14: NA | S14: FALSE | T14: =IFERROR(__xludf.DUMMYFUNCTION("IFERROR(VLOOKUP(C14,IMPORTRANGE(""https://docs.google.com/spreadsheets/d/1RmEXtNg60OGvqZjyMxiYNPJ6S_kcz01v57qrHugDWVc/edit#gid=0"",""Chegadas!E:AQ""),19,0),"""")"),"") | U14: Encerrado | V14: N/A | W14: =N14 -> 44247
A15: IMAGINARIUM | B15: =HYPERLINK("https://imagens.imgnet.com.br/f/imaginarium/"&C15&";"&C15,image("https://imagens.imgnet.com.br/f/imaginarium/"&C15&"))")) | C15: PI4217Y | D15: 2020 - FAT04 | E15: Hesen | F15: KIT PIPOCA DUPLO SERIE KILLER | G15: COMES E BEBES | H15: INMETRO SISTEMA 5 (FABRICA) - PORTARIA 563 | I15: Aguardando RAM | J15: Finalizado | L15: Produto + Embalagem (INMETRO) | N15: 44050 | O15: 44020 | P15: IPI-BRI-9951-2019-05 | Q15: 002937/2020 | S15: TRUE | T15: =IFERROR(__xludf.DUMMYFUNCTION("IFERROR(VLOOKUP(C15,IMPORTRANGE(""https://docs.google.com/spreadsheets/d/1RmEXtNg60OGvqZjyMxiYNPJ6S_kcz01v57qrHugDWVc/edit#gid=0"",""Chegadas!E:AQ""),19,0),"""")"),"") | U15: Encerrado | V15: Certificação INMETRO:Produto certificado por INNAC OCP 0061 Nº Registro 002937/2020 | W15: =N15 -> 44050
A16: IMAGINARIUM | B16: =HYPERLINK("https://imagens.imgnet.com.br/f/imaginarium/"&C16&";"&C16,image("https://imagens.imgnet.com.br/f/imaginarium/"&C16&"))")) | C16: PI4255Y | D16: 2020 - FAT04 | E16: Sun Lin | F16: PIANO GIGANTE DO RE MI | G16: CASA E DECORAÇÃO | H16: INMETRO SISTEMA 7 (LOTE) - PORTARIA 321 | I16: Aguardando RAM | J16: Certificado emitido | L16: Produto + Embalagem (INMETRO) | N16: Até o final do lote | O16: Novo desenvolvimento - Analise documental somente das informações de SAC - Sem necessidade de input da ASTEC até manutenção | P16: 5236-2019-BRI-1 | Q16: NA | R16: BRICS OCP 0098 | S16: FALSE | T16: =IFERROR(__xludf.DUMMYFUNCTION("IFERROR(VLOOKUP(C16,IMPORTRANGE(""https://docs.google.com/spreadsheets/d/1RmEXtNg60OGvqZjyMxiYNPJ6S_kcz01v57qrHugDWVc/edit#gid=0"",""Chegadas!E:AQ""),19,0),"""")"),"") | U16: Encerrado | V16: Certificação INMETRO:Produto certificado por BRICS OCP 0098 CE-BRI/BRICS 001180-20 | W16: =N16 -> Até o final do lote
A17: IMAGINARIUM | B17: =HYPERLINK("https://imagens.imgnet.com.br/f/imaginarium/"&C17&";"&C17,image("https://imagens.imgnet.com.br/f/imaginarium/"&C17&"))")) | C17: PI4193Y | D17: 2020 - FAT04 | E17: Robotime | F17: QUEBRA CABEÇA 3D DINOSSAURO ROBO | G17: CASA E DECORAÇÃO | H17: INMETRO SISTEMA 7 (LOTE) - PORTARIA 321 | I17: Aguardando RAM | J17: Certificado emitido | L17: Produto + Embalagem (INMETRO) | N17: Até o final do lote | O17: Novo desenvolvimento - Analise documental somente das informações de SAC - Sem necessidade de input da ASTEC até manutenção | P17: 5238/2019-BRI-1 | Q17: NA | R17: BRICS OCP 0098 | S17: FALSE | T17: =IFERROR(__xludf.DUMMYFUNCTION("IFERROR(VLOOKUP(C17,IMPORTRANGE(""https://docs.google.com/spreadsheets/d/1RmEXtNg60OGvqZjyMxiYNPJ6S_kcz01v57qrHugDWVc/edit#gid=0"",""Chegadas!E:AQ""),19,0),"""")"),"") | U17: Encerrado | V17: Certificação INMETRO:Produto certificado por BRICS OCP 0098 CE-BRI/BRICS 001180-20 | W17: =N17 -> Até o final do lote
A18: IMAGINARIUM | C18: LY2877 | D18: 2020 - FAT04 | E18: Hesen | F18: ALMOFADA MANIA URSO VALENTIM ME LEVA | G18: CASA E DECORAÇÃO | H18: INMETRO SISTEMA 7 (LOTE) - PORTARIA 321 | I18: 18 Amostras | J18: Certificado emitido, já destinado ao CD | L18: Embalagem (INMETRO) | N18: Até o final do lote | O18: Novo desenvolvimento - Analise documental somente das informações de SAC - Sem necessidade de input da ASTEC até manutenção | P18: 5450-2020-BRI-1 | Q18: NA | R18: BRICS OCP 0098 | S18: TRUE | T18: =IFERROR(__xludf.DUMMYFUNCTION("IFERROR(VLOOKUP(C18,IMPORTRANGE(""https://docs.google.com/spreadsheets/d/1RmEXtNg60OGvqZjyMxiYNPJ6S_kcz01v57qrHugDWVc/edit#gid=0"",""Chegadas!E:AQ""),19,0),"""")"),"") | U18: Encerrado | V18: LUDI | W18: =N18 -> Até o final do lote
A19: IMAGINARIUM | B19: =HYPERLINK("https://imagens.imgnet.com.br/f/imaginarium/"&C19&";"&C19,image("https://imagens.imgnet.com.br/f/imaginarium/"&C19&"))")) | C19: PI4220Y | D19: 2020 - FAT04 | E19: Hesen | F19: ALMOFADA SARDADINHA DE VOCE | G19: CASA E DECORAÇÃO | H19: INMETRO SISTEMA 5 (FABRICA) - PORTARIA 563 | I19: Já separadas | J19: Finalizado | L19: Produto + Embalagem (INMETRO) | N19: Até o final do lote | O19: Novo desenvolvimento - Analise documental somente das informações de SAC - Sem necessidade de input da ASTEC até manutenção | P19: 5617/2020-BRI-1 | Q19: NA | R19: BRICS OCP 0098 | S19: TRUE | T19: =IFERROR(__xludf.DUMMYFUNCTION("IFERROR(VLOOKUP(C19,IMPORTRANGE(""https://docs.google.com/spreadsheets/d/1RmEXtNg60OGvqZjyMxiYNPJ6S_kcz01v57qrHugDWVc/edit#gid=0"",""Chegadas!E:AQ""),19,0),"""")"),"") | U19: Encerrado | V19: Certificação INMETRO:Produto certificado por BRICS OCP 0098 CE-BRI/BRICS 001180-20 | W19: =N19 -> Até o final do lote
A20: IMAGINARIUM | B20: =HYPERLINK("https://imagens.imgnet.com.br/f/imaginarium/"&C20&";"&C20,image("https://imagens.imgnet.com.br/f/imaginarium/"&C20&"))")) | C20: PI4306Y | D20: 2020 - FAT06 | E20: Yopinshi | F20: KIT ACESSORIOS TECH JUNTO E CONECTADO | G20: TECH | H20: ANATEL CATEGORIA 1 - CELULARES | I20: 2 Amostras completas + 1 Amostra teste lab (Placa PCB com entradas de cabo de RF e Software) | J20: Finalizado | L20: Produto (ANATEL) | N20: 44370 | O20: Homologação ANATEL - Sem necessidade de Auditoria | P20: NA | Q20: NA | S20: TRUE | T20: =IFERROR(__xludf.DUMMYFUNCTION("IFERROR(VLOOKUP(C20,IMPORTRANGE(""https://docs.google.com/spreadsheets/d/1RmEXtNg60OGvqZjyMxiYNPJ6S_kcz01v57qrHugDWVc/edit#gid=0"",""Chegadas!E:AQ""),19,0),"""")"),"") | U20: Encerrado | V20: NA | W20: =N20 -> 44370
A21: IMAGINARIUM | B21: =HYPERLINK("https://imagens.imgnet.com.br/f/imaginarium/"&C21&";"&C21,image("https://imagens.imgnet.com.br/f/imaginarium/"&C21&"))")) | C21: PI4214Y | D21: 2020 - FAT04 | E21: Chuyang | F21: ORGANIZADOR E CARREGADOR SEM FIO CORTICA | G21: TECH | H21: ANATEL CATEGORIA 1 - CELULARES | I21: 2 Amostras completas + 1 Amostra teste lab (Placa PCB com entradas de cabo de RF e Software) | J21: Finalizado | L21: Produto + Manual (ANATEL) | N21: Item não certificado | O21: Homologação ANATEL - Sem necessidade de Auditoria | P21: NA | Q21: NA | S21: TRUE | T21: =IFERROR(__xludf.DUMMYFUNCTION("IFERROR(VLOOKUP(C21,IMPORTRANGE(""https://docs.google.com/spreadsheets/d/1RmEXtNg60OGvqZjyMxiYNPJ6S_kcz01v57qrHugDWVc/edit#gid=0"",""Chegadas!E:AQ""),19,0),"""")"),"") | U21: Encerrado | V21: N/A | W21: =N21 -> Item não certificado
A22: IMAGINARIUM | B22: =HYPERLINK("https://imagens.imgnet.com.br/f/imaginarium/"&C22&";"&C22,image("https://imagens.imgnet.com.br/f/imaginarium/"&C22&"))")) | C22: PI4308Y | D22: 2020 - FAT06 | E22: Huazeng | F22: LUMINARIA SPEAKER BUD | G22: TECH | H22: ANATEL CATEGORIA 2 - MÓDULO BLUETOOTH | I22: 2 Amostras completas + 1 Amostra teste lab (Placa PCB com entradas de cabo de RF e Software) | J22: Certificado Emitido Registro: 07231-20-12851 Criação já alinhou a aplicação das artes | L22: Produto + Manual (ANATEL) | N22: Item não certificado | O22: Homologação ANATEL - Sem necessidade de Auditoria | P22: NA | Q22: NA | S22: FALSE | T22: =IFERROR(__xludf.DUMMYFUNCTION("IFERROR(VLOOKUP(C22,IMPORTRANGE(""https://docs.google.com/spreadsheets/d/1RmEXtNg60OGvqZjyMxiYNPJ6S_kcz01v57qrHugDWVc/edit#gid=0"",""Chegadas!E:AQ""),19,0),"""")"),"") | U22: Encerrado | V22: N/A | W22: =N22 -> Item não certificado
A23: IMAGINARIUM | B23: =HYPERLINK("https://imagens.imgnet.com.br/f/imaginarium/"&C23&";"&C23,image("https://imagens.imgnet.com.br/f/imaginarium/"&C23&"))")) | C23: PI4259Y | D23: 2020 - FAT05 | E23: Hangzhou Shouyi I/E CO,,LTD | F23: CESTA DE BASQUETE COM LED JOGADA CERTA | G23: CASA E DECORAÇÃO | H23: INMETRO SISTEMA 7 (LOTE) - PORTARIA 321 | I23: 10 Amostras Completas | J23: Certificado recebido e anûencia deferida, processo de certificação finalizado. | L23: Embalagem (INMETRO) | N23: Até o final do lote | O23: Sem necessidade - Certificação de Lote | P23: 5637-2020-BRI-1 | Q23: NA | R23: BRICS OCP 0098 | S23: FALSE | T23: =IFERROR(__xludf.DUMMYFUNCTION("IFERROR(VLOOKUP(C23,IMPORTRANGE(""https://docs.google.com/spreadsheets/d/1RmEXtNg60OGvqZjyMxiYNPJ6S_kcz01v57qrHugDWVc/edit#gid=0"",""Chegadas!E:AQ""),19,0),"""")"),"") | U23: Encerrado | V23: Certificação INMETRO:Produto certificado por BRICS OCP 0098 CE-BRI/BRICS 001180-20 | W23: =N23 -> Até o final do lote
A24: IMAGINARIUM | B24: =HYPERLINK("https://imagens.imgnet.com.br/f/imaginarium/"&C24&";"&C24,image("https://imagens.imgnet.com.br/f/imaginarium/"&C24&"))")) | C24: PI4586Y | D24: 2020 - FAT10 | E24: Universe Sound | F24: FONE DE OUVIDO SEM FIO ESCUTA AQUI | G24: TECH | H24: ANATEL CATEGORIA 2 - MÓDULO BLUETOOTH | I24: 1 Amostras completas + 1 Amostra teste lab (Placa PCB com entradas de cabo de RF e Software) | J24: 01/06/2023 - Certificado suspenso. - Amostras enviadas para o laboratório (Eldorado) em 17/06, finalizando pendências documentais com o certificador para obtermos o número de registro ANATEL que deve conter no produto. Ensaios finalizados Registro emitido:08894-20-12418 | L24: Produto + Manual (ANATEL) | N24: 45077 | O24: =N24-90 -> 44987 | P24: MT-5347/2021 | Q24: 06109-21-12418 | S24: TRUE | T24: =IFERROR(__xludf.DUMMYFUNCTION("IFERROR(VLOOKUP(C24,IMPORTRANGE(""https://docs.google.com/spreadsheets/d/1RmEXtNg60OGvqZjyMxiYNPJ6S_kcz01v57qrHugDWVc/edit#gid=0"",""Chegadas!E:AQ""),19,0),"""")"),"") | U24: Encerrado | V24: Produto homologado pela Anatel: Nº Homologação 06109-21-12418 | W24: =N24 -> 45077
A25: IMAGINARIUM | B25: =HYPERLINK("https://imagens.imgnet.com.br/f/imaginarium/"&C25&";"&C25,image("https://imagens.imgnet.com.br/f/imaginarium/"&C25&"))")) | C25: PI4587Y | D25: 2020 - FAT10 | E25: Universe Sound | F25: FONE DE OUVIDO SEM FIO OUVIR | G25: TECH | H25: ANATEL CATEGORIA 2 - MÓDULO BLUETOOTH | I25: 1 Amostras completas + 1 Amostra teste lab (Placa PCB com entradas de cabo de RF e Software) | J25: 01/06/2023 - Certificado suspenso. - Amostras enviadas para o laboratório (Eldorado) em 17/06, finalizando pendências documentais com o certificador para obtermos o número de registro ANATEL que deve conter no produto. Ensaios finalizados Registro emitido:08894-20-12418 | L25: Produto + Manual (ANATEL) | N25: 45077 | O25: =N25-90 -> 44987 | P25: MT-5347/2021 | Q25: 06109-21-12418 | S25: TRUE | T25: =IFERROR(__xludf.DUMMYFUNCTION("IFERROR(VLOOKUP(C25,IMPORTRANGE(""https://docs.google.com/spreadsheets/d/1RmEXtNg60OGvqZjyMxiYNPJ6S_kcz01v57qrHugDWVc/edit#gid=0"",""Chegadas!E:AQ""),19,0),"""")"),"") | U25: Encerrado | V25: Produto homologado pela Anatel: Nº Homologação 06109-21-12418 | W25: =N25 -> 45077
A26: IMAGINARIUM | B26: =HYPERLINK("https://imagens.imgnet.com.br/f/imaginarium/"&C26&";"&C26,image("https://imagens.imgnet.com.br/f/imaginarium/"&C26&"))")) | C26: PI4511Y | D26: 2022 - FAT05 | E26: Joy rain | F26: CANETA MUDA FRASES HP FEITICOS | G26: USO PESSOAL | H26: INMETRO SISTEMA 5 (FABRICA) - PORTARIA 481 | I26: 50 Amostras | J26: 23/04/2025 - Manutenção finalizada. 03/06/24 - Manutenção concluída. Retrabalho das canetas concluído. | K26: 45770 | L26: Embalagem (INMETRO) | N26: 46153 | O26: =N26-90 -> 46063 | P26: 9114/2023-AE-1 | Q26: 004671/2023 | R26: BRICS OCP 0098 | S26: TRUE | T26: =IFERROR(__xludf.DUMMYFUNCTION("IFERROR(VLOOKUP(C26,IMPORTRANGE(""https://docs.google.com/spreadsheets/d/1RmEXtNg60OGvqZjyMxiYNPJ6S_kcz01v57qrHugDWVc/edit#gid=0"",""Chegadas!E:AQ""),19,0),"""")"),44686.0) -> 44686 | U26: Ativo | V26: Certificação INMETRO:Produto certificado por BRICS OCP 0098 Nº Registro 004671/2023 | W26: =IFERROR(IF(U26="Ativo","Ativo",IF(U26="SKU excluído","Vencido",VLOOKUP(C26,Encerramentos!B:G,6,0))),"") -> Ativo
A27: IMAGINARIUM | B27: =HYPERLINK("https://imagens.imgnet.com.br/f/imaginarium/"&C27&";"&C27,image("https://imagens.imgnet.com.br/f/imaginarium/"&C27&"))")) | C27: PI4499Y | D27: 2020 - FAT09 | E27: Joy rain | F27: CANETA MUDA FRASES FRIENDS MOLDURA | G27: USO PESSOAL | H27: INMETRO SISTEMA 5 (FABRICA) - PORTARIA 481 | I27: 0 Amostras, (amostras da caneta HP foram ensaiadas no processo) | J27: 21/08/23 - Certificado encerrado. - Retrabalho das Canetas concluído em 23/11 | L27: Embalagem (INMETRO) | N27: 45788 | O27: =N27-90 -> 45698 | P27: 5605/2020-AE-1 | Q27: 006550/2020 | R27: BRICS OCP 0098 | S27: TRUE | T27: =IFERROR(__xludf.DUMMYFUNCTION("IFERROR(VLOOKUP(C27,IMPORTRANGE(""https://docs.google.com/spreadsheets/d/1RmEXtNg60OGvqZjyMxiYNPJ6S_kcz01v57qrHugDWVc/edit#gid=0"",""Chegadas!E:AQ""),19,0),"""")"),"") | U27: Encerrado | V27: Certificação INMETRO:Produto certificado por BRICS OCP 0098 Nº Registro 006550/2020 | W27: =N27 -> 45788
A28: IMAGINARIUM | B28: =HYPERLINK("https://imagens.imgnet.com.br/f/imaginarium/"&C28&";"&C28,image("https://imagens.imgnet.com.br/f/imaginarium/"&C28&"))")) | C28: PI4628Y | D28: 2021 - FAT01 | E28: AUBADI | F28: MOUSE SEM FIO GLITTER DEIXAR ROLAR | G28: USO PESSOAL | H28: ANATEL CATEGORIA 2 - MÓDULO BLUETOOTH | I28: 1 Amostras completas + 1 Amostra teste lab (Placa PCB com entradas de cabo de RF e Software) | J28: 21/05 - Homologação Anatel finalizada. 23/04 - Processo cadastrado na Anatel. 12/04 - Em análise pela engenharia da OCD - previsão 16/05 24/03 - Entrega dos relatórios prevista para 12/04 e finalização homologação 16/05. Amostras chegaram no laboratório em 17/09. Nº de Registro já recebido e encaminhado para fornecedor incluir no produto 14600-20-13387 | L28: Produto + Manual (ANATEL) | N28: 45038 | O28: =N28-90 -> 44948 | P28: MT-5057/2020 | Q28: 14600-20-13387 | S28: FALSE | T28: =IFERROR(__xludf.DUMMYFUNCTION("IFERROR(VLOOKUP(C28,IMPORTRANGE(""https://docs.google.com/spreadsheets/d/1RmEXtNg60OGvqZjyMxiYNPJ6S_kcz01v57qrHugDWVc/edit#gid=0"",""Chegadas!E:AQ""),19,0),"""")"),"") | U28: Encerrado | V28: Produto homologado pela Anatel: Nº Homologação 14600-20-13387 | W28: =N28 -> 45038
A29: IMAGINARIUM | B29: =HYPERLINK("https://imagens.imgnet.com.br/f/imaginarium/"&C29&";"&C29,image("https://imagens.imgnet.com.br/f/imaginarium/"&C29&"))")) | C29: PI4630Y | D29: 2021 - FAT01 | E29: AUBADI | F29: MOUSE SEM FIO GLITTER AMEI | G29: USO PESSOAL | H29: ANATEL CATEGORIA 2 - MÓDULO BLUETOOTH | I29: 1 Amostras completas + 1 Amostra teste lab (Placa PCB com entradas de cabo de RF e Software) | J29: 21/05 - Homologação Anatel finalizada. 23/04 - Processo cadastrado na Anatel. 12/04 - Em análise pela engenharia da OCD - previsão 16/05 24/03 - Entrega dos relatórios prevista para 12/04 e finalização homologação 16/05. Amostras chegaram no laboratório em 17/09. Nº de Registro já recebido e encaminhado para fornecedor incluir no produto 14600-20-13387 | L29: Produto + Manual (ANATEL) | N29: 45038 | O29: =N29-90 -> 44948 | P29: MT-5057/2020 | Q29: 14600-20-13387 | S29: FALSE | T29: =IFERROR(__xludf.DUMMYFUNCTION("IFERROR(VLOOKUP(C29,IMPORTRANGE(""https://docs.google.com/spreadsheets/d/1RmEXtNg60OGvqZjyMxiYNPJ6S_kcz01v57qrHugDWVc/edit#gid=0"",""Chegadas!E:AQ""),19,0),"""")"),"") | U29: Encerrado | V29: Produto homologado pela Anatel: Nº Homologação 14600-20-13387 | W29: =N29 -> 45038
A30: IMAGINARIUM | B30: =HYPERLINK("https://imagens.imgnet.com.br/f/imaginarium/"&C30&";"&C30,image("https://imagens.imgnet.com.br/f/imaginarium/"&C30&"))")) | C30: PI1172Y PI1183Y PI3716Y | D30: 2021 - FAT01 | E30: NIHAO | F30: Nihao Familia 1 - Manutenção dos produtos | G30: USO PESSOAL | H30: INMETRO SISTEMA 5 (FABRICA) - PORTARIA 481 | I30: Aguardando RAM | J30: Transfererência do Certificado do INNAC para a Brics concluída, avançando para envio das amostras para teste LI Prévia deferida pelo INMETRO | L30: Embalagem (INMETRO) | N30: 44231 | O30: 44025 | P30: 000910/2015 | Q30: IP-AESC-3847/2019-01 IP-AESC-3847/2019-02 | S30: TRUE | T30: =IFERROR(__xludf.DUMMYFUNCTION("IFERROR(VLOOKUP(C30,IMPORTRANGE(""https://docs.google.com/spreadsheets/d/1RmEXtNg60OGvqZjyMxiYNPJ6S_kcz01v57qrHugDWVc/edit#gid=0"",""Chegadas!E:AQ""),19,0),"""")"),"") | U30: Encerrado | W30: =N30 -> 44231
A31: IMAGINARIUM | B31: =HYPERLINK("https://imagens.imgnet.com.br/f/imaginarium/"&C31&";"&C31,image("https://imagens.imgnet.com.br/f/imaginarium/"&C31&"))")) | C31: PI4642Y | D31: 2021 - FAT01 | E31: JYK | F31: VITROLA DE MALA BLUETOOTH AMARELA | G31: TECH | H31: ANATEL CATEGORIA 2 - MÓDULO BLUETOOTH | I31: 1 Amostras completas + 1 Amostra teste lab (Placa PCB com entradas de cabo de RF e Software) | J31: 10/01/23 - Planejamento informou que não deseja renovar o certificado. - Amostra chegou em 28/09 em SP, foi enviada para ensaios laboratoriais em 30/09. Número de registro recebido em 29/10. ANATEL: 15743-20-13462 | L31: Produto + Manual (ANATEL) | N31: 45007 | O31: =N31-90 -> 44917 | P31: MT-5084/2020 | Q31: 15743-20-13462 | S31: TRUE | T31: =IFERROR(__xludf.DUMMYFUNCTION("IFERROR(VLOOKUP(C31,IMPORTRANGE(""https://docs.google.com/spreadsheets/d/1RmEXtNg60OGvqZjyMxiYNPJ6S_kcz01v57qrHugDWVc/edit#gid=0"",""Chegadas!E:AQ""),19,0),"""")"),"") | U31: Encerrado | V31: Este produto contém a placa ST226A código de homologação ANATEL 15743-20-13462 | W31: =N31 -> 45007
A32: IMAGINARIUM | B32: =HYPERLINK("https://imagens.imgnet.com.br/f/imaginarium/"&C32&";"&C32,image("https://imagens.imgnet.com.br/f/imaginarium/"&C32&"))")) | C32: PI4669Y | D32: 2021 - FAT10 | E32: Wallesun | F32: AROMATIZADOR E UMIDIFICADOR NO AR | G32: CASA E DECORAÇÃO | H32: INMETRO Eletrodomésticos | I32: 2 amostras para ensaios na China | J32: Documentação recebida e encaminhada para análise do OCP. Aguardando confirmação do laboratório para envio das amostras e confirmação do OCP quanto a etiqueta de Certificação para alinhamento com o time de criação. Amostras Chegaram no FEDEX 772035901130 Aprovação da Etiqueta concedida pelo OCP. Relatório preliminar do laboratório agendado para dia 18/12. Tipo de certificação alterada para Lote em função do fornecedor não conseguir cumprir com os requisitos minímos cobrados pelo laboratório. Embarque será agendado após a conclusão dos ensaios preliminares. Ensaios preliminares concluídos e instrução de embarque encaminhada para o time da China Previsão da emissão do certificado 22/01 21/01 - Recebemos o Draft do Certificado e demos ok para emissão, devemos receber o certificado assinado amanhã dia 22/01 28/01 - Certificado emitido. Processo liberado pela RFB. | L32: Produto + Embalagem (INMETRO) | N32: Até o final do lote | O32: Sem auditoria - lote | P32: 6926/2021-ELE-1 | Q32: N/A | R32: BRICS OCP 0098 | S32: FALSE | T32: =IFERROR(__xludf.DUMMYFUNCTION("IFERROR(VLOOKUP(C32,IMPORTRANGE(""https://docs.google.com/spreadsheets/d/1RmEXtNg60OGvqZjyMxiYNPJ6S_kcz01v57qrHugDWVc/edit#gid=0"",""Chegadas!E:AQ""),19,0),"""")"),44474.0) -> 44474 | U32: Encerrado | V32: Certificação INMETRO:Produto certificado por BRICS OCP 0098 Nº Certificado 6356/2020-ELE | W32: =N32 -> Até o final do lote
A33: IMAGINARIUM | B33: =HYPERLINK("https://imagens.imgnet.com.br/f/imaginarium/"&C33&";"&C33,image("https://imagens.imgnet.com.br/f/imaginarium/"&C33&"))")) | C33: PI4732Y | D33: 2021 - FAT03 | E33: Iceberg | F33: MINI GELADEIRA PARA COSMETICOS LILAS | G33: TECH | H33: INMETRO Eletrodomésticos | I33: 2 amostras para ensaios na China | J33: 10/11 - Certificado encerrado: Informado pela empresa que o prazo para que estes produtos sejam comercializados é de 15 meses contados da data de 10/11/2021, para Cooler Elétrico modelo PI4732Y possui 461 unidades em estoque . -- 05/02 - Certificado emitido - validade: 04/02/2024. etiquetagem ok Documentação recebida e encaminhada para análise do OCP. Aguardando confirmação do laboratório para envio das amostras e confirmação do OCP quanto a etiqueta de Certificação para alinhamento com o time de criação Aprovação da Etiqueta concedida pelo OCP. Ensaios com previsão de término em 04/01, produção em massa irá seguir após a conclusão dos ensaios. Draft de Ensaios recebido em 06/01 e aprovados na mesma data, aguardando finalização da análise pelo time técnico do OCP para confirmamos a conformidade dos ensaios e seguir com a produção do produto. 08/01 - Recebemos a confirmação dos ensaios e o relatório final já seguiu para emissão, asim que tivermos o mesmo vamos seguir para obter o Certificado de Conformidade 20/01 - Validação de documentos realizada, aguardando envio do draft do certificado. 26/01 - Certificado cobrado novamente 03/02 - Draft do Certificado recebido 04/02 - Draft aprovado. | L33: Produto + Embalagem (INMETRO) | N33: 44597 | O33: =N33-90 -> 44507 | P33: 6364/2020-ELE-1 | Q33: N/A | R33: BRICS OCP 0098 | S33: TRUE | T33: =IFERROR(__xludf.DUMMYFUNCTION("IFERROR(VLOOKUP(C33,IMPORTRANGE(""https://docs.google.com/spreadsheets/d/1RmEXtNg60OGvqZjyMxiYNPJ6S_kcz01v57qrHugDWVc/edit#gid=0"",""Chegadas!E:AQ""),19,0),"""")"),"") | U33: Encerrado | V33: Certificação INMETRO:Produto certificado por BRICS OCP 0098 Nº Certificado 6364/2020-ELE-1 | W33: =N33 -> 44597
A34: IMAGINARIUM | B34: =HYPERLINK("https://imagens.imgnet.com.br/f/imaginarium/"&C34&";"&C34,image("https://imagens.imgnet.com.br/f/imaginarium/"&C34&"))")) | C34: PI4368Y | D34: 2020 - FAT08 | E34: Hesen | F34: ALMOFADA SONORA HP CHAPEU SELETOR | G34: CASA E DECORAÇÃO | H34: INMETRO SISTEMA 7 (LOTE) - PORTARIA 321 | I34: Amostras enviadas para laboratório, aguardando finalização dos ensaios laboratoriais | J34: 09/03 - Certificado emitido. Aguardando estar disponível no Orquestra para anuência da LI (10 dias - 30/03, chega dia 02/04 no Brasil). Novo processo de certificação de lote, já aberto com a Brics Certificações, data de conclusão da produção em massa solicitada para a China para averiguarmos a data para amostragem das peças a serem ensaiadas 11/01 - Confirmação da conclusão da Mass Production em 29/01, verificar se é possível pegar amostras do lote antes, quantas deverão ser produzidas, e qual a data de embarque para ver se o prazo está de acordo 21/01 - Combinado com o OCP a coleta antecipada, aguardando retorno da antecipação de amostras. Embarque agendado para o dia 06/02 no processo 1739_SH 05/02 - Amostra coletada, já está no Cobo. Proposta ensaio aprovada. Previsão de relatório 26/02. | L34: Produto + Embalagem (INMETRO) | N34: Até o final do lote | O34: Sem auditoria - lote | P34: 6544/2021-BRI | Q34: N/A | R34: BRICS OCP 0098 | S34: TRUE | T34: =IFERROR(__xludf.DUMMYFUNCTION("IFERROR(VLOOKUP(C34,IMPORTRANGE(""https://docs.google.com/spreadsheets/d/1RmEXtNg60OGvqZjyMxiYNPJ6S_kcz01v57qrHugDWVc/edit#gid=0"",""Chegadas!E:AQ""),19,0),"""")"),"") | U34: Encerrado | V34: Certificação INMETRO:Produto certificado por BRICS OCP 0098 CE-BRI/BRICS 001180-20 | W34: =N34 -> Até o final do lote
A35: IMAGINARIUM | B35: =HYPERLINK("https://imagens.imgnet.com.br/f/imaginarium/"&C35&";"&C35,image("https://imagens.imgnet.com.br/f/imaginarium/"&C35&"))")) | C35: PI4461Y | D35: 2020 - FAT08 | E35: KYC | F35: CARREGADOR SEM FIO HP PLATAFORMA 9 3/4 | G35: TECH | H35: ANATEL CATEGORIA 1 - CELULARES | I35: 2 Amostras completas | J35: 27/10/23 - O certificado não será renovado. 07/03/22 - Manutenção do Certificado realizada. -- 12/03 - Certificado de homologação emitido pela ANATEL. Precisamos etiquetar 10 unidades deste lote. Documentos submetidos para a ANATEL. Previsão homologação repassada pela OCP: 15/03. Recompra de produto, solicitação de compras de etiquetas realizada, previsão de envio para 28/12. Assim que recebidas serão encaminhadas via FedEx para time na China. Código de homologação emitido: 09318-20-12562 - Compra das etiquetas realizadas e recebidas pelo Guilherme em 04/01/2021, encaminhadas para China via FedEx em 05/01/2021 - Tracking: 772527892413 12/01 - Confirmação de FAT 04 recebida | L35: Produto + Manual (ANATEL) | M35: Shenzhen Kaiyue Century Techonology Co. LTD | N35: 45355 | O35: =N35-90 -> 45265 | P35: MT-4968/2020 | Q35: 09318-20-12562 | S35: TRUE | T35: =IFERROR(__xludf.DUMMYFUNCTION("IFERROR(VLOOKUP(C35,IMPORTRANGE(""https://docs.google.com/spreadsheets/d/1RmEXtNg60OGvqZjyMxiYNPJ6S_kcz01v57qrHugDWVc/edit#gid=0"",""Chegadas!E:AQ""),19,0),"""")"),44474.0) -> 44474 | U35: Encerrado | V35: Produto homologado pela Anatel: Nº Homologação 09318-20-1256 | W35: =N35 -> 45355
A36: IMAGINARIUM | B36: =HYPERLINK("https://imagens.imgnet.com.br/f/imaginarium/"&C36&";"&C36,image("https://imagens.imgnet.com.br/f/imaginarium/"&C36&"))")) | C36: PI4717Y | D36: 2021 - FAT03 | E36: Pic value | F36: CESTA DE PICNIC COM AMPLIFICADOR CESTOU | G36: TECH | H36: ANATEL MÓDULO BLUETOOTH | I36: 2 Amostras completas + 1 Amostra teste lab (Placa PCB com entradas de cabo de RF e Software) | J36: 10/01/23 - Certificado não será renovado. - 19/05 - Homologação finalizada. 07/05 - Processo cadastrado na Anatel. 07/04 - Nova amostra está no laboratório, entrega dos relatórios prevista para 28/04 e finalização homologação 30/05. Nova amostra enviada por Fedex tracking number: 773271403014 - nova data de finalização estimada 30/05 17/03 - Cobramos novamente a equipe da China resposta sobre o firmware. Os testes estão marcados para 22/03, entrega laudos 26/03 e homologação prevista para estar ok em 01/05. Amostra retirada do Laboratório, está na Eagle Tech para configuração. Previsão de finalização de relatórios dos testes: 26/03 e homologação: 01/05. Documentos recebidos, encaminhados para o OCD confirmar se podemos reutilizar o módulo anterior. Confirmação recebida, poderemos reutilizar o código ANATEL 05882-19-04646 | L36: Produto + Manual (ANATEL) | N36: 45052 | O36: =N36-90 -> 44962 | P36: MT-5258/2021 | Q36: 03460-21-13781 | S36: FALSE | T36: =IFERROR(__xludf.DUMMYFUNCTION("IFERROR(VLOOKUP(C36,IMPORTRANGE(""https://docs.google.com/spreadsheets/d/1RmEXtNg60OGvqZjyMxiYNPJ6S_kcz01v57qrHugDWVc/edit#gid=0"",""Chegadas!E:AQ""),19,0),"""")"),"") | U36: Encerrado | V36: Este produto contém a placa SL-272 código de homologação ANATEL 03460-21-13781 | W36: =N36 -> 45052
A37: IMAGINARIUM | B37: =HYPERLINK("https://imagens.imgnet.com.br/f/imaginarium/"&C37&";"&C37,image("https://imagens.imgnet.com.br/f/imaginarium/"&C37&"))")) | C37: PI4225Y | D37: 2021 - FAT04 | E37: Wantong | F37: FONDUE ELETRICO COM JOGO VAI ESQUENTAR | G37: COMES E BEBES | H37: INMETRO Eletrodomésticos | I37: 2 amostras para ensaios no Brasil | J37: Seguindo com o encerramento da certificação 01/02 - CANCELAMENTO DA MANUNTEÇÃO SOLICITADO (sem recompras posteriores a esta para justificar) - chegou no CD hoje. Renovação de Certificado, projeto já iniciado com certificador, amostras para testes compradas pelo Danilo, serão encaminhadas para o Laboratório no retorno após o recesso de final de ano em 04/01/2021. 08/01 - Recebemos ok para envio das amostras e as mesmas já foram encaminhadas para o lab 21/01 - Datas para auditoria da Manuntenção agendadas, produto já encaminhado para embarque no dia 25/01 | L37: Selo de certificação na embalagem e no produto | N37: 44286 | O37: =N37-90 -> 44196 | P37: 5319/2020-ELE-1 | Q37: N/A | R37: BRICS OCP 0098 | S37: FALSE | T37: =IFERROR(__xludf.DUMMYFUNCTION("IFERROR(VLOOKUP(C37,IMPORTRANGE(""https://docs.google.com/spreadsheets/d/1RmEXtNg60OGvqZjyMxiYNPJ6S_kcz01v57qrHugDWVc/edit#gid=0"",""Chegadas!E:AQ""),19,0),"""")"),"") | U37: Encerrado | V37: Certificação INMETRO:Produto certificado por BRICS OCP 0098 Nº Certificado 5319/2020-ELE | W37: =N37 -> 44286
A38: IMAGINARIUM | B38: =HYPERLINK("https://imagens.imgnet.com.br/f/imaginarium/"&C38&";"&C38,image("https://imagens.imgnet.com.br/f/imaginarium/"&C38&"))")) | C38: PI4750Y | D38: 2021 - FAT04 | E38: Kingstar | F38: GARRAFA COM AMPLIFICADOR SENTE A BATIDA | G38: TECH | H38: ANATEL CATEGORIA 2 - MÓDULO BLUETOOTH | I38: 2 Amostras completas + 1 Amostra teste lab (Placa PCB com entradas de cabo de RF e Software) | J38: 22/12 - Não teremos venda sell-in e nem recompra desses itens. Certificado não será renovado. - 12/04 - Homologação Anatel finalizada. 01/04 - Processo submetido a Anatel. 15/03 - Amostra encaminhada ao lab. Previsão de finalização de relatórios dos testes: 26/03 e homologação: 02/05. Primeira documentação reecbida em 10/12 após a confirmação de compra. Fora do prazo normal e FAT em risco. Amostra foi enviada para o Brasil da China no dia 18/12, Rastreio 772413404017, encaminhada para o laboratório em 06/01/2021. Previsão para recebermos o código ANATEL em 15/01. 15/01 - Número ANATEL emitido e artes encaminhadas para o time da China - ANATEL: 00427-21-13647 21/01 - Questionamento se o produto vai pegar FAT 04 encaminhado 22/01 - Produto confirmado para FAT 04 03/02 - Por problemas de produção o produto vai para FAT 05 17/02 - Amostra recebida pelo laboratório. Relatório deve estar pronto dia 26/02 (aguardando confirmação de agenda do Lab); | L38: Produto + Manual (ANATEL) | N38: 45017 | O38: =N38-90 -> 44927 | P38: MT-5157/2021 | Q38: 00427-21-13647 | S38: FALSE | T38: =IFERROR(__xludf.DUMMYFUNCTION("IFERROR(VLOOKUP(C38,IMPORTRANGE(""https://docs.google.com/spreadsheets/d/1RmEXtNg60OGvqZjyMxiYNPJ6S_kcz01v57qrHugDWVc/edit#gid=0"",""Chegadas!E:AQ""),19,0),"""")"),"") | U38: Encerrado | V38: Este produto contém a placa PI4750Y código de homologação ANATEL 00427-21-13647 | W38: =N38 -> 45017
A39: IMAGINARIUM | B39: =HYPERLINK("https://imagens.imgnet.com.br/f/imaginarium/"&C39&";"&C39,image("https://imagens.imgnet.com.br/f/imaginarium/"&C39&"))")) | C39: PI4764Y | D39: 2021 - FAT04 | E39: freesun | F39: PROJETOR PORTATIL TRAGO IMAGENS | G39: TECH | H39: ANATEL CATEGORIA 2 - MÓDULO BLUETOOTH | I39: 2 Amostras completas + 1 Amostra teste lab (Placa PCB com entradas de cabo de RF e Software) | J39: 19/01/23 - Projetores estão sem estoque no CD, certificado não será renovado. - 21/05 - Homologação Anatel finalizada. 12/05 - Processo submetido a Anatel - previsão homologação 12/06. 07/05 - Recebidos os laudos, em análise da Engenharia da Master. 12/04 - Amostra recebida e em preparo, início dos testes: 26/04 e entrega dos laudos 07/05. Finalização homologação prevista para 12/06. Vamos enviar a placa do produto final para configuração - nova data de finalização estimada 30/05 Tracking OM946335005BR 17/03 - Empresa que está configurando a placa solicitou algumas informações para o fornecedor (e-mail enviado ontem 16/03). Precisamos de retorno para os testes que serão realizados em 26/03. Previsão homologação 07/05. -atende namorados? 12/03 - Projetor da qualidade não é o mesmo. Vamos homologar a placa. Ensaios agendados no Laboratório, relatórios estarão prontos em 01/04. Homologação: 07/05. 09/03 - Amostra está na Eagle Tech para configuração, Bruno informou que a placa está danificada (queimada). Temos que enviar o projetor que está na qualidade para SP. Documentos Recebidos em 04/11 e encaminhados para o OCD Amostras Chegaram no FEDEX 772035901130. ANATEL 16942-20-13646 21/01 - Produto pode passar por mudanças e perder funcionalidade BT, solicitação da nova documentação encaminhada para avaliar se manteremos o mesmo número ANATEL 26/01 - Documentação é idêntica ao do modelo anterior, materemos o código | L39: Produto + Manual (ANATEL) | N39: 45058 | O39: =N39-90 -> 44968 | P39: MT-5268/2021 | Q39: 03906-21-13799 | S39: FALSE | T39: =IFERROR(__xludf.DUMMYFUNCTION("IFERROR(VLOOKUP(C39,IMPORTRANGE(""https://docs.google.com/spreadsheets/d/1RmEXtNg60OGvqZjyMxiYNPJ6S_kcz01v57qrHugDWVc/edit#gid=0"",""Chegadas!E:AQ""),19,0),"""")"),"") | U39: Encerrado | V39: Este produto contém a placa PI4764Y código de homologação ANATEL 03906-21-13799 | W39: =N39 -> 45058
A40: IMAGINARIUM | B40: =HYPERLINK("https://imagens.imgnet.com.br/f/imaginarium/"&C40&";"&C40,image("https://imagens.imgnet.com.br/f/imaginarium/"&C40&"))")) | C40: PI4197Y | D40: 2020 - FAT04 | E40: Huazeng | F40: LUMINARIA CARREGADOR SEM FIO OFFICE | G40: TECH | H40: ANATEL CATEGORIA 1 - CELULARES | I40: Amostras enviadas para laboratório, aguardando finalização dos ensaios laboratoriais | J40: 15/02/2023 - Confirmado por e-mail que não seguiremos com a renovação desse certificado. 21/07/2022 - Certificado atualizado, nova data de validade: 21/05/2024. 07/05 - Homologação Anatel finalizada. 24/05 - Processo cadastrado na Anatel. 21/05 - Recebido o CCT, sistema da Anatel está fora e não conseguimos cadastrar o processo hoje. 10/05 - Em análise pela OCD, previsão homologação 05/06. 26/04 - Item entregue no laboratório. Testes serão iniciados em 30/04, laudos entregues em 11/05. Finalização homologação prevista paa 05/06. 06/04 - Enviamos novas amostras para o laboratório. Estimativa de homologação atualizada para 04/06. 01/04 - Amostra com problema, laboratório tentou repetir o ensaio de Imunidade à ESD em outra amostra, porém ela não está funcionando adequadamente para o ensaio. Não está reconhecendo o touch. 08/03 - Previsão de entrega dos relatórios do laboratório: 31/03.Sem data de embarque definida. Estimativa homologação 04/05. Recompra de produto, solicitação de compras de etiquetas realizada, previsão de envio para 28/12. Assim que recebidas serão encaminhadas via FedEx para time na China. Código de homologação emitido: 05161-20-12355 - Compra das etiquetas realizadas e recebidas pelo Guilherme em 04/01/2021, encaminhadas para China via FedEx em 05/01/2021 - Tracking: 772527892413 06/01 - Produto confirmado para FAT 05 | L40: Produto + Manual (ANATEL) | M40: Shenzhen Huazeng Technology Co., Ltd | N40: 45433 | O40: =N40-90 -> 45343 | P40: MT-5341/2021 | Q40: 06105-21-12851 | R40: MASTER | S40: TRUE | T40: =IFERROR(__xludf.DUMMYFUNCTION("IFERROR(VLOOKUP(C40,IMPORTRANGE(""https://docs.google.com/spreadsheets/d/1RmEXtNg60OGvqZjyMxiYNPJ6S_kcz01v57qrHugDWVc/edit#gid=0"",""Chegadas!E:AQ""),19,0),"""")"),"") | U40: Encerrado | V40: Produto homologado pela Anatel: Nº Homologação 06105-21-12851 | W40: =N40 -> 45433
A41: IMAGINARIUM | B41: =HYPERLINK("https://imagens.imgnet.com.br/f/imaginarium/"&C41&";"&C41,image("https://imagens.imgnet.com.br/f/imaginarium/"&C41&"))")) | C41: PI4800Y | D41: 2021 - FAT05 | E41: Lexinda | F41: LUMINARIA LED SPEAKER FESTA POR ONDE VOU | G41: TECH | H41: ANATEL CATEGORIA 2 - MÓDULO BLUETOOTH | I41: 2 Amostras completas + 1 Amostra teste lab (Placa PCB com entradas de cabo de RF e Software) | J41: 22/12 - Não teremos venda sell-in e nem recompra desses itens. Certificado não será renovado. - 12/04 - Homologação Anatel finalizada. 01/04 - Processo cadastrado na Anatel. Em análise. Amostra está no laboratorio aguardando os ensaios, previsão de liberação dos relatórios 29/03 e homologação 02/05. Sem processo. Etiqueta ok 17/02 - Amostra recebida pelo laboratório. Relatório deve estar pronto dia 26/02 (aguardando confirmação de agenda do Lab); 05/01 - Recebemos a documentação para homologação 08/01- Estamos aguardando as amostras que estão sendo enviadas no próximo FEDEX, tracking no conjunto a seguir (772570214662, 772570215176, 772570214673) 21/01 - Remessa FEDEX retornou para a China e nova previsão de entrega está para a próxima semana (carga se encontra em memphis de acordo com a ultima atualização do FUP), previsão de emissão do código de homologação para dia 29/01 - Questionei o Vincent se está ok para FAT 05 (está ok) 26/01 - Amostras recebidas e encaminhadas para o laboratório e Nº ANATEL cobrado. 01/02 - Recebido o código de homologação ANATEL: 01372-21-04646. - Alinhamento passado com o time da criação. | L41: Produto + Manual (ANATEL) | N41: 45017 | O41: =N41-90 -> 44927 | P41: MT-5177/2021 | Q41: 01372-21-04646 | S41: FALSE | T41: =IFERROR(__xludf.DUMMYFUNCTION("IFERROR(VLOOKUP(C41,IMPORTRANGE(""https://docs.google.com/spreadsheets/d/1RmEXtNg60OGvqZjyMxiYNPJ6S_kcz01v57qrHugDWVc/edit#gid=0"",""Chegadas!E:AQ""),19,0),"""")"),"") | U41: Encerrado | V41: Este produto contém a placa PI4800Y código de homologação ANATEL 01372-21-04646 | W41: =N41 -> 45017
A42: IMAGINARIUM | B42: =HYPERLINK("https://imagens.imgnet.com.br/f/imaginarium/"&#REF!&";"&#REF!,image("https://imagens.imgnet.com.br/f/imaginarium/"&C42&"))")) | C42: PI4779Y | D42: 2021 - FAT05 | E42: Kayuan | F42: HEADPHONE BLUETOOTH IDAS E OUVIDAS | G42: TECH | H42: ANATEL CATEGORIA 2 - MÓDULO BLUETOOTH | I42: 2 Amostras completas + 1 Amostra teste lab (Placa PCB com entradas de cabo de RF e Software) | J42: 14/03/23 - Certificado não será renovado. - 05/07 - Homologação Anatel finalizada. 18/06 - Processo cadastrado na Anatel. 08/06 - Em análise pelo OC, produção autorizada em 01/06 -- será LATE FAT 08. 18/05 - Bruno deve entregar amostra configurada até sexta, novo agendamento de ensaios para 25/05 e envio de relatórios em 01/06 e finalização da homologação 05/07. 29/04 - Nos ensaios de RF, após o lab montar o plano de ensaio o cabo escapou da placa e o shield do cristal foi desconectado da placa, e a placa não ficou funcional. Vamos esperar finalizarem os ensaios de EMC para usarmos a mesma amostra no ensaio de RF. 07/04 - Amostras no laboratório, entrega dos relatórios prevista para 06/05 e finalização da homologação 11/06. 26/03 - Amostra entregue na Eagle Tech, será configurada semana que vem. 17/03 - Aguardando o envio das amostras, cobramos o Vincent e pedimos para segurar a produção. -- Vincent havia informado que enviaria na sexta, cobrei tracking nr. Para pegarmos o cronograma de FAT 05 precisamos enviar esta semana (homologação 04/05). 08/03 - OCP confirmou que as placas dos headphones são diferentes do modelo PI4240Y. Vicent informou que consegue enviar as amostras sexta-feira. O item pode ter atraso, pois considerando relatório finalizado no final de abril e seguindo os demais cronogramas a homologação estaria ok em 05/06. should we ask supplier to hold the production to wait for the certifiction process? Aguardando documentação e amostras do produto 07/01 - Documentação Recebida e encaminhada para Análise do OCD, prazo de resposta até 12/01 21/01 - Recebemos na segunda-feira (18/01) a confirmação de que podemos reutilizar a mesma numeração ANATEL para os headphones, alinhamento repassado para o time de Criação - ANATEL: 05767-19-11617 | L42: Produto + Manual (ANATEL) | N42: 45093 | O42: =N42-90 -> 45003 | P42: MT-5295/2021 | Q42: 04730-21-11617 | S42: TRUE | T42: =IFERROR(__xludf.DUMMYFUNCTION("IFERROR(VLOOKUP(C42,IMPORTRANGE(""https://docs.google.com/spreadsheets/d/1RmEXtNg60OGvqZjyMxiYNPJ6S_kcz01v57qrHugDWVc/edit#gid=0"",""Chegadas!E:AQ""),19,0),"""")"),"") | U42: Encerrado | V42: Produto homologado pela Anatel: Nº Homologação 04730-21-11617 | W42: =N42 -> 45093
A43: IMAGINARIUM | B43: =HYPERLINK("https://imagens.imgnet.com.br/f/imaginarium/"&#REF!&";"&#REF!,image("https://imagens.imgnet.com.br/f/imaginarium/"&C43&"))")) | C43: PI4828Y | D43: 2021 - FAT05 | E43: Kayuan | F43: HEADPHONE BLUETOOTH TUMDUM BOM | G43: TECH | H43: ANATEL CATEGORIA 2 - MÓDULO BLUETOOTH | I43: 2 Amostras completas + 1 Amostra teste lab (Placa PCB com entradas de cabo de RF e Software) | J43: 14/03/23 - Certificado não será renovado. - 05/07 - Homologação Anatel finalizada. 18/06 - Processo cadastrado na Anatel. 08/06 - Em análise pelo OC, produção autorizada em 01/06 -- será LATE FAT 08. 18/05 - Bruno deve entregar amostra configurada até sexta, novo agendamento de ensaios para 25/05 e envio de relatórios em 01/06 e finalização da homologação 05/07. 29/04 - Nos ensaios de RF, após o lab montar o plano de ensaio o cabo escapou da placa e o shield do cristal foi desconectado da placa, e a placa não ficou funcional. Vamos esperar finalizarem os ensaios de EMC para usarmos a mesma amostra no ensaio de RF. 07/04 - Amostras no laboratório, entrega dos relatórios prevista para 06/05 e finalização da homologação 11/06. 26/03 - Amostra entregue na Eagle Tech, será configurada semana que vem. 17/03 - Aguardando o envio das amostras, cobramos o Vincent e pedimos para segurar a produção. -- Vincent havia informado que enviaria na sexta, cobrei tracking nr. Para pegarmos o cronograma de FAT 05 precisamos enviar esta semana (homologação 04/05). 08/03 - OCP confirmou que as placas dos headphones são diferentes do modelo PI4240Y. Vicent informou que consegue enviar as amostras sexta-feira. O item pode ter atraso, pois considerando relatório finalizado no final de abril e seguindo os demais cronogramas a homologação estaria ok em 05/06. should we ask supplier to hold the production to wait for the certifiction process? Aguardando documentação e amostras do produto 07/01 - Documentação Recebida e encaminhada para Análise do OCD, prazo de resposta até 12/01 21/01 - Recebemos na segunda-feira (18/01) a confirmação de que podemos reutilizar a mesma numeração ANATEL para os headphones, alinhamento repassado para o time de Criação - ANATEL: 05767-19-11617 | L43: Produto + Manual (ANATEL) | N43: 45093 | O43: =N43-90 -> 45003 | P43: MT-5295/2021 | Q43: 04730-21-11617 | S43: TRUE | T43: =IFERROR(__xludf.DUMMYFUNCTION("IFERROR(VLOOKUP(C43,IMPORTRANGE(""https://docs.google.com/spreadsheets/d/1RmEXtNg60OGvqZjyMxiYNPJ6S_kcz01v57qrHugDWVc/edit#gid=0"",""Chegadas!E:AQ""),19,0),"""")"),"") | U43: Encerrado | V43: Produto homologado pela Anatel: Nº Homologação 04730-21-11617 | W43: =N43 -> 45093
A44: IMAGINARIUM | B44: =HYPERLINK("https://imagens.imgnet.com.br/f/imaginarium/"&#REF!&";"&#REF!,image("https://imagens.imgnet.com.br/f/imaginarium/"&C44&"))")) | C44: PI4791Y | D44: 2021 - FAT05 | E44: Kayuan | F44: HEADPHONE BLUETOOTH HP HOGWARTS | G44: TECH | H44: ANATEL CATEGORIA 2 - MÓDULO BLUETOOTH | I44: 2 Amostras completas + 1 Amostra teste lab (Placa PCB com entradas de cabo de RF e Software) | J44: 14/03/23 - Certificado não será renovado. - 05/07 - Homologação Anatel finalizada. 18/06 - Processo cadastrado na Anatel. 08/06 - Em análise pelo OC, produção autorizada em 01/06 -- será LATE FAT 08. 18/05 - Bruno deve entregar amostra configurada até sexta, novo agendamento de ensaios para 25/05 e envio de relatórios em 01/06 e finalização da homologação 05/07. 29/04 - Nos ensaios de RF, após o lab montar o plano de ensaio o cabo escapou da placa e o shield do cristal foi desconectado da placa, e a placa não ficou funcional. Vamos esperar finalizarem os ensaios de EMC para usarmos a mesma amostra no ensaio de RF. 07/04 - Amostras no laboratório, entrega dos relatórios prevista para 06/05 e finalização da homologação 11/06. 26/03 - Amostra entregue na Eagle Tech, será configurada semana que vem. 17/03 - Aguardando o envio das amostras, cobramos o Vincent e pedimos para segurar a produção. -- Vincent havia informado que enviaria na sexta, cobrei tracking nr. Para pegarmos o cronograma de FAT 05 precisamos enviar esta semana (homologação 04/05). 08/03 - OCP confirmou que as placas dos headphones são diferentes do modelo PI4240Y. Vicent informou que consegue enviar as amostras sexta-feira. O item pode ter atraso, pois considerando relatório finalizado no final de abril e seguindo os demais cronogramas a homologação estaria ok em 05/06. should we ask supplier to hold the production to wait for the certifiction process? Aguardando documentação e amostras do produto 07/01 - Documentação Recebida e encaminhada para Análise do OCD, prazo de resposta até 12/01 21/01 - Recebemos na segunda-feira (18/01) a confirmação de que podemos reutilizar a mesma numeração ANATEL para os headphones, alinhamento repassado para o time de Criação - ANATEL: 05767-19-11617 | L44: Produto + Manual (ANATEL) | N44: 45093 | O44: =N44-90 -> 45003 | P44: MT-5295/2021 | Q44: 04730-21-11617 | S44: TRUE | T44: =IFERROR(__xludf.DUMMYFUNCTION("IFERROR(VLOOKUP(C44,IMPORTRANGE(""https://docs.google.com/spreadsheets/d/1RmEXtNg60OGvqZjyMxiYNPJ6S_kcz01v57qrHugDWVc/edit#gid=0"",""Chegadas!E:AQ""),19,0),"""")"),"") | U44: Encerrado | V44: Produto homologado pela Anatel: Nº Homologação 04730-21-11617 | W44: =N44 -> 45093
A45: IMAGINARIUM | B45: =HYPERLINK("https://imagens.imgnet.com.br/f/imaginarium/"&#REF!&";"&#REF!,image("https://imagens.imgnet.com.br/f/imaginarium/"&C45&"))")) | C45: PI4765Y | D45: 2021 - FAT04 | E45: Eastar | F45: RACLETTE GRILL VAI ESQUENTAR 110V | G45: COMES E BEBES | H45: INMETRO Eletrodomésticos | I45: 2 amostras para ensaios na China | J45: 20/01/22 - Certificado encerrado (Inmetro). - 09/04 - Certificado de conformidade emitido. 06/04 - Cobrei lista de componentes que está faltando para a emissão do certificado -- deve ser emitido esta semana. 16/03 - Testes foram finalizados, vamos dar seguimento a produção. Artes alinhadas com a Criação 26/02 - OCP informou que os testes devem estar ok em 18/03. Com esta data conseguimos manter o produto para FAT 06. 18/02 - Auditoria da fábrica está ok, amostras estão no laboratório aguardando a volta do feriado chinês para dar início nos testes. Só tivemos a confirmação da comtra no e-mail da Serena em 10/12 só tivemos a, documentação recebida em 15/12 e já encaminhada para o OCP. Processo iniciado junto com a BRICS, aguardando trâmites técnicos para agendamento da auditoria junto ao fornecedor, data estimada para auditoria para 14/01. 21/01 - Auditoria marcada para o dia 25/01 em função da agenda do fornecedor e do OCP 01/02 - Ensaios laboratoriais aprovados, ensaios irão iniciar após ano novo chinês | L45: Manual e Produto | N45: 44659 | O45: =N45-90 -> 44569 | P45: 6504/2021-ELE-1 | Q45: 6504/2021-ELE-1 | R45: BRICS OCP 0098 | S45: TRUE | T45: =IFERROR(__xludf.DUMMYFUNCTION("IFERROR(VLOOKUP(C45,IMPORTRANGE(""https://docs.google.com/spreadsheets/d/1RmEXtNg60OGvqZjyMxiYNPJ6S_kcz01v57qrHugDWVc/edit#gid=0"",""Chegadas!E:AQ""),19,0),"""")"),"") | U45: Encerrado | V45: Certificação INMETRO:Produto certificado por BRICS OCP 0098 Nº Certificado 6504/2021-ELE-1 | W45: =N45 -> 44659
A46: IMAGINARIUM | B46: =HYPERLINK("https://imagens.imgnet.com.br/f/imaginarium/"&#REF!&";"&#REF!,image("https://imagens.imgnet.com.br/f/imaginarium/"&C46&"))")) | C46: PI4766Y | D46: 2021 - FAT04 | E46: Eastar | F46: RACLETTE GRILL VAI ESQUENTAR 220V | G46: COMES E BEBES | H46: INMETRO Eletrodomésticos | I46: 2 amostras para ensaios na China | J46: 20/01/22 - Certificado encerrado (Inmetro). - 09/04 - Certificado de conformidade emitido. 06/04 - Cobrei lista de componentes que está faltando para a emissão do certificado -- deve ser emitido esta semana. 16/03 - Testes foram finalizados, vamos dar seguimento a produção. Artes alinhadas com a Criação 26/02 - OCP informou que os testes devem estar ok em 18/03. Com esta data conseguimos manter o produto para FAT 06. 18/02 - Auditoria da fábrica está ok, amostras estão no laboratório aguardando a volta do feriado chinês para dar início nos testes. Só tivemos a confirmação da comtra no e-mail da Serena em 10/12 só tivemos a, documentação recebida em 15/12 e já encaminhada para o OCP. Processo iniciado junto com a BRICS, aguardando trâmites técnicos para agendamento da auditoria junto ao fornecedor, data estimada para auditoria para 14/01. 21/01 - Auditoria marcada para o dia 25/01 em função da agenda do fornecedor e do OCP 01/02 - Ensaios laboratoriais aprovados, ensaios irão iniciar após ano novo chinês | L46: Manual e Produto | N46: 44659 | O46: =N46-90 -> 44569 | P46: 6504/2021-ELE-1 | Q46: 6504/2021-ELE-1 | R46: BRICS OCP 0098 | S46: TRUE | T46: =IFERROR(__xludf.DUMMYFUNCTION("IFERROR(VLOOKUP(C46,IMPORTRANGE(""https://docs.google.com/spreadsheets/d/1RmEXtNg60OGvqZjyMxiYNPJ6S_kcz01v57qrHugDWVc/edit#gid=0"",""Chegadas!E:AQ""),19,0),"""")"),"") | U46: Encerrado | V46: Certificação INMETRO:Produto certificado por BRICS OCP 0098 Nº Certificado 6504/2021-ELE-1 | W46: =N46 -> 44659
A47: IMAGINARIUM | B47: =HYPERLINK("https://imagens.imgnet.com.br/f/imaginarium/"&C47&";"&C47,image("https://imagens.imgnet.com.br/f/imaginarium/"&C47&"))")) | C47: PI4810Y | D47: 2021 - FAT05 | E47: 3rd Eye | F47: LUMINARIA COM SPEAKER HP CALDEIRAO | G47: TECH | H47: ANATEL CATEGORIA 2 - MÓDULO BLUETOOTH | I47: 2 Amostras completas + 1 Amostra teste lab (Placa PCB com entradas de cabo de RF e Software) | J47: 05/05/25 - Time de produto decidiu não seguir com a manutenção. 12/06/23 - Manutenção finalizada. Certificado de Homologação emitido. - 16/08 - Homologação Anatel finalizada. 16/07 - Processo cadastrado na Anatel. Estimate ready date 30/07, ETA CD 22/09 - Late FAT 09. 08/07 - Laudos dos testes enviados nesta data. 22/06 - Produção antes da finalização dos testes - ready date final de Julho. Avaliar FAT. 09/06 - Laboratórios nos enviou a agenda - 09/07 testes serão finalizados (antecipamos uma semana em relação ao schedule inicial). 08/06 - Amostra chegou hoje no Brasil. 25/05 - Amostra deve ser recebida no escritório em 31/05. Se considerar início da produção após testes e análise, atrasa para FAT 10 21/05 - Amostra deve chegar em 25/05 no escritório. 20/05 - FAT atualizado para 09. Considerando chegada das amostras no Brasil até o final de maio, a homologação estaria pronta em 30/07. Podemos liberar a amostra após os ensaios, por volta da metade de Julho, para não atrasar para FAT 10. 27/04 - Vincent informou que as amostras devem ser recebidas em 20/05 - estaria homologado por volta de 07/08 mas já estaria embarcado - atraso FAT 29/03 - Amostra e documentos devem estar ok em 20/04. -- confirmado que deve ser o shape final. 16/03 - Amanda informou que a amostra vai demorar 30 dias para ficar pronta. Amostra deve chegar dia 01/05 para atendermos cronograma. Fornecedor mudou para 3rd Eye. Mesmo módulo do PI4861Y. - Confirmando com Vincent se poderemos utilizá-lo. Fat alterado para 08. Documentos Recebidos em 17/11 e encaminhados para o OCD. ANATEL 17002-20-14193 | K47: 45782 | L47: Produto + Manual (ANATEL) | M47: Shenzhen Chenruixin Technology Co., Ltd | N47: 45854 | O47: =N47-90 -> 45764 | P47: MODERNA-1131/23 | Q47: 07480-21-10468 | R47: MODERNA | S47: TRUE | T47: =IFERROR(__xludf.DUMMYFUNCTION("IFERROR(VLOOKUP(C47,IMPORTRANGE(""https://docs.google.com/spreadsheets/d/1RmEXtNg60OGvqZjyMxiYNPJ6S_kcz01v57qrHugDWVc/edit#gid=0"",""Chegadas!E:AQ""),19,0),"""")"),44505.0) -> 44505 | U47: Encerrado | V47: Produto homologado pela Anatel: Nº Homologação 07480-21-10468 | W47: =IFERROR(IF(U47="Ativo","Ativo",IF(U47="SKU excluído","Vencido",VLOOKUP(C47,Encerramentos!B:G,6,0))),"") -> 45852
A48: IMAGINARIUM | B48: =HYPERLINK("https://imagens.imgnet.com.br/f/imaginarium/"&C48&";"&C48,image("https://imagens.imgnet.com.br/f/imaginarium/"&C48&"))")) | C48: PI4709Y | D48: 2021 - FAT03 | E48: Huazeng | F48: RELOGIO SPEAKER LUZ GRADUAL BEATLES SUN | G48: TECH | H48: ANATEL CATEGORIA 2 - MÓDULO BLUETOOTH | I48: 2 Amostras completas + 1 Amostra teste lab (Placa PCB com entradas de cabo de RF e Software) | J48: 02/03/23 - Certificado não será renovado. - 13/08 - Homologação Anatel finalizada. 14/07 - Processo cadastrado na Anatel. Estimate ready date 30/07, ETA CD 22/09 - late FAT 09. 22/06 - Produção antes da finalização dos testes - ready date final de Julho. Avaliar FAT. 09/06 - Teste complementar agendado, será finalizado dia 30/06. 07/06 - Amostra coletada no laboratório para ajustes. 31/05 - Amostra falhou no teste de descarga eletrostática, vamos enviar para Eagle Tech fazer os ajustes necessários. 18/05 - Amostra entregue no laboratório. Testes serão iniciados em 24/05, laudos entregues em 31/05 e homologação finalizada em 04/07. 10/05 - Amostras sendo configuradas, previsão de entrega no lab 14/05. Finalização homologação: 28/06. 27/04 - Amostra enviada, tracking nr 773581911600. 13/04 - Recebimento de amostra atualizado para 16/04. 07/04 - Documentos e amostras serão recebidas em 13/04. 16/03 - Amanda: Amostras já solicitadas semana passada, Vincent está checando previsão de recebimento e irá enviar via ERP. Será nova certificação (novo módulo). Amostra deve chegar dia 01/06 para atendermos cronograma. 04/02 - Solicitada a nova amostra, questionei sobre o módulo BT. 02/04 Documentos recebidos, amostras recebidas em 16/10, encaminhadas para o laboratório em 19/10. Número de registro recebido em 28/10 ANATEL: 15720-20-12851 Número cancelado, amostra trocada. Produto rejeitado pela qualidade, fornecedor não conseguiu ajustar os pedidos da qualidade. Avaliar se o módulo poderá ser usado em outro produto. PI4709Y FAT alterado para 09 2ª Amostra foi cancelada, aguardando retorno da China com atualizações sobre o produto | L48: Produto + Manual (ANATEL) | N48: 45121 | O48: =N48-90 -> 45031 | P48: MT-5486/2021 | Q48: 08317-21-12851 | S48: TRUE | T48: =IFERROR(__xludf.DUMMYFUNCTION("IFERROR(VLOOKUP(C48,IMPORTRANGE(""https://docs.google.com/spreadsheets/d/1RmEXtNg60OGvqZjyMxiYNPJ6S_kcz01v57qrHugDWVc/edit#gid=0"",""Chegadas!E:AQ""),19,0),"""")"),44474.0) -> 44474 | U48: Encerrado | V48: Produto homologado pela Anatel: Nº Homologação 08317-21-12851 | W48: =N48 -> 45121
A49: IMAGINARIUM | B49: =HYPERLINK("https://imagens.imgnet.com.br/f/imaginarium/"&C49&";"&C49,image("https://imagens.imgnet.com.br/f/imaginarium/"&#REF!&"))")) -> #REF! | C49: PI4848Y | D49: 2021 - FAT06 | E49: Huazeng | F49: RELOGIO INTELIGENTE TODAS AS HORAS | G49: TECH | H49: ANATEL CATEGORIA 2 - MÓDULO BLUETOOTH | I49: 2 Amostras completas + 1 Amostra teste lab (Placa PCB com entradas de cabo de RF e Software) | J49: 29/11/22 - Estoque zerado CD, não teremos mais venda sell-in e recompra. Certificado não será renovado. - 22/04 - Homologação Anatel finalizada. 25/03 - Processo cadastrado na Anatel. Em análise. 16/03 - Amostras já foram verificadas e estão configuradas, de acordo com as instruções enviadas, para a realização dos ensaios. Etiquetas ok 05/03 - Amostras preparadas e aguardando ensaios no laboratório, previsão de finalização dos relatórios: 19/03 e finalização da homologação: 24/04. Amostra enviada para qualidade Brasil, após conclusão dos ensaios verificar possibilidade de utilizar a mesma para ensaios 04/01 - Documentação recepcionada no ERP. 08/01- Estamos aguardando as amostras que estão sendo enviadas no próximo FEDEX, tracking no conjunto a seguir (772570214662, 772570215176, 772570214673) 21/01 - Remessa FEDEX retornou para a China e nova previsão de entrega está para a próxima semana (carga se encontra em memphis de acordo com a ultima atualização do FUP), previsão de emissão do código de homologação para dia 29/01 26/01 - Amostras recebidas e encaminhadas para o laboratório e Nº ANATEL cobrado. 01/02 - Recebido o código de homologação ANATEL: 01374-21-12851. Alinhamento passado com o time da criação. 17/02 - Amostra recebida pelo laboratório. Relatório deve estar pronto dia 26/02 (aguardando confirmação de agenda do Lab); | L49: Produto + Manual (ANATEL) | N49: 45038 | O49: =N49-90 -> 44948 | P49: MT-5179/2021 | Q49: 01374-21-12851 | S49: TRUE | T49: =IFERROR(__xludf.DUMMYFUNCTION("IFERROR(VLOOKUP(C49,IMPORTRANGE(""https://docs.google.com/spreadsheets/d/1RmEXtNg60OGvqZjyMxiYNPJ6S_kcz01v57qrHugDWVc/edit#gid=0"",""Chegadas!E:AQ""),19,0),"""")"),"") | U49: Encerrado | V49: Produto homologado pela Anatel: Nº Homologação 01374-21-12851 | W49: =N49 -> 45038
A50: IMAGINARIUM | B50: =HYPERLINK("https://imagens.imgnet.com.br/f/imaginarium/"&C50&";"&C50,image("https://imagens.imgnet.com.br/f/imaginarium/"&#REF!&"))")) -> #REF! | C50: PI4908Y | D50: 2021 - FAT06 | E50: Huazeng | F50: RELOGIO INTELIGENTE SEM TEMPO RUIM | G50: TECH | H50: ANATEL CATEGORIA 2 - MÓDULO BLUETOOTH | I50: 2 Amostras completas + 1 Amostra teste lab (Placa PCB com entradas de cabo de RF e Software) | J50: 29/11/22 - Estoque zerado CD, não teremos mais venda sell-in e recompra. Certificado não será renovado. - 22/04 - Homologação Anatel finalizada. 25/03 - Processo cadastrado na Anatel. Em análise. 16/03 - Amostras já foram verificadas e estão configuradas, de acordo com as instruções enviadas, para a realização dos ensaios. Etiquetas ok 05/03 - Amostras preparadas e aguardando ensaios no laboratório, previsão de finalização dos relatórios: 19/03 e finalização da homologação: 24/04. Amostra enviada para qualidade Brasil, após conclusão dos ensaios verificar possibilidade de utilizar a mesma para ensaios 04/01 - Documentação recepcionada no ERP. 08/01- Estamos aguardando as amostras que estão sendo enviadas no próximo FEDEX, tracking no conjunto a seguir (772570214662, 772570215176, 772570214673) 21/01 - Remessa FEDEX retornou para a China e nova previsão de entrega está para a próxima semana (carga se encontra em memphis de acordo com a ultima atualização do FUP), previsão de emissão do código de homologação para dia 29/01 26/01 - Amostras recebidas e encaminhadas para o laboratório e Nº ANATEL cobrado. 01/02 - Recebido o código de homologação ANATEL: 01374-21-12851. Alinhamento passado com o time da criação. 17/02 - Amostra recebida pelo laboratório. Relatório deve estar pronto dia 26/02 (aguardando confirmação de agenda do Lab); | L50: Produto + Manual (ANATEL) | N50: 45038 | O50: =N50-90 -> 44948 | P50: MT-5179/2021 | Q50: 01374-21-12851 | S50: TRUE | T50: =IFERROR(__xludf.DUMMYFUNCTION("IFERROR(VLOOKUP(C50,IMPORTRANGE(""https://docs.google.com/spreadsheets/d/1RmEXtNg60OGvqZjyMxiYNPJ6S_kcz01v57qrHugDWVc/edit#gid=0"",""Chegadas!E:AQ""),19,0),"""")"),"") | U50: Encerrado | V50: Produto homologado pela Anatel: Nº Homologação 01374-21-12851 | W50: =N50 -> 45038
A51: IMAGINARIUM | B51: =HYPERLINK("https://imagens.imgnet.com.br/f/imaginarium/"&C51&";"&C51,image("https://imagens.imgnet.com.br/f/imaginarium/"&C51&"))")) | C51: PI4861Y | D51: 2021 - FAT06 | E51: 3rd Eye | F51: AMPLIFICADOR BLUETOOTH RETRO MEU TEMPO | G51: TECH | H51: ANATEL CATEGORIA 2 - MÓDULO BLUETOOTH | I51: 2 Amostras completas + 1 Amostra teste lab (Placa PCB com entradas de cabo de RF e Software) | J51: 01/09/23 - Previsão de finalizar estoque em novembro 202. Certificado não será renovado. - 19/03 - Homologação Anatel finalizada nesta data. 17/03 - O certificado da OCP foi emitido. Agora vamos aguardar a homologação, previsão: 13/04. Etiquetas ok 08/03 - Realizada a conectorização no laboratório e modelo foi encaminhado para ensaios. Relatório de testes: 10/03 e homologação: 13/04. 19/02 - Código de homologação Anatel: 02232-21-13731. Repassado ao time de Criação. 17/02 - Amostra recebida pelo laboratório e sexta 19/02 teremos o código ANATEL para repasse ao time da Criação. Relatório deve estar pronto dia 26/02 (aguardando confirmação de agenda do Lab); 05/01 - Recebemos a documentação para homologação previsão de envio das amostras para dia 15/01 21/01 - Ainda não recebemos as amostras nem confirmação do envio, código de homologação pode ser antecipado porém vamos aguardar a confirmação do envio/tracking 26/01 - Amostras a caminho no Fedex 772727344940 01/02 - Amostras recebidas. 02/02 - Amostras encaminhadas para o certificador preparar o lote para os ensaios laboratoriais. Aguardando documentação e amostras do produto | L51: Produto + Manual (ANATEL) | N51: 45000 | O51: =N51-90 -> 44910 | P51: MT-5204/2021 | Q51: 02232-21-13731 | S51: TRUE | T51: =IFERROR(__xludf.DUMMYFUNCTION("IFERROR(VLOOKUP(C51,IMPORTRANGE(""https://docs.google.com/spreadsheets/d/1RmEXtNg60OGvqZjyMxiYNPJ6S_kcz01v57qrHugDWVc/edit#gid=0"",""Chegadas!E:AQ""),19,0),"""")"),"") | U51: Encerrado | V51: Este produto contém a placa PI4861Y código de homologação ANATEL 02232-21-13731 | W51: =N51 -> 45000
A52: IMAGINARIUM | B52: =HYPERLINK("https://imagens.imgnet.com.br/f/imaginarium/"&C52&";"&C52,image("https://imagens.imgnet.com.br/f/imaginarium/"&C52&"))")) | C52: PI4860Y | D52: 2021 - FAT06 | E52: Huazeng | F52: AMPLIFICADOR BLUETOOTH MADEIRA | G52: TECH | H52: ANATEL CATEGORIA 2 - MÓDULO BLUETOOTH | I52: 2 Amostras completas + 1 Amostra teste lab (Placa PCB com entradas de cabo de RF e Software) | J52: 22/12 - Não teremos venda sell-in e nem recompra desses itens. Certificado não será renovado. - 12/04 - Homologação Anatel finalizada. 05/04 - Processo cadastrado na Anatel. Em análise. 08/03 - Amostra preparada pela Eagle Tech e está no laboratório aguardando os ensaios. Entrega de relatórios prevista para 30/03 e homologação 12/04. 05/01 - Recebemos a documentação para homologação 08/01- Estamos aguardando as amostras que estão sendo enviadas no próximo FEDEX, tracking no conjunto a seguir (772570214662, 772570215176, 772570214673) 21/01 - Remessa FEDEX retornou para a China e nova previsão de entrega está para a próxima semana (carga se encontra em memphis de acordo com a ultima atualização do FUP), previsão de emissão do código de homologação para dia 29/01 26/01 - Amostras recebidas e encaminhadas para o laboratório e Nº ANATEL cobrado. 01/02 - Recebido o código de homologação ANATEL: 01373-21-12851. Alinhamento passado com o time da criação. | L52: Produto + Manual (ANATEL) | N52: 45018 | O52: =N52-90 -> 44928 | P52: MT-5178/2021 | Q52: 01373-21-12851 | S52: TRUE | T52: =IFERROR(__xludf.DUMMYFUNCTION("IFERROR(VLOOKUP(C52,IMPORTRANGE(""https://docs.google.com/spreadsheets/d/1RmEXtNg60OGvqZjyMxiYNPJ6S_kcz01v57qrHugDWVc/edit#gid=0"",""Chegadas!E:AQ""),19,0),"""")"),"") | U52: Encerrado | V52: Este produto contém a placa PI4860Y código de homologação ANATEL 01373-21-12851 | W52: =N52 -> 45018
A53: IMAGINARIUM | B53: =HYPERLINK("https://imagens.imgnet.com.br/f/imaginarium/"&C53&";"&C53,image("https://imagens.imgnet.com.br/f/imaginarium/"&C53&"))")) | C53: PI4872Y | D53: 2021 - FAT06 | E53: JONTER | F53: AMPLIFICADOR RADIO RELOGIO SOLTA O SONO | G53: TECH | H53: ANATEL CATEGORIA 2 - MÓDULO BLUETOOTH | I53: 2 Amostras completas + 1 Amostra teste lab (Placa PCB com entradas de cabo de RF e Software) | J53: 19/01/23 - Não vamos renovar o certificado, Entraremos com alguma ação para finalizar o estoque que existe hoje no CD. - 06/05 - Homologação Anatel finalizada. 27/04 - Processo cadastrado na Anatel. Em análise. 13/04 - Em avaliação pela engenharia da OCD - finalização 15/05. 23/03 - Amostra configurada, relatórios de testes devem sair dia 09/04 e finalização homologação 15/05. 15/03 - Amostra está sendo configurada. Sem agendamento no lab ainda, mas considerando prazos normais, relatórios devem estar ok em 25/04, e previsão de homologação para o final de maio. etiquetas ok 08/03 - Eldorado: não conseguimos realizar a configuração para o modelo em questão. Estamos retirando a amostra para configuração na Eagle Tech. (Cronograma anterior: relatórios 09/03 e homologação 12/04 - comprometido). 19/02 - Código de homologação Anatel: 02234-21-09538. Repassado ao time de Criação. 17/02 - Amostra recebida pelo laboratório e sexta 19/02 teremos o código ANATEL para repasse ao time da Criação. Relatório deve estar pronto dia 26/02 (aguardando confirmação de agenda do Lab); 08/01 - Documentos seguem pendentes 12/01 - Produto aguardando aprovação da qualidade. 21/01 - Cobrei informações sobre o projeto, ainda estamos aguardando o envio da documentação 26/01 - Amostras a caminho no Fedex 772727344940 01/02 - Documentos pendentes solicitados, amostras recebidas. 02/02 - Amostras encaminhadas para o certificador preparar o lote para os ensaios laboratoriais. | L53: Produto + Manual (ANATEL) | N53: 45043 | O53: =N53-90 -> 44953 | P53: MT-5205/2021 | Q53: 02234-21-09538 | S53: TRUE | T53: =IFERROR(__xludf.DUMMYFUNCTION("IFERROR(VLOOKUP(C53,IMPORTRANGE(""https://docs.google.com/spreadsheets/d/1RmEXtNg60OGvqZjyMxiYNPJ6S_kcz01v57qrHugDWVc/edit#gid=0"",""Chegadas!E:AQ""),19,0),"""")"),"") | U53: Encerrado | V53: Este produto contém a placa M46-AMP código de homologação ANATEL 02234-21-09538 | W53: =N53 -> 45043
A54: IMAGINARIUM | B54: =HYPERLINK("https://imagens.imgnet.com.br/f/imaginarium/"&C54&";"&C54,image("https://imagens.imgnet.com.br/f/imaginarium/"&C54&"))")) | C54: PI4838Y | D54: 2021 - FAT06 | E54: ANC China | F54: LOCALIZADOR DE CHAVE HP ACCIO | G54: TECH | H54: ANATEL CATEGORIA 2 - MÓDULO BLUETOOTH | I54: 2 Amostras completas + 1 Amostra teste lab (Placa PCB com entradas de cabo de RF e Software) | J54: 22/12/22 - Não teremos venda sell-in e nem recompra desses itens. Certificado não será renovado. - 14/04 - Homologação Anatel finalizada. 07/04 - Processo cadastrado na Anatel. Em análise. Previsão de homologação: 02/05. 17/03 - Código de Homologação atualizado e encaminhado para a Criação (16/03). Cronograma homologação: 17/04. 08/03 - Os relatórios já estavam emitidos (localizador preto). Estão pendentes o documento de similaridade assinado (tratando com Vincent), Cronograma homologação: 17/04. 31/12 - Vincent confirmou que o modelo do módulo bluetooth é diferente e vamos precisar fazer uma nova certificação, alterar o cronograma e enviar na tarefa. Amostras já solicitadas pela Renata 08/01 - Documentos do modelo do produto recebidas, validando com o OCD, previsão de confirmação para 12/01 21/01 - Recebemos na segunda-feira (18/01) a confirmação de que podemos reutilizar a mesma numeração ANATEL para os headphones, alinhamento repassado para o time de Criação - ANATEL: 02461-20-12855 | L54: Produto + Manual (ANATEL) | N54: 45021 | O54: =N54-90 -> 44931 | P54: MT-5263/2021 | Q54: 03511-21-12855 | S54: TRUE | T54: =IFERROR(__xludf.DUMMYFUNCTION("IFERROR(VLOOKUP(C54,IMPORTRANGE(""https://docs.google.com/spreadsheets/d/1RmEXtNg60OGvqZjyMxiYNPJ6S_kcz01v57qrHugDWVc/edit#gid=0"",""Chegadas!E:AQ""),19,0),"""")"),"") | U54: Encerrado | V54: Produto homologado pela Anatel: Nº Homologação 03511-21-12855 | W54: =N54 -> 45021
A55: IMAGINARIUM | B55: =HYPERLINK("https://imagens.imgnet.com.br/f/imaginarium/"&C55&";"&C55,image("https://imagens.imgnet.com.br/f/imaginarium/"&C55&"))")) | C55: PI4878Y | D55: 2021 - FAT07 | E55: 3rd Eye | F55: BALDE DE GELO COM SPEAKER E LED OPEN BAR | G55: COMES E BEBES | H55: ANATEL CATEGORIA 2 - MÓDULO BLUETOOTH | I55: 2 Amostras completas + 1 Amostra teste lab (Placa PCB com entradas de cabo de RF e Software) | J55: 10/01/23 - Certificado não será renovado. - 26/04 - Homologação Anatel finalizada. 13/04 - Em avaliação pela engenharia da OCD - finalização 15/05. 23/03 - Amostra configurada, relatórios de testes devem sair dia 09/04 e finalização homologação 15/05. 17/03 - Amostras estão sendo configuradas. Sem agendamento no lab ainda, mas considerando entrega dos relatórios no final de abril (previsão), homologação deve estar ok no início de Junho. etiquetas ok 08/03 - Pendência no laboratório - Não conseguimos realizar a configuração para o modelo em questão. Vamos enviar para preparação na Eagle Tech. (Cronograma anterior: relatórios 11/03, homologação 16/04). 19/02 - Código de homologação Anatel: 02235-21-13731. Repassado ao time de Criação. 17/02 - Amostra recebida pelo laboratório e sexta 19/02 teremos o código ANATEL para repasse ao time da Criação. Relatório deve estar pronto dia 26/02 (aguardando confirmação de agenda do Lab); Preço confirmado, (módulo novo da 3rd Eye), qualidade ok. Balde de gelo é desmontável e vão mandar sem o balde. Avaliar pelo tamanho do FedEx 08/01 - Documentos seguem pendentes 11/01 - Documentos ainda sendo preparados, devem ficar prontos nos próximos dias, amostras de certificação ficarão prontas próximas ao dia 20/01 19/01 - Documentos recebidos, estamos no aguardo da prepação das amostras para envio. 21/01 - Amostras cobradas via ERP 26/01 - Amostras a caminho no Fedex 772727344940 01/02 - Amostras recebidas. 02/02 - Amostras encaminhadas para o certificador preparar o lote para os ensaios laboratoriais. | L55: Produto + Manual (ANATEL) | N55: 45036 | O55: =N55-90 -> 44946 | P55: MT-5206/2021 | Q55: 02235-21-13731 | S55: TRUE | T55: =IFERROR(__xludf.DUMMYFUNCTION("IFERROR(VLOOKUP(C55,IMPORTRANGE(""https://docs.google.com/spreadsheets/d/1RmEXtNg60OGvqZjyMxiYNPJ6S_kcz01v57qrHugDWVc/edit#gid=0"",""Chegadas!E:AQ""),19,0),"""")"),"") | U55: Encerrado | V55: Este produto contém a placa PI4878Y código de homologação ANATEL 02235-21-13731 | W55: =N55 -> 45036
A56: IMAGINARIUM | B56: =HYPERLINK("https://imagens.imgnet.com.br/f/imaginarium/"&C56&";"&C56,image("https://imagens.imgnet.com.br/f/imaginarium/"&C56&"))")) | C56: PI4882Y | D56: 2021 - FAT07 | E56: New tech | F56: KARAOKE PORTATIL SEGUE O BAILE | G56: TECH | H56: ANATEL CATEGORIA 2 - MÓDULO BLUETOOTH | I56: 2 Amostras completas + 1 Amostra teste lab (Placa PCB com entradas de cabo de RF e Software) | J56: 22/12 - Não teremos venda sell-in e nem recompra desses itens. Certificado não será renovado. - 12/04 - Homologação Anatel finalizada. 05/04 - Processo cadastrado na Anatel. Em análise. 17/03 - Placa está no laboratório aguardando ensaios, previsão de entrega de relatórios 30/03, e homologação 03/05. Enviado hoje as instruções de manual e etiqueta 17/02 - Placa PCB encaminhada ao Laboratório para darmos sequência nos testes. 12/02 - Microfone encaminhado para a Qualidade - Sedex QB218864869BR. 03/02 - Amostra pendente de ser encaminhada para a Qualidade | L56: Produto + Manual (ANATEL) | N56: 45018 | O56: =N56-90 -> 44928 | P56: MT-5259/2021 | Q56: 03474-21-13782 | S56: FALSE | T56: =IFERROR(__xludf.DUMMYFUNCTION("IFERROR(VLOOKUP(C56,IMPORTRANGE(""https://docs.google.com/spreadsheets/d/1RmEXtNg60OGvqZjyMxiYNPJ6S_kcz01v57qrHugDWVc/edit#gid=0"",""Chegadas!E:AQ""),19,0),"""")"),"") | U56: Encerrado | V56: Este produto contém a placa PI4882Y código de homologação ANATEL 03474-21-13782 | W56: =N56 -> 45018
A57: IMAGINARIUM | B57: =HYPERLINK("https://imagens.imgnet.com.br/f/imaginarium/"&C57&";"&C57,image("https://imagens.imgnet.com.br/f/imaginarium/"&C57&"))")) | C57: PI4899Y | D57: 2021 - FAT06 | E57: JYK | F57: VITROLA BLUETOOTH TAMPA ACRILICO VERDE | G57: TECH | H57: ANATEL CATEGORIA 2 - MÓDULO BLUETOOTH | I57: 2 Amostras completas + 1 Amostra teste lab (Placa PCB com entradas de cabo de RF e Software) | J57: 20/03/23 - O certificado não será renovado. - 09/09 - Homologação Anatel finalizada. 03/09 - Previsão de chegada no CD atualizada: 29/10. 16/08 - Processo cadastrado na Anatel. Previsão de finalização homologação: 10/09. Chegada no CD: 04/11. 02/08 - Aguardando o envio do relatório revisado - schedule ok para FAT 11. 26/07 - Solicitado o envio do relatório com as alterações para certificação RF. 20/07 - Ensaios estão em andamento e previsão de finalização é 23/07. 17/05 - Amostra de RF configurada e liberada para ensaios. 15/07 - Produto apresentou ocorrência no ensaio de Imunidade a RF Conduzida - Terminais de Energia Elétrica, do Ato 1120 da Anatel. Bruno não considera falha, verificando com Ademir. 12/07 - Amostra de RF e instruçõoes enviados ao laboratório. 08/07 - Finalização testes: 22/07. 22/06 - Vincent enviou a amostra test mode - 774060074627. Formalizei sobre MP antes da finalização dos testes - permanece FAT 11. 14/06 - Início dos testes agendados para 28/06 e previsão de finalização para 12/07. 12/06 - Não recebemos a amostra test mode, questionando Vincent. 09/06 - Amostra será recebida hoje. 21/05 - Amostra enviada FEDEX 773786818334 / 773786818595 - produção deve ser iniciada no começo de Julho para manter FAT 10 27/04 - Vincent irá enviar os documentos ainda esta semana e confirmou que as amostras estarão prontas em 15/05. - amostras já chegaram 20/04 - Vincent informou que poderá enviar os documentos ainda esta semana e sobre a amostra não tinha confirmação. 12/04 - Sem informação exata quanto a amostra e documentos do fornecedor, Vincent ficou de enviar esta quarta. 17/03 - Fat alterado pra 10, aguardando detalhes quanto a amostra - Amostra deve chegar dia 14/08 para seguir o cronograma. 10 a 15 dias (amostra) Verificar se é o mesmo módulo da ultima vitrola, produto muito grande para ser enviado via FEDEX 08/01 - Documentos seguem pendentes, porém o FAT foi alterado para 10 | L57: Produto + Manual (ANATEL) | N57: 45151 | O57: 45121 | P57: MT-5502/2021 | Q57: 09132-21-06091 | S57: TRUE | T57: =IFERROR(__xludf.DUMMYFUNCTION("IFERROR(VLOOKUP(C57,IMPORTRANGE(""https://docs.google.com/spreadsheets/d/1RmEXtNg60OGvqZjyMxiYNPJ6S_kcz01v57qrHugDWVc/edit#gid=0"",""Chegadas!E:AQ""),19,0),"""")"),44505.0) -> 44505 | U57: Encerrado | V57: Este produto contém a placa PI4899Y código de homologação ANATEL: 09132-21-06091. | W57: =N57 -> 45151
A58: IMAGINARIUM | B58: =HYPERLINK("https://imagens.imgnet.com.br/f/imaginarium/"&C58&";"&C58,image("https://imagens.imgnet.com.br/f/imaginarium/"&C58&"))")) | C58: PI4993Y | D58: 2021 - FAT09 | E58: MUV | F58: MOUSEPAD WITH WIRELESS CHARGER GAME OVER | G58: TECH | H58: ANATEL CATEGORIA 1 - CELULARES | I58: 2 Amostras completas | J58: 14/07/23 - Homologação finalizada. 26/04/23 - Manutenção do certificado em andamento. - 29/06 - Homologação Anatel finalizada. 21/06 - Processo cadastrado na Anatel. 01/06 - Laudos verificados, autorizamos a produção. Estimado para LATE FAT 08. 29/04 - Ensaios serão iniciados em 24/05, laudos entregues em 01/06 e finalização da homologação prevista para 24/06. 28/04 - Enviamos a amostra para identificação e envio ao laboratório. 13/04 - Amostra enviada via FEDEX 773424649294. 07/06 - Amostras serão enviadas em 13/04. 16/03 - Produto com pendência de qualidade, e teremos o retorno do fornecedor à respeito até amanhã. Após a confirmação, Vincent irá checar a ready date e enviará via ERP, mas a previsão é que leve em média 1-2 semanas para recebermos as amostras de certificação. Amostra deve chegar dia 01/05 para atendermos cronograma. amostra e docs: 02/04 09/03 - Cobrei amostras 28/01 - Solicitação de documentos enviada no ERP | L58: Produto + Manual (ANATEL) | M58: Shenzhen Botech Technology Co., Ltd | N58: 45829 | O58: =N58-90 -> 45739 | P58: MODERNA-1132/23 | Q58: 06516-21-13892 | R58: MODERNA | S58: TRUE | T58: =IFERROR(__xludf.DUMMYFUNCTION("IFERROR(VLOOKUP(C58,IMPORTRANGE(""https://docs.google.com/spreadsheets/d/1RmEXtNg60OGvqZjyMxiYNPJ6S_kcz01v57qrHugDWVc/edit#gid=0"",""Chegadas!E:AQ""),19,0),"""")"),"") | U58: Encerrado | V58: Produto homologado pela Anatel: Nº homologação 06516-21-13892 | W58: =IFERROR(IF(U58="Ativo","Ativo",IF(U58="SKU excluído","Vencido",VLOOKUP(C58,Encerramentos!B:G,6,0))),"") -> 45829
A59: IMAGINARIUM | B59: =HYPERLINK("https://imagens.imgnet.com.br/f/imaginarium/"&C59&";"&C59,image("https://imagens.imgnet.com.br/f/imaginarium/"&C59&"))")) | C59: PI4995Y | D59: 2021 - FAT09 | E59: JYK | F59: VITROLA BLUETOOTH BEATLES TWIST & SHOUT | G59: TECH | H59: ANATEL CATEGORIA 2 - MÓDULO BLUETOOTH | I59: 2 Amostras completas + 1 Amostra teste lab (Placa PCB com entradas de cabo de RF e Software) | J59: 09/07 - Seguindo com a inclusão no certificado da Vitrola, Anatel ID 15743-20-13462 - solicitado etiqueta para a Criação 17/03 - Avaliando com a OCP as fotos das placas enviadas pelo Vincent ontem, para checar se podemos incluir na mesma família do PI4642Y 09/03 - Solicitei ao Vincent fotos da placa desta Vitrola para checar se conseguimos incluir na família do PI4642Y. 28/01 - Solicitação de documentos enviada no ERP | L59: Produto + Manual (ANATEL) | N59: 45007 | O59: =N59-90 -> 44917 | P59: MT-5084/2020 | Q59: 15743-20-13462 | S59: TRUE | T59: =IFERROR(__xludf.DUMMYFUNCTION("IFERROR(VLOOKUP(C59,IMPORTRANGE(""https://docs.google.com/spreadsheets/d/1RmEXtNg60OGvqZjyMxiYNPJ6S_kcz01v57qrHugDWVc/edit#gid=0"",""Chegadas!E:AQ""),19,0),"""")"),"") | U59: Encerrado | V59: Este produto contém a placa ST226A código de homologação ANATEL 15743-20-13462 | W59: =N59 -> 45007
A60: IMAGINARIUM | B60: =HYPERLINK("https://imagens.imgnet.com.br/f/imaginarium/"&C60&";"&C60,image("https://imagens.imgnet.com.br/f/imaginarium/"&C60&"))")) | C60: PI4943Y | D60: 2021 - FAT08 | E60: Kyc | F60: CARREGADOR POR INDUCAO BEATLES HELP | G60: TECH | H60: ANATEL CATEGORIA 1 - CELULARES | I60: 2 Amostras completas | J60: 05/05/25 - Time de produto decidiu não seguir com a manutenção. 22/06/23 - Homologação emitida. 26/04/23 - Manutenção do certificado em andamento. - 04/08 - Homologação Anatel finalizada. 28/07 - Vincent informou que a MP atrasou e item será postergado para FAT 10. 14/07 - Processo cadastrado na Anatel. Estimate ready date 30/07, ETA CD 22/09 - Late FAT 09. 29/06 - Ready date 25/07, questionei sobre o FAT: But if some specific item I think we could try to fast it . Arrange it as urgent and make some time? But if we don’t need to try to catch FAT09. Then of course is better to moved to FAT10. Será etiquetado aqui. 22/06 - Formalizei sobre produção antes do teste. Prazo para entregar as etiquetas na China: 10/07. 21/06 - Solicitada cotação das etiquetas para Compras. 17/06 - Amostra (Friends) recebida no laboratório, data de finalização dos testes: 30/06. 08/06 - Amostra de Friends chegou ontem em SP, enviada com as demais amostras para a Eagle Tech para identificação e envio ao Lab -- será a mesma família de certificação. Recebemos a agenda do Lab, testes irão finalizar dia 30/06 conforme schedule inicial. 26/05 - Amostra chegou hoje no escritório. Foi alterada para mesma placa do carregador Friends, verificar se podemos fazer a mesma certificação 20/05 - Data estimada para chegada do carregador alterou para 24/05. 12/05 - Amostras chegam no escritório semana que vem, avaliar atraso. 07/04 - Aguardando retorno do fornecedor para confirmar envio das amostras e documentos. +2 semanas 09/03 - Cobrei amostras (verificando com Vincent sobre a placa ser igual para incluirmos no certificado do HP) - aguardando update do ready date. Amostra deve chegar dia 01/06 para atendermos cronograma. 28/01 - Solicitação de do28/01 - Solicitação de documentos enviada no ERP | K60: 45782 | L60: Produto + Manual (ANATEL) | M60: Shenzhen Kaiyue Century Technology Co., Ltd | N60: 45852 | O60: =N60-90 -> 45762 | P60: MODERNA-1130/23 | Q60: 08886-21-12562 | R60: MODERNA | S60: TRUE | T60: =IFERROR(__xludf.DUMMYFUNCTION("IFERROR(VLOOKUP(C60,IMPORTRANGE(""https://docs.google.com/spreadsheets/d/1RmEXtNg60OGvqZjyMxiYNPJ6S_kcz01v57qrHugDWVc/edit#gid=0"",""Chegadas!E:AQ""),19,0),"""")"),44474.0) -> 44474 | U60: Encerrado | V60: Produto homologado pela Anatel: Nº homologação 08886-21-12562 | W60: =IFERROR(IF(U60="Ativo","Ativo",IF(U60="SKU excluído","Vencido",VLOOKUP(C60,Encerramentos!B:G,6,0))),"") -> 45852
A61: IMAGINARIUM | B61: =HYPERLINK("https://imagens.imgnet.com.br/f/imaginarium/"&C61&";"&C61,image("https://imagens.imgnet.com.br/f/imaginarium/"&C61&"))")) | C61: PI4916Y | D61: 2021 - FAT08 | E61: Universe Sound | F61: ABRIDOR DE GARRAFA ONCA | G61: TECH | H61: ANATEL CATEGORIA 2 - MÓDULO BLUETOOTH | I61: 2 Amostras completas + 1 Amostra teste lab (Placa PCB com entradas de cabo de RF e Software) | J61: 01/06/23 - Certificado suspenso. 03/04/23 - O certificado não será renovado. - 25/06 - Homologação Anatel finalizada. 01/06 - Processo cadastrado na Anatel - irá para FAT 09. 25/05 - Confirmei que os testes estão ok e liberamos a MP, o ready date estimado é início de Julho então este item será Late FAT 8 26/04 - Início dos testes agendados para 04/05, entrega dos laudos 13/05 e finalização da homologação 07/06. 06/04 - Amostra na Eagle Tech para configuração. Data prevista: 01/06. 23/03 - Amostras enviadas via FEDEX, tracking number: 773271403014 (entrega prevista 05/04) 16/03 - Mesmo produto que o modelo anterior PI4587Y. Estão iniciando a amostra com base no nosso projeto, e trabalhando nas melhorias do microfone. Fornecedor confirmou que não precisarão alterar a placa PCB com a melhoria do microfone, mas pedimos fotos para ter certeza que a placa será a mesma. Vincent enviará no ERP assim que recebermos essa foto (previsão início da semana que vem). Amostra deve chegar dia 01/05 para atendermos cronograma. 09/03 - Cobrei amostras e ISO (fornecedor placa). 28/01 - Solicitação de documentos enviada no ERP | L61: Produto + Manual (ANATEL) | N61: 45077 | O61: =N61-90 -> 44987 | P61: MT-5347/2021 | Q61: 06109-21-12418 | S61: TRUE | T61: =IFERROR(__xludf.DUMMYFUNCTION("IFERROR(VLOOKUP(C61,IMPORTRANGE(""https://docs.google.com/spreadsheets/d/1RmEXtNg60OGvqZjyMxiYNPJ6S_kcz01v57qrHugDWVc/edit#gid=0"",""Chegadas!E:AQ""),19,0),"""")"),"") | U61: Encerrado | V61: Produto homologado pela Anatel: Nº Homologação 06109-21-12418 | W61: =N61 -> 45077
A62: IMAGINARIUM | B62: =HYPERLINK("https://imagens.imgnet.com.br/f/imaginarium/"&C62&";"&C62,image("https://imagens.imgnet.com.br/f/imaginarium/"&C62&"))")) | C62: PI4917Y | D62: 2021 - FAT08 | E62: Kyc | F62: CARREGADOR POR INDUCAO FRIENDS SOFA | G62: TECH | H62: ANATEL CATEGORIA 1 - CELULARES | I62: 2 Amostras completas | J62: 05/05/25 - Time de produto decidiu não seguir com a manutenção. 22/06/23 - Homologação emitida. 26/04/23 - Manutenção do certificado em andamento. - 04/08 - Homologação Anatel finalizada. 14/07 - Processo cadastrado na Anatel. Estimate ready date 30/07, ETA CD 22/09 - Late FAT 09. 29/06 - Ready date 25/07, questionei sobre o FAT: But if some specific item I think we could try to fast it . Arrange it as urgent and make some time? But if we don’t need to try to catch FAT09. Then of course is better to moved to FAT10. Será etiquetado aqui. 22/06 - Formalizei sobre produção antes do teste. Prazo para entregar as etiquetas na China: 10/07. 21/06 - Solicitada cotação das etiquetas para Compras. 17/06 - Amostra (Friends) recebida no laboratório, data de finalização dos testes: 30/06. 08/06 - Amostra de Friends chegou ontem em SP, enviada com as demais amostras para a Eagle Tech para identificação e envio ao Lab -- será a mesma família de certificação. Recebemos a agenda do Lab, testes irão finalizar dia 30/06 conforme schedule inicial. 26/05 - Amostra chegou hoje no escritório. Foi alterada para mesma placa do carregador Friends, verificar se podemos fazer a mesma certificação 20/05 - Data estimada para chegada do carregador alterou para 24/05. 12/05 - Amostras chegam no escritório semana que vem, avaliar atraso. 07/04 - Aguardando retorno do fornecedor para confirmar envio das amostras e documentos. +2 semanas 09/03 - Cobrei amostras (verificando com Vincent sobre a placa ser igual para incluirmos no certificado do HP) - aguardando update do ready date. Amostra deve chegar dia 01/06 para atendermos cronograma. 28/01 - Solicitação de do28/01 - Solicitação de documentos enviada no ERP" 29/06 - Ready date estimado: 20/07. Dentro do FAT. Será etiquetado aqui. 22/06 - Formalizei sobre produção antes do teste. Prazo para entregar as etiquetas na China: 10/07. 21/06 - Solicitada cotação das etiquetas para Compras. 17/06 - Amostra recebida no laboratório, data de finalização dos testes: 30/06. 08/06 - Amostra chegou ontem em SP, enviada com as demais amostras para a Eagle Tech para identificação e envio ao Lab. Recebemos a agenda do Lab, testes irão finalizar dia 30/06 conforme schedule inicial. 12/05 - Item vai atrasar pra FAT 9 pois a homologação finalizará em Julho. 07/04 - Aguardando retorno do fornecedor para confirmar envio das amostras e documentos. +2 semanas 18/03 - Vincent confirmou que não será a mesma placa. Ainda não conseguiu passar data estimada de envio de amostras. 16/03 - Projeto recebido 5 dias atrás e estamos aguardando o layout 3D do fornecedor. Estão checando se por conta da estrutura interna, conseguiremos manter a mesma placa PCB dos SKUs anteriores da KYC, vamos ter esse ok até amanhã e Vincent atualizará no ERP. De qualquer forma, esse produto levará em torno de 20 dias para abrir o molde, então só teremos a amostra completa em mãos início de abril. Amostra deve chegar dia 01/05 para atendermos cronograma. 10/03 - Vincent: OK，right now supplier not sure if they need to adjust something , we quoted with similar design of the PI3876Y , if the shape and design not affect something(which will confirm after receiving artwork ) , then we will follow the PCB board as the same with PI3876Y. 09/03 - Cobrei amostras (verificando com Vincent sobre a placa ser igual para incluirmos no certificado do HP) 28/01 - Solicitação de documentos enviada no ERP | K62: 45782 | L62: Produto + Manual (ANATEL) | M62: Shenzhen Kaiyue Century Technology Co., Ltd | N62: 45852 | O62: =N62-90 -> 45762 | P62: MODERNA-1130/23 | Q62: 08886-21-12562 | R62: MODERNA | S62: TRUE | T62: =IFERROR(__xludf.DUMMYFUNCTION("IFERROR(VLOOKUP(C62,IMPORTRANGE(""https://docs.google.com/spreadsheets/d/1RmEXtNg60OGvqZjyMxiYNPJ6S_kcz01v57qrHugDWVc/edit#gid=0"",""Chegadas!E:AQ""),19,0),"""")"),44474.0) -> 44474 | U62: Encerrado | V62: Produto homologado pela Anatel: Nº homologação 08886-21-12562 | W62: =IFERROR(IF(U62="Ativo","Ativo",IF(U62="SKU excluído","Vencido",VLOOKUP(C62,Encerramentos!B:G,6,0))),"") -> 45852
A63: IMAGINARIUM | B63: =HYPERLINK("https://imagens.imgnet.com.br/f/imaginarium/"&C63&";"&C63,image("https://imagens.imgnet.com.br/f/imaginarium/"&C63&"))")) | C63: PI4934Y | D63: 2021 - FAT08 | E63: MUV | F63: BASE HEADSET E CARREGADOR SEM FIO GAMER | G63: TECH | H63: ANATEL CATEGORIA 1 - CELULARES | I63: 2 Amostras completas | J63: 14/07/23 - Homologação finalizada. 26/04/23 - Manutenção do certificado em andamento. - 29/06 - Homologação Anatel finalizada. 21/06 - Processo cadastrado na Anatel. 01/06 - Laudos verificados, autorizamos a produção. Estimado para LATE FAT 08. Verificar sobre etiquetagem. 01/06 - Laudos verificados, autorizamos a produção. Verificar sobre etiquetagem. 29/04 - Ensaios serão iniciados em 24/05, laudos entregues em 01/06 e finalização da homologação prevista para 24/06. 28/04 - Enviamos a amostra para identificação e envio ao laboratório. 13/04 - Amostra enviada via FEDEX 773424649294. 07/04 - Amostras serão enviadas dia 13/04. 16/03 - Amanda cobrou o Vincent sobre a solicitação das 2 amostras, ele está checando a ready date e enviará via ERP, mas a previsão é que leve 1-2 semanas para recebermos as amostras de certificação. Amostra deve chegar dia 01/05 para atendermos cronograma. prev. recebimento 02/04 10/03 - Amanda: For this product, we are still pending a reply from pricing regarding the quotation. As soon as we have the price approval and the confirmation of the model, we can request the samples and documents to start the certification process. 09/03 - Cobrei amostras 03/02 - Verificação ISO 28/01 - Solicitação de documentos enviada no ERP | L63: Produto + Manual (ANATEL) | M63: Shenzhen Botech Technology Co., Ltd | N63: 45829 | O63: =N63-90 -> 45739 | P63: MODERNA-1133/23 | Q63: 06517-21-13892 | R63: MODERNA | S63: TRUE | T63: =IFERROR(__xludf.DUMMYFUNCTION("IFERROR(VLOOKUP(C63,IMPORTRANGE(""https://docs.google.com/spreadsheets/d/1RmEXtNg60OGvqZjyMxiYNPJ6S_kcz01v57qrHugDWVc/edit#gid=0"",""Chegadas!E:AQ""),19,0),"""")"),"") | U63: Encerrado | V63: Produto homologado pela Anatel: Nº Homologação 06517-21-13892 | W63: =IFERROR(IF(U63="Ativo","Ativo",IF(U63="SKU excluído","Vencido",VLOOKUP(C63,Encerramentos!B:G,6,0))),"") -> 45829
A64: IMAGINARIUM | B64: =HYPERLINK("https://imagens.imgnet.com.br/f/imaginarium/"&C64&";"&C64,image("https://imagens.imgnet.com.br/f/imaginarium/"&C64&"))")) | C64: PI4939Y | D64: 2021 - FAT08 | E64: Joy rain | F64: CANETA DOG | G64: USO PESSOAL | H64: INMETRO ARTIGOS ESCOLARES SISTEMA 5 - PORTARIA 481 | I64: Inclusão | J64: 21/08/23 - Certificado encerrado. - 23/03 - Certificado de conformidade emitido OCP informou que não precisará ser realizado os ensaios neste caso. Estou aguardando a confirmação. - número de registro é o mesmo utilizado para as canetas que ja compramos Muda frases HP. | L64: Embalagem (INMETRO) | N64: 44428 | O64: =N64-90 -> 44338 | P64: 5605/2020-AE-1 | Q64: 006550/2020 | R64: BRICS OCP 0098 | S64: TRUE | T64: =IFERROR(__xludf.DUMMYFUNCTION("IFERROR(VLOOKUP(C64,IMPORTRANGE(""https://docs.google.com/spreadsheets/d/1RmEXtNg60OGvqZjyMxiYNPJ6S_kcz01v57qrHugDWVc/edit#gid=0"",""Chegadas!E:AQ""),19,0),"""")"),"") | U64: Encerrado | V64: Certificação INMETRO:Produto certificado por BRICS OCP 0098 Nº Registro 006550/2020 | W64: =N64 -> 44428
A65: IMAGINARIUM | B65: =HYPERLINK("https://imagens.imgnet.com.br/f/imaginarium/"&C65&";"&C65,image("https://imagens.imgnet.com.br/f/imaginarium/"&C65&"))")) | C65: PI4940Y | D65: 2022 - FAT09 | E65: Joy rain | F65: CANETA GATINHO | G65: USO PESSOAL | H65: INMETRO ARTIGOS ESCOLARES SISTEMA 5 - PORTARIA 481 | I65: Inclusão | J65: 21/08/23 - Certificado encerrado. - 23/03 - Certificado de conformidade emitido OCP informou que não precisará ser realizado os ensaios neste caso. Estou aguardando a confirmação. - número de registro é o mesmo utilizado para as canetas que ja compramos Muda frases HP. | L65: Embalagem (INMETRO) | N65: 44428 | O65: =N65-90 -> 44338 | P65: 5605/2020-AE-1 | Q65: 006550/2020 | R65: BRICS OCP 0098 | S65: TRUE | T65: =IFERROR(__xludf.DUMMYFUNCTION("IFERROR(VLOOKUP(C65,IMPORTRANGE(""https://docs.google.com/spreadsheets/d/1RmEXtNg60OGvqZjyMxiYNPJ6S_kcz01v57qrHugDWVc/edit#gid=0"",""Chegadas!E:AQ""),19,0),"""")"),44809.0) -> 44809 | U65: Encerrado | V65: Certificação INMETRO:Produto certificado por BRICS OCP 0098 Nº Registro 006550/2020 | W65: =N65 -> 44428
A66: IMAGINARIUM | B66: =HYPERLINK("https://imagens.imgnet.com.br/f/imaginarium/"&C66&";"&C66,image("https://imagens.imgnet.com.br/f/imaginarium/"&C66&"))")) | C66: PI4990Y | D66: 2021 - FAT09 | E66: Joy rain | F66: CANETA MUDA FRASES SORTE DO DIA | G66: USO PESSOAL | H66: INMETRO ARTIGOS ESCOLARES SISTEMA 5 - PORTARIA 481 | I66: Inclusão | J66: 21/08/23 - Certificado encerrado. - 23/03 - Certificado de conformidade emitido OCP informou que não precisará ser realizado os ensaios neste caso. Estou aguardando a confirmação. - número de registro é o mesmo utilizado para as canetas que ja compramos Muda frases HP. | L66: Embalagem (INMETRO) | N66: 44428 | O66: =N66-90 -> 44338 | P66: 5605/2020-AE-1 | Q66: 006550/2020 | R66: BRICS OCP 0098 | S66: TRUE | T66: =IFERROR(__xludf.DUMMYFUNCTION("IFERROR(VLOOKUP(C66,IMPORTRANGE(""https://docs.google.com/spreadsheets/d/1RmEXtNg60OGvqZjyMxiYNPJ6S_kcz01v57qrHugDWVc/edit#gid=0"",""Chegadas!E:AQ""),19,0),"""")"),44474.0) -> 44474 | U66: Encerrado | V66: Certificação INMETRO:Produto certificado por BRICS OCP 0098 Nº Registro 006550/2020 | W66: =N66 -> 44428
A67: IMAGINARIUM | B67: =HYPERLINK("https://imagens.imgnet.com.br/f/imaginarium/"&C67&";"&C67,image("https://imagens.imgnet.com.br/f/imaginarium/"&C67&"))")) | C67: PI4771Y | D67: 2021 - FAT04 | E67: AUBADI | F67: AMPLIFICADOR PARA CHUVEIRO SO PRA DANCAR | G67: TECH | H67: ANATEL CATEGORIA 2 - MÓDULO BLUETOOTH | I67: 2 Amostras completas + 1 Amostra teste lab (Placa PCB com entradas de cabo de RF e Software) | J67: 24/01 - Não iremos renovar o certificado, uma vez que o estoque no CD já está zerado e não pretendemos recomprar o item - 08/06 - Homologação Anatel finalizada. 24/05 - Processo cadastrado na Anatel. Por conta do retrabalho o FAT foi alterado para 8. 28/04 - Amostra entregue no laboratório - homologação prevista para 21/06. 27/04 - Produto está sendo retrabalhado e será late FAT 7. Testes serão iniciados em 10/05, laudos entregues em 18/05 e previsão de homologação está para 21/06. | L67: Produto + Manual (ANATEL) | N67: 45066 | O67: =N67-90 -> 44976 | P67: MT-5423/2021 | Q67: 07145-21-13801 | S67: FALSE | T67: =IFERROR(__xludf.DUMMYFUNCTION("IFERROR(VLOOKUP(C67,IMPORTRANGE(""https://docs.google.com/spreadsheets/d/1RmEXtNg60OGvqZjyMxiYNPJ6S_kcz01v57qrHugDWVc/edit#gid=0"",""Chegadas!E:AQ""),19,0),"""")"),"") | U67: Encerrado | V67: Este produto contém a placa PI4771Y código de homologação ANATEL 07145-21-13801 | W67: =N67 -> 45066
A68: IMAGINARIUM | B68: =HYPERLINK("https://imagens.imgnet.com.br/f/imaginarium/"&C68&";"&C68,image("https://imagens.imgnet.com.br/f/imaginarium/"&C68&"))")) | C68: PI5059Y | D68: 2021 - FAT10 | E68: 3Rd Eye | F68: AMPLIFICADOR BLUETOOTH COM LED LUA CHEIA | G68: TECH | H68: ANATEL CATEGORIA 2 - MÓDULO BLUETOOTH | I68: 2 Amostras completas + 1 Amostra teste lab (Placa PCB com entradas de cabo de RF e Software) | J68: 18/09/23 - Certificado suspenso. 07/10 - Homologação Anatel finalizada. 20/09 - Processo cadastrado na Anatel. Em análise. 14/09 - Laudos recebidos, em análise pela Master. Deve ser cadastrado na Anatel até sexta-feira. Previsão de finalização da homologação: 17/10, previsão de chegada no CD: 16/11. 10/09 - Ensaios finalizados, previsão de envio de relatório: 15/09. 03/09 - Chegada no CD atualizada para 16/11. Item alterado para FAT 11. Previsão de finalização de homologação: 31/10. 31/08 - Amostra entregue hoje no laboratório. Previsão de finalização dos ensaios: 10/09 e entrega do relatório: 17/09. Previsão de finalização homologação: 26/10 (produto chega dia 27/10 no CD). 26/08 - Amostra enviada para configuração. Previsão de entrega no laboratório: 31/08. 19/08 - Amostra enviada, AWB 774575803482. 11/08 - Solicitada nova amostra para a China - amostra com o Bruno não está emitindo continuamente o sinal BT. Será enviada na sexta-feira, com isso a nova previsão de finalização da homologação fica para 30/10. 02/08 - Ensaios finalizam dia 10/08 e relatórios serão emitidos dia 16/08. 30/07 - Chega no CD 12/10 - Certificação estará finalizada por volta de 16/09. 02/07 - Amostra enviada para configuração. Previsão finalização dos testes: 11/08. Ready date: 20/08. 22/06 - Nova previsão de envio amostra: 25/06. Formalizado sobre a produção antes da finalização do teste - avaliar FAT. 03/06 - Chegada da amostra atualizada para 10/06. Com nosso schedule o ETA no CD seria 10/11. Fred pediu para liberar a MP 30/06 para pegar FAT 10. 26/05 - Sem notícias sobre as amostras e documentos de certificação, cobrei novamente. -- AMOSTRA NEXT MONDAY FRED 23/04 - Enviadas as instruções no ERP quanto a certificação. Cobrei a ISO. Para estar finalizado no embarque as amostras precisam ser enviadas até final de Maio - não recebi retorno | L68: Produto + Manual (ANATEL) | M68: Shenzhen Chenruixin Technology Co., Ltd | N68: 45186 | O68: =N68-90 -> 45096 | P68: MT-5549/2021 | Q68: 10134-21-10468 | R68: MASTER | S68: TRUE | T68: =IFERROR(__xludf.DUMMYFUNCTION("IFERROR(VLOOKUP(C68,IMPORTRANGE(""https://docs.google.com/spreadsheets/d/1RmEXtNg60OGvqZjyMxiYNPJ6S_kcz01v57qrHugDWVc/edit#gid=0"",""Chegadas!E:AQ""),19,0),"""")"),44505.0) -> 44505 | U68: Encerrado | V68: Este produto contém a placa 644563A_Y13 código de homologação ANATEL: 10134-21-10468 | W68: =N68 -> 45186
A69: IMAGINARIUM | B69: =HYPERLINK("https://imagens.imgnet.com.br/f/imaginarium/"&C69&";"&C69,image("https://imagens.imgnet.com.br/f/imaginarium/"&C69&"))")) | C69: PI5048Y | D69: 2021 - FAT10 | E69: Aiosa | F69: CAFETEIRA ELETRICA COM COPO 127V FRIENDS | G69: COMES E BEBES | H69: INMETRO Eletrodomésticos | I69: 2 amostras para ensaios na China | J69: 10/11/22 - Certificado encerrado. - 16/08 - Certificado de conformidade emitido. 21/07 - A correção solicitada pelo laboratório foi feita e foi recebido o draft dos laudos pelo OCP, vamos liberar a produção hoje. Informação Fred: ready date final de setembro, late FAT 11. 16/07 - O laboratório solicitou ao fabricante uma correção no PCB. 22/06 - Testes estão em andamento, previsão de finalização e análise: 19/07. Finalização produção: 30/09 06/06 - Auditoria feita e amostras coletas, considerando tudo pronto em 24/07. Posição Fred: If we start production 25/07, ready date is end of Sept, estimated DC ETA will be end of Nov(due to Oct holiday in China, ETD might be mid of Oct). So better if we can anticipate start production around 2 weeks; 25/05 - Previsão de recebermos a amostra final: 05/06. Seguindo com o agendamento da auditoria. 24/05 - Solicitado as demais informações técnicas. Questionei a Serena sobre a amostra final (agora só temos a amostra preta). 11/05 - Recebidos os documentos Considerar embarque 10/08 e certificado - 120 dias de cronograma, início se daria em 12/04 | L69: Produto + Embalagem (INMETRO) | N69: 44788 | O69: =N69-90 -> 44698 | P69: 6829/2021-ELE-1 | Q69: N/A | R69: BRICS OCP 0098 | S69: TRUE | T69: =IFERROR(__xludf.DUMMYFUNCTION("IFERROR(VLOOKUP(C69,IMPORTRANGE(""https://docs.google.com/spreadsheets/d/1RmEXtNg60OGvqZjyMxiYNPJ6S_kcz01v57qrHugDWVc/edit#gid=0"",""Chegadas!E:AQ""),19,0),"""")"),44505.0) -> 44505 | U69: Encerrado | V69: Certificação INMETRO:Produto certificado por BRICS OCP 0098 Nº Certificado 6829/2021-ELE-1 | W69: =N69 -> 44788
A70: IMAGINARIUM | B70: =HYPERLINK("https://imagens.imgnet.com.br/f/imaginarium/"&C70&";"&C70,image("https://imagens.imgnet.com.br/f/imaginarium/"&C70&"))")) | C70: PI5049Y | D70: 2021 - FAT10 | E70: Aiosa | F70: CAFETEIRA ELETRICA COM COPO 220V FRIENDS | G70: COMES E BEBES | H70: INMETRO Eletrodomésticos | I70: 2 amostras para ensaios na China | J70: 10/11/22 - Certificado encerrado. - 16/08 - Certificado de conformidade emitido. 21/07 - A correção solicitada pelo laboratório foi feita e foi recebido o draft dos laudos pelo OCP, vamos liberar a produção hoje. Informação Fred: ready date final de setembro, late FAT 11. 16/07 - O laboratório solicitou ao fabricante uma correção no PCB. 22/06 - Testes estão em andamento, previsão de finalização e análise: 19/07. Finalização produção: 30/09 06/06 - Auditoria feita e amostras coletas, considerando tudo pronto em 24/07. Posição Fred: If we start production 25/07, ready date is end of Sept, estimated DC ETA will be end of Nov(due to Oct holiday in China, ETD might be mid of Oct). So better if we can anticipate start production around 2 weeks; 25/05 - Previsão de recebermos a amostra final: 05/06. Seguindo com o agendamento da auditoria. 24/05 - Solicitado as demais informações técnicas. Questionei a Serena sobre a amostra final (agora só temos a amostra preta). 11/05 - Recebidos os documentos Considerar embarque 10/08 e certificado - 120 dias de cronograma, início se daria em 12/04 | L70: Produto + Embalagem (INMETRO) | N70: 44788 | O70: =N70-90 -> 44698 | P70: 6829/2021-ELE-1 | Q70: N/A | R70: BRICS OCP 0098 | S70: TRUE | T70: =IFERROR(__xludf.DUMMYFUNCTION("IFERROR(VLOOKUP(C70,IMPORTRANGE(""https://docs.google.com/spreadsheets/d/1RmEXtNg60OGvqZjyMxiYNPJ6S_kcz01v57qrHugDWVc/edit#gid=0"",""Chegadas!E:AQ""),19,0),"""")"),44505.0) -> 44505 | U70: Encerrado | V70: Certificação INMETRO:Produto certificado por BRICS OCP 0098 Nº Certificado 6829/2021-ELE-1 | W70: =N70 -> 44788
A71: IMAGINARIUM | B71: =HYPERLINK("https://imagens.imgnet.com.br/f/imaginarium/"&C71&";"&C71,image("https://imagens.imgnet.com.br/f/imaginarium/"&C71&"))")) | C71: PI5081Y | D71: 2021 - FAT11 | E71: Qikang | F71: KIT MIXER COM COPOS 127V AMARELO | G71: COMES E BEBES | H71: INMETRO Eletrodomésticos | I71: 5 amostras para ensaios na China | J71: 11/08/22 - Certificado encerrado. - 10/09 - Certificado de conformidade emitido. 08/09 - Solicitadas alterações no draft. 03/09 - Relatório oficial recebido. 30/08 - Laudo do teste recebido e está ok, informei para seguir com a MP. Brics está fechando o relatório de auditoria ara finalizar o processo. Aguardando confirmação de ready date, previsão de chegada atual: 17/01. 11/08 - Data estimada para finalização dos testes + análise dos laudos: 06/09. Ready date estimado: 10/11, item será FAT 01 por enquanto. 06/08 - Amostras entregues novamente ao laboratório, verificando schedule. 02/08 - Produto aprovado, verificando com o laboratório a situação dos primeiros testes, muito provavelmente Late FAT 1. 07/07 - ITEM CANCELADO - Problemas com Qualidade. 07/07 - Testes iniciaram hoje, previsão de finalização 02/08 - dentro do FAT. 23/06 - Auditoria agendada para o dia 2/7. 08/06 - Serena informou que a amostra final estará pronta em 30/06. 26/05 - Cobrei algumas informações sobre a fábrica para agendar a auditoria. Produto entrando na pauta da Criação hoje. 20/05 - Enviados os documentos para a BRICS, aguardando retorno. 10/05 - Cobrado documentos - sem retorno Considerar embarque 10/09 e certificado - 120 dias cronograma, início em Maio | L71: Produto + Embalagem (INMETRO) | N71: 44813 | O71: =N71-90 -> 44723 | P71: 6851/2021-ELE-1 | Q71: N/A | R71: BRICS OCP 0098 | S71: TRUE | T71: =IFERROR(__xludf.DUMMYFUNCTION("IFERROR(VLOOKUP(C71,IMPORTRANGE(""https://docs.google.com/spreadsheets/d/1RmEXtNg60OGvqZjyMxiYNPJ6S_kcz01v57qrHugDWVc/edit#gid=0"",""Chegadas!E:AQ""),19,0),"""")"),44566.0) -> 44566 | U71: Encerrado | V71: Certificação INMETRO:Produto certificado por BRICS OCP 0098 Nº Certificado 6851/2021-ELE-1 | W71: =N71 -> 44813
A72: IMAGINARIUM | B72: =HYPERLINK("https://imagens.imgnet.com.br/f/imaginarium/"&C72&";"&C72,image("https://imagens.imgnet.com.br/f/imaginarium/"&C72&"))")) | C72: PI5082Y | D72: 2021 - FAT11 | E72: Qikang | F72: KIT MIXER COM COPOS 220V AMARELO | G72: COMES E BEBES | H72: INMETRO Eletrodomésticos | I72: 5 amostras para ensaios na China | J72: 11/08/22 - Certificado encerrado. - 10/09 - Certificado de conformidade emitido. 08/09 - Solicitadas alterações no draft. 03/09 - Relatório oficial recebido. 30/08 - Laudo do teste recebido e está ok, informei para seguir com a MP. Brics está fechando o relatório de auditoria ara finalizar o processo. Aguardando confirmação de ready date, previsão de chegada atual: 17/01. 11/08 - Data estimada para finalização dos testes + análise dos laudos: 06/09. Ready date estimado: 10/11, item será FAT 01 por enquanto. 06/08 - Amostras entregues novamente ao laboratório, verificando schedule. 02/08 - Produto aprovado, verificando com o laboratório a situação dos primeiros testes, muito provavelmente Late FAT 1. 07/07 - ITEM CANCELADO - Problemas com Qualidade. 07/07 - Testes iniciaram hoje, previsão de finalização 02/08 - dentro do FAT. 23/06 - Auditoria agendada para o dia 2/7. 08/06 - Serena informou que a amostra final estará pronta em 30/06. 26/05 - Cobrei algumas informações sobre a fábrica para agendar a auditoria. Produto entrando na pauta da Criação hoje. 20/05 - Enviados os documentos para a BRICS, aguardando retorno. 10/05 - Cobrado documentos - sem retorno Considerar embarque 10/09 e certificado - 120 dias cronograma, início em Maio | L72: Produto + Embalagem (INMETRO) | N72: 44813 | O72: =N72-90 -> 44723 | P72: 6851/2021-ELE-1 | Q72: N/A | R72: BRICS OCP 0098 | S72: TRUE | T72: =IFERROR(__xludf.DUMMYFUNCTION("IFERROR(VLOOKUP(C72,IMPORTRANGE(""https://docs.google.com/spreadsheets/d/1RmEXtNg60OGvqZjyMxiYNPJ6S_kcz01v57qrHugDWVc/edit#gid=0"",""Chegadas!E:AQ""),19,0),"""")"),44566.0) -> 44566 | U72: Encerrado | V72: Certificação INMETRO:Produto certificado por BRICS OCP 0098 Nº Certificado 6851/2021-ELE-1 | W72: =N72 -> 44813
A73: IMAGINARIUM | B73: =HYPERLINK("https://imagens.imgnet.com.br/f/imaginarium/"&C73&";"&C73,image("https://imagens.imgnet.com.br/f/imaginarium/"&C73&"))")) | C73: PI5097Y | D73: 2021 - FAT10 | E73: Audmic | F73: MESA SPEAKER E CARREGADOR SEM FIO CINZA | G73: TECH | H73: ANATEL CATEGORIA 2 - MÓDULO BLUETOOTH | I73: 2 Amostras completas + 1 Amostra teste lab (Placa PCB com entradas de cabo de RF e Software) | J73: 11/09/25 - Decidiram não fazer a manutenção desse certificado e farão ações para acabar com o estoque antes de 30/11/2025. 10/01/24 - Recebemos o certificado de homologação ANATEL, processo finalizado. 27/11/23 - Manutenção finalizada, aguardamos submissão no sistema da Anatel. 27/10/23 - Foi decidido que vamos fazer a manutenção desse certificado. 03/01 - Homologação Anatel finalizada. 30/11 - Processo cadastrado na Anatel. Em análise. 08/11 - Demos o ok dos ensaios para a China. Aguardamos as fotos para enviar ao OCD verificar se ocorreu alteração no circuito de alimentação (caso sim, precisará ser testado novamente). 05/11 - Laudo dos ensaios recebidos. 21/10 - Iniciando MP em 03/11, ready date seria 23/12. Previsão FAT02~03. 18/10 - Teste de compatibilidade eletrogmagnética ok, aguardando data para finalização dos testes de RF (bluetooth) para recebimento dos laudos completos. 06/10 - Nova amostra está no laboratório, previsão de entrega dos laudos: 18/10. Pelo schedule seria FAT 3. 14/09 - Nova amostra será enviada na sexta-feira via FedEx. Previsão de chegada no CD: 16/03. 30/08 - Previsão do fornecedor de envio de nova amostra: 10/09. Com esta data a previsão de finalização dos testes é 26/10 e o item seria FAT 2. 17/08 - Item apresentou falha novamente, Bruno irá retirar a amostra para análise e configuração, e verificar se vamos precisar de uma nova amostra da China. 04/08 - Modelo apresentou ocorrência no teste de Emissão Radiada. Solicitamos teste em câmara 3m, finalização 12/08. 29/07 - According to the new certification schedule, MP estimated finished 25/9, will be able to catch late FAT11. 28/07 - Reteste será feito até dia 30/07, Bruno coletará a amostra para configurar para os testes de RF, que tem previsão de ficarem prontos em 10/08. Verificando com Vincent quanto a MP / schedule. 23/07 - O laboratório não deveria ter sido exercitada a função "carregamento indutivo" durante o ensaio de Emissão Radiada. Solicitamos um reteste com a reprodução de músicas somente através da tecnologia Bluetooth, sem estar carregando indutivamente em aparelho celular (configuração solicitada no RT). 15/07 - Eldorado: Em uma segunda tentativa de solda, a amostra parou de funcionar e não respondeu a mais nenhum comando. Precisamos esperar a finalização dos testes (22/07) para coletar e preparar novamente a amostra de RF. 24/06 - Amostra será entregue na quarta-feira no Lab. Agenda: início 13/07, finalização e entrega dos laudos: 20/07. 18/06 - Amostra enviada: 774035122117. Previsão de finalização dos testes: 01/08+40 dias leadtime: 19/11 Br. 08/06 - Solicitado ao Vincent update sobre o item - sem info 25/05 -Paulo:Com o cronograma que temos, caso não seja possível encontrar rapidamente um fornecedor pronto para nos fornecer, precisamos considerar que o item terá seu lançamento POSTERGADO para uma coleção futura. 24/05 - Cobrei novamente sobre informações e a amostra da qualidade. Vi: sorry for lack of reply on this task about this item, for this item , we are still not sure about which supplier is the best option we could go on . we also haven't choose the model yet . the certication process would be on hold for now once we have further news would let you know. 10/05 - Cobrado sobre a ISO novamente - ainda não tive retorno. 23/04 - Enviada as instruções no ERP quanto a certificação. Cobrei a ISO. Para estar finalizado no embarque as amostras precisam ser enviadas até final de Junho. | K73: 45911 | L73: Produto + Manual (ANATEL) | M73: Shenzhen Ao Lai De Electronic Co., Ltd | N73: 45991 | O73: =N73-90 -> 45901 | P73: MODERNA-2323/23 | Q73: 11136-21-14089 | R73: MODERNA | S73: TRUE | T73: =IFERROR(__xludf.DUMMYFUNCTION("IFERROR(VLOOKUP(C73,IMPORTRANGE(""https://docs.google.com/spreadsheets/d/1RmEXtNg60OGvqZjyMxiYNPJ6S_kcz01v57qrHugDWVc/edit#gid=0"",""Chegadas!E:AQ""),19,0),"""")"),44717.0) -> 44717 | U73: Encerrado | V73: Produto homologado pela Anatel: Nº Homologação 11136-21-14089 | W73: =IFERROR(IF(U73="Ativo","Ativo",IF(U73="SKU excluído","Vencido",VLOOKUP(C73,Encerramentos!B:G,6,0))),"") -> 45991
A74: IMAGINARIUM | B74: =HYPERLINK("https://imagens.imgnet.com.br/f/imaginarium/"&C74&";"&C74,image("https://imagens.imgnet.com.br/f/imaginarium/"&C74&"))")) | C74: PI5103Y | D74: 2021 - FAT10 | E74: Freesun | F74: PROJETOR PORTATIL NETFLIX VERMELHO | G74: TECH | H74: ANATEL CATEGORIA 2 - MÓDULO BLUETOOTH | I74: 2 Amostras completas + 1 Amostra teste lab (Placa PCB com entradas de cabo de RF e Software) | J74: 19/01/23 - Projetores estão sem estoque no CD, certificado não será renovado. - 07/06 - Vamos seguir com a certificação do módulo do projetor anterior. 23/04 - Verificando se vamos utilizar a mesma placa do projetor anterior. Feeling informou que o projeto está parado até os problemas do projetor serem ajustados - Paulo está ciente. | L74: Produto + Manual (ANATEL) | N74: 45058 | O74: =N74-90 -> 44968 | P74: MT-5268/2021 | Q74: 03906-21-13799 | S74: TRUE | T74: =IFERROR(__xludf.DUMMYFUNCTION("IFERROR(VLOOKUP(C74,IMPORTRANGE(""https://docs.google.com/spreadsheets/d/1RmEXtNg60OGvqZjyMxiYNPJ6S_kcz01v57qrHugDWVc/edit#gid=0"",""Chegadas!E:AQ""),19,0),"""")"),44505.0) -> 44505 | U74: Encerrado | V74: Este produto contém a placa PI4764Y código de homologação ANATEL 03906-21-13799 | W74: =N74 -> 45058
A75: IMAGINARIUM | B75: =HYPERLINK("https://imagens.imgnet.com.br/f/imaginarium/"&C75&";"&C75,image("https://imagens.imgnet.com.br/f/imaginarium/"&C75&"))")) | C75: PI5118Y | D75: 2021 - FAT10 | E75: Ed Origin | F75: AROMATIZADOR SPEAKER INSPIRASOM | G75: CASA E DECORAÇÃO | H75: INMETRO Eletrodomésticos + ANATEL CATEGORIA 2 - MÓDULO BLUETOOTH | I75: 2 amostras para ensaios na China + 2 Amostras completas + 1 Amostra teste lab (Placa PCB com entradas de cabo de RF e Software) | J75: 10/08/22 - Certificado encerrado. - 06/09 - Homologação Anatel finalizada. 26/08 - Emitido o certificado de conformidade do Inmetro. Anatel em análise, previsão era 30/08 mas está levando mais tempo que o normal. Chegada estimada no CD: 09/11. 05/08 - Processo cadastrado na Anatel, previsão de homologação: 30/08. Certificado final do Inmetro será recebido semana que vem. 02/08 - Processo será cadastrado na Anatel esta semana. Aguardnado resultado Inmetro. 19/07 - Ensaios ANATEL finalizados hoje, emissão dos laudos prevista para 21/07. 13/07 - Previsão de finalização dos ensaios Inmetro: 05/08. 28/06 - Auditoria (Inmetro) agendada para 08/07. Finalização dos testes Anatel: 21/07. Finalização produção 10/09. 22/06 - Considerando a data de análise do relatório Inmetro 09/08, ready date estimado seria 10/09. 18/06 - Amostra Anatel está na Eagle Tech para configuração -- verificando agenda. / Inmetro: BRICS está aguardando ok da fábrica para seguir com a auditoria. Atualização FAT p/ 11. 31/05 - Anatel tests should be ready around 01/08/2021 (with sample arrival by mid June), Inmetro tests, around 22/07. If we start production by 01/08, ready date around Sept.10th. Estimated DC ETA end of Oct, beginning of Nov. So please check if we could anticipate the start production around 2 weeks. 24/05 - Cobrei novamente os documentos e amostras. Vi: got it , supplier is preparing , due to the lack of chip and component problem on this product , they do a confirmation on every material first before taking our order , it took around 1-2 week delay on this documents and sample . now base on the feedback they gave me yesterday , the schedule for received the samples and the docs will be within this week . 10/05 - Cobrei documentos e amostras - não tive retorno. 28/04 - Confirmado função BT, enviada a instrução de certificação no ERP. Para eletro, considerar embarque 10/08 e certificado - 120 dias de cronograma, início em Maio o e para Anatel as amostras pecisam ser enviadas até o final de Maio. | L75: Produto + Manual (ANATEL) | N75: 25/08/2022 04/08/2023 | O75: 44708 | P75: 6906-2021-ELE-1 MT-5590/2021 | Q75: 11135-21-12612 | R75: BRICS OCP 0098 | S75: TRUE | T75: =IFERROR(__xludf.DUMMYFUNCTION("IFERROR(VLOOKUP(C75,IMPORTRANGE(""https://docs.google.com/spreadsheets/d/1RmEXtNg60OGvqZjyMxiYNPJ6S_kcz01v57qrHugDWVc/edit#gid=0"",""Chegadas!E:AQ""),19,0),"""")"),44505.0) -> 44505 | U75: Encerrado | V75: Certificação INMETRO:Produto certificado por BRICS OCP 0098 Nº Certificado 6906-2021-ELE-1 Este produto contém a placa PI5118Y código de homologação ANATEL 11135-21-12612 | W75: =N75 -> 25/08/2022 04/08/2023
A76: IMAGINARIUM | B76: =HYPERLINK("https://imagens.imgnet.com.br/f/imaginarium/"&C76&";"&C76,image("https://imagens.imgnet.com.br/f/imaginarium/"&C76&"))")) | C76: PI5112Y | D76: 2021 - FAT10 | E76: Huazeng | F76: AMPLIFICADOR PORTA CELULAR NETFLIX TV | G76: TECH | H76: ANATEL CATEGORIA 2 - MÓDULO BLUETOOTH | I76: 2 Amostras completas + 1 Amostra teste lab (Placa PCB com entradas de cabo de RF e Software) | J76: 27/10/23 - O certificado não será renovado. - 02/12 - Homologação Anatel finalizada. 04/11 - Processo cadastrado na Anatel. 29/10 - Laudos recebidos. Testes ok. 05/10 - Agenda recebida, previsão de entrega dos relatórios: 20/10. Previsão de finalização: 17/12 (FAT 01). 14/09 - A bateria compatível será enviada sexta-feira, junto com a amostra do PI5097Y. Previsão de finalização da homologação: 19/11. Previsão de chegada no CD: 05/11 (produto não será liberado para venda antes de FAT 01). 10/09 - A nova amostra não funcionou, e a fábrica informou que talvez seja necessário alimentar a placa através de uma bateria, porém, não enviaram uma bateria compatível. 30/08 - Previsão do início dos testes: 13/09, entrega dos relatórios 23/09. Previsão de finalização da homologação: 12/11. Processo foi antecipado, previsão de chegada no CD: 29/10. 26/08 - Amostra enviada para configuração. Previsão de entrega no laboratório: 31/08. 19/08 - Amostra enviada, AWB 774575803482. 16/08 - Nova amostra será enviada na sexta-feira, já que a amostra coletada no laboratório para testes de RF não está funcionando devidamente. Produção em paralelo e certificação deve estar finalizada para FAT 11. 02/08 - Solicitada nova amostra de RF, previsão de finalização: 30/09. 19/07 - Finalização dos testes prevista para 22/07. 14/07 - Eldorado: Informo que o André Favaron, do meu Comercial, autorizou a repetir o ensaio de Emissão Radiada alimentando o produto com um Notebook. 02/07 - Laboratório informou que o equipamento apresentou ocorrência no ensaio de Emissão Radiada do Ato Anatel 1120. Solicitamos ao laboratório, de acordo com orientações do Bruno, reteste do equipamento com alimentação via laptop utilizando a câmara de 3 metros. 22/06 - MP pode ser iniciada antes da finalização dos ensaios (01/07). 08/07 - Amostra chegou ontem em SP, enviadas para a Eagle Tech seguir com a configuração -- Agenda recebida, testes finalizados em 01/07 (antecipado 2 semanas em relação ao schedule inicial). Verificar schedule com Fred. 24/05 - Documentos recebidos - FAT postergado para 11. 21/05 - Enviada nova amostra + test mode, FEDEX 773786818334 / 773786818595 - 11/05 - Paulo aprovou a amostra ontem, Vincent nos atualizará sobre envio estimado amanhã. 10/05 - Cobrei documentos e amostras. 23/04 - Vincent informou que o fabricante da placa não tem ISO, apenas a Huazeng. Para estar finalizado no embarque as amostras precisam ser enviadas até final de Maio. | L76: Produto + Manual (ANATEL) | M76: Shenzhen Huazeng Technology Co., Ltd | N76: 45234 | O76: =N76-90 -> 45144 | P76: MT-5494/2021 | Q76: 08885-21-12851 | S76: TRUE | T76: =IFERROR(__xludf.DUMMYFUNCTION("IFERROR(VLOOKUP(C76,IMPORTRANGE(""https://docs.google.com/spreadsheets/d/1RmEXtNg60OGvqZjyMxiYNPJ6S_kcz01v57qrHugDWVc/edit#gid=0"",""Chegadas!E:AQ""),19,0),"""")"),44505.0) -> 44505 | U76: Encerrado | V76: Este produto contém a placa PI5112Ycódigo de homologação ANATEL 08885-21-12851 | W76: =N76 -> 45234
A77: IMAGINARIUM | B77: =HYPERLINK("https://imagens.imgnet.com.br/f/imaginarium/"&C77&";"&C77,image("https://imagens.imgnet.com.br/f/imaginarium/"&C77&"))")) | C77: PI5101Y | D77: 2021 - FAT10 | E77: Huazeng | F77: MICROFONE KARAOKE BLUETOOTH DANDO SHOW | G77: TECH | H77: INMETRO SISTEMA 7 (LOTE) - PORTARIA 321 + ANATEL CATEGORIA 2 - MÓDULO BLUETOOTH | I77: 2 Amostras completas + 1 Amostra teste lab (Placa PCB com entradas de cabo de RF e Software) + RAM | J77: 20/03/23 - O certificado não será renovado. - 07/10 - LI deferida. 04/10 - Certificado de Conformidade emitido (revisado). Aguardando o certificado estar ativo no Orquestra para solicitar a anuência da LI. 13/09 - Testes em andamento. Previsão de chegada no CD: 05/11. 03/09 - Coleta agendada para 08/09. Previsão de emissão do certificado: 07/10. Previsão de chegada no CD: 29/10. 26/08 - Coleta agendada para 02/09. Previsão de finalização: 13/10, chegada no CD prevista para 21/10. 24/08 - Coleta da Brics estava agendada para amanhã, porém foram informados que o lote ainda não está pronto (retrabalhos do cabo). 19/08 - Processo cadastrado na Anatel. Em análise. 16/08 - Emitido laudo Anatel, sob análise da Engenharia da Master. Devido a retrabalho realizado no cabo do microfone, lote estará pronto no dia 25/08, será coletado neste dia para testes do Inmetro. 11/08 - Relatório foi postergado, mas testes Anatel foram finalizados sem ocorrência. Coleta das amostras do Inmetro serão no dia 18/08 (dia que o lote estará pronto). 21/07 - Vamos dar sequência com os testes que faltam em outro laboratório, encaminhamos a amostra hoje. Finalização dos ensaios: 05/08. Data envio relatório: 11/08. 02/07 - Ocorrem duas falhas no teste: emissões espúrias e ESD. 22/06 - MP pode ser iniciada antes da finalização dos ensaios (01/07), finalização do lote prevista para 10/08. 08/07 - Amostra chegou ontem em SP, enviadas para a Eagle Tech seguir com a configuração -- Recebemos a agenda, testes estarão finalizados em 1/07 (foi antecipada aprox. 2 semanas). Checar com Fred novamente o schedule. 21/05 - Enviada nova amostra + test mode, a enviada em 14/05 não está com a placa correta. FEDEX 773786818334 / 773786818595 11/05 - Paulo: amostra aprovada com restrição, por conta de instabilidade na conexão Bluetooth. Será enviada amostra para aprovação do time da Qualidade. 10/05 - Cobrei documentos e amostras. 23/04 - Enviada as instruções no ERP quanto a certificação. Considerando embarque 10/08 e certificado - 100 dias de cronograma, dar início ao processo em Maio o e para Anatel as amostras pecisam ser enviadas até o final de Maio. | L77: Produto + Manual (ANATEL) | N77: 45156 | O77: =N77-90 -> 45066 | P77: 6916-2021-BRI-1 MT-5493/2021 | Q77: 08884-21-12851 | R77: BRICS OCP 0098 | S77: TRUE | T77: =IFERROR(__xludf.DUMMYFUNCTION("IFERROR(VLOOKUP(C77,IMPORTRANGE(""https://docs.google.com/spreadsheets/d/1RmEXtNg60OGvqZjyMxiYNPJ6S_kcz01v57qrHugDWVc/edit#gid=0"",""Chegadas!E:AQ""),19,0),"""")"),44474.0) -> 44474 | U77: Encerrado | V77: Certificação INMETRO:Produto certificado por BRICS OCP 0098 CE-BRI/BRICS 001180-20. Produto homologado pela Anatel: Nº Homologação 08884-21-12851 | W77: =N77 -> 45156
A78: IMAGINARIUM | B78: =HYPERLINK("https://imagens.imgnet.com.br/f/imaginarium/"&C78&";"&C78,image("https://imagens.imgnet.com.br/f/imaginarium/"&C78&"))")) | C78: PI5040Y | D78: 2021 - FAT11 | E78: Yongkang Aining | F78: MAQUINA DE DONUTS 127V VERDE MENTA | G78: COMES E BEBES | H78: INMETRO Eletrodomésticos | I78: 2 amostras para ensaios na China | J78: 10/08/22 - Certificado encerrado. - 26/08 - Certificado de Conformidade emitido. 18/08 - Serena: Após negociação, fornecedor concordou em finalizar a produção antes do dia 20/10, então pegaremos Lafe FAT 12. 11/08 - Serena informou que a produção deve finalizar no final de Outubro. Questionei pois considerando este schedule, produto viraria FAT 01. 10/08 - Draft dos laudos recebido e aprovado pela BRICS. 02/08 - Solicitei os drafts dos laudos para a Brics, com o ok do OCP damos andamento na mass production. 07/07 - Laboratório passou a previsão de finalização dos testes: 02/08. Contando que a BRICS analise os drafts e nos de o ok, ficamos dentro do schedule. 30/06 - Auditoria e coleta das amostras agendadas para 03/07. 18/06 - Serena informou que a amostra deve estar ok 28/06, considerando leadtime 60 dias, Br: 22/12. 08/06 - Serena informou que amostra deve estar ok 24/06. Serena: We changed supplier and shape of product. Today I received the sample to test quality, and will send the docs to creation team to do artwork. We need to receive the artwork soon. 24/05 - Amostra está atrasada, deve chegar no escritório 30/05. 18/05 - Cobrei update. 11/05 - Serena: Não foi confirmado qual item irão comprar, receberemos os documentos apenas após esta confirmação. O Paulo ia testar hoje a amostra que o fornecedor envia antes de fecharmos a compra e depois vão enviar para a Qualidade. 10/05 - Cobrei documentos e amostras. Considerar embarque 10/09 e certificado - 120 dias cronograma, início em Maio | L78: Selo de certificação na embalagem e no produto | N78: 44799 | O78: =N78-90 -> 44709 | P78: 6927/2021-ELE-1 | Q78: NA | R78: BRICS OCP 0098 | S78: TRUE | T78: =IFERROR(__xludf.DUMMYFUNCTION("IFERROR(VLOOKUP(C78,IMPORTRANGE(""https://docs.google.com/spreadsheets/d/1RmEXtNg60OGvqZjyMxiYNPJ6S_kcz01v57qrHugDWVc/edit#gid=0"",""Chegadas!E:AQ""),19,0),"""")"),44535.0) -> 44535 | U78: Encerrado | V78: Certificação INMETRO:Produto certificado por BRICS OCP 0098 Nº Certificado 6927-2021-ELE-1 | W78: =N78 -> 44799
A79: IMAGINARIUM | B79: =HYPERLINK("https://imagens.imgnet.com.br/f/imaginarium/"&C79&";"&C79,image("https://imagens.imgnet.com.br/f/imaginarium/"&C79&"))")) | C79: PI5041Y | D79: 2021 - FAT11 | E79: Yongkang Aining | F79: MAQUINA DE DONUTS 220V VERDE MENTA | G79: COMES E BEBES | H79: INMETRO Eletrodomésticos | I79: 2 amostras para ensaios na China | J79: 10/08/22 - Certificado encerrado. - 26/08 - Certificado de Conformidade emitido. 18/08 - Serena: Após negociação, fornecedor concordou em finalizar a produção antes do dia 20/10, então pegaremos Lafe FAT 12. 11/08 - Serena informou que a produção deve finalizar no final de Outubro. Questionei pois considerando este schedule, produto viraria FAT 01. 10/08 - Draft dos laudos recebido e aprovado pela BRICS. 02/08 - Solicitei os drafts dos laudos para a Brics, com o ok do OCP damos andamento na mass production. 07/07 - Laboratório passou a previsão de finalização dos testes: 02/08. Contando que a BRICS analise os drafts e nos de o ok, ficamos dentro do schedule. 30/06 - Auditoria e coleta das amostras agendadas para 03/07. 18/06 - Serena informou que a amostra deve estar ok 28/06, considerando leadtime 60 dias, Br: 22/12. 08/06 - Serena informou que amostra deve estar ok 24/06. Serena: We changed supplier and shape of product. Today I received the sample to test quality, and will send the docs to creation team to do artwork. We need to receive the artwork soon. 24/05 - Amostra está atrasada, deve chegar no escritório 30/05. 18/05 - Cobrei update. 11/05 - Serena: Não foi confirmado qual item irão comprar, receberemos os documentos apenas após esta confirmação. O Paulo ia testar hoje a amostra que o fornecedor envia antes de fecharmos a compra e depois vão enviar para a Qualidade. 10/05 - Cobrei documentos e amostras. Considerar embarque 10/09 e certificado - 120 dias cronograma, início em Maio | L79: Selo de certificação na embalagem e no produto | N79: 44799 | O79: =N79-90 -> 44709 | P79: 6927/2021-ELE-1 | Q79: NA | R79: BRICS OCP 0098 | S79: TRUE | T79: =IFERROR(__xludf.DUMMYFUNCTION("IFERROR(VLOOKUP(C79,IMPORTRANGE(""https://docs.google.com/spreadsheets/d/1RmEXtNg60OGvqZjyMxiYNPJ6S_kcz01v57qrHugDWVc/edit#gid=0"",""Chegadas!E:AQ""),19,0),"""")"),44535.0) -> 44535 | U79: Encerrado | V79: Certificação INMETRO:Produto certificado por BRICS OCP 0098 Nº Certificado 6927-2021-ELE-1 | W79: =N79 -> 44799
A80: IMAGINARIUM | B80: =HYPERLINK("https://imagens.imgnet.com.br/f/imaginarium/"&C80&";"&C80,image("https://imagens.imgnet.com.br/f/imaginarium/"&C80&"))")) | C80: PI5046Y | D80: 2021 - FAT11 | E80: Aubadi | F80: MOUSE SEM FIO GLITTER MANDA JOBS | G80: TECH | H80: ANATEL CATEGORIA 2 - MÓDULO BLUETOOTH | I80: 2 Amostras completas + 1 Amostra teste lab (Placa PCB com entradas de cabo de RF e Software) | J80: 20/03/23 - O certificado não será renovado. - 14/03 - Aguardando retorno do Planejamento sobre manutenção (custo adicional). 07/03 - Aguardando retorno do Planejamento sobre manutenção (custo adicional). 13/02 - Cobramos atualização. 08/02 - Enviado documento da auditoria solicitado pelo fabricante. 06/02 - Verificando quanto à realização da auditoria remota. 31/01 - Cobramos os documentos do OCD. 10/01 - Vamos fazer a manutenção do certificado. - 08/06 - Homologação Anatel finalizada. Homologação finalizada, aguardando confirmação da cor do novo modelo para submeter novamente Aguardando finalização da homologação dos mouses antigos para incusão de cor 27/04 - Vincent confirmou que o item possui a mesma placa dos mouses anteriores. Precisamos das fotos para fazer a validação com a OCP da inclusão na mesma família até dia 30/05 (certificado dos demais mouses deve sair dia 15/05 - Fornecedor não possui ISO) | L80: Produto + Manual (ANATEL) | N80: 45038 | O80: =N80-90 -> 44948 | P80: MT-5057/2020 | Q80: 14600-20-13387 | S80: FALSE | T80: =IFERROR(__xludf.DUMMYFUNCTION("IFERROR(VLOOKUP(C80,IMPORTRANGE(""https://docs.google.com/spreadsheets/d/1RmEXtNg60OGvqZjyMxiYNPJ6S_kcz01v57qrHugDWVc/edit#gid=0"",""Chegadas!E:AQ""),19,0),"""")"),44505.0) -> 44505 | U80: Encerrado | V80: Produto homologado pela Anatel: Nº Homologação 14600-20-13387 | W80: =N80 -> 45038
A81: IMAGINARIUM | B81: =HYPERLINK("https://imagens.imgnet.com.br/f/imaginarium/"&C81&";"&C81,image("https://imagens.imgnet.com.br/f/imaginarium/"&C81&"))")) | C81: PI4368Y | D81: 2020 - FAT08 | E81: Hesen | F81: ALMOFADA SONORA HP CHAPEU SELETOR | G81: CASA E DECORAÇÃO | H81: INMETRO SISTEMA 7 (LOTE) - PORTARIA 321 | I81: Amostras enviadas para laboratório, aguardando finalização dos ensaios laboratoriais | J81: 26/07 - LI deferida. 06/07 - Recebemos o certificado de conformidade. Itens já estão com as marcações necessárias na embalagem. Processo chega no Brasil 06/08. 06/06 - MP vai ser finalizada 10/06, coleta das amostras agendadas para 11/06. Finalização prevista para 06/07, chega 31/07 no Br. 02/06 - Coleta agendada para 15/06. 21/05 - A coleta das amostras para teste seria feita em 22/05 mas ocorreu um problema na produção e estamos aguardando o desfecho para seguir. | L81: Produto + Embalagem (INMETRO) | N81: Até o final do lote | O81: Sem auditoria - lote | P81: 6788/2021-BRI | Q81: NA | R81: BRICS OCP 0098 | S81: TRUE | T81: =IFERROR(__xludf.DUMMYFUNCTION("IFERROR(VLOOKUP(C81,IMPORTRANGE(""https://docs.google.com/spreadsheets/d/1RmEXtNg60OGvqZjyMxiYNPJ6S_kcz01v57qrHugDWVc/edit#gid=0"",""Chegadas!E:AQ""),19,0),"""")"),"") | U81: Encerrado | V81: Certificação INMETRO:Produto certificado por BRICS OCP 0098 CE-BRI/BRICS 001180-20 | W81: =N81 -> Até o final do lote
A82: IMAGINARIUM | B82: =HYPERLINK("https://imagens.imgnet.com.br/f/imaginarium/"&C82&";"&C82,image("https://imagens.imgnet.com.br/f/imaginarium/"&C82&"))")) | C82: PI4669Y | D82: 2021 - FAT10 | E82: Wallesun | F82: AROMATIZADOR E UMIDIFICADOR NO AR | G82: CASA E DECORAÇÃO | H82: INMETRO Eletrodomésticos | I82: 3 amostras para ensaios no Brasil | J82: 14/10 - Certificado de conformidade emitido. 20/09 - Draft do certificado emitido, aguardando assinatura. 14/09 - Item embarcou dia 09/09, previsão de chegada no CD: 18/10. Aguardando revisão do relatório de testes oficial para emissão do certificado. 31/08 - Previsão de chegada no CD atualizada para 21/10. 11/08 - LI emitida, aguardando embarque para emissão do certificado final. Produto chega no CD 08/10. 30/07 - Produto chega no CD em 01/10 - aguardando emissão dos laudos. 20/07 - Pré-teste realizado: concluímos que o produto atende aos requisitos de segurança especificados por norma. 07/07 - Amostras enviadas para o responsável no laboratório - Tracking 774190128887. 29/06 - Ficou acordado com a BRICS que os testes preliminares não serão cobrados. Informado endereço de destino das amostras ao Vincent, aguardando informação de produção e leadtime. 18/06 - Amostra aprovada. Vamos seguir com a certificação de lote, pois a Wallesun não tem os requisitos para atender a uma auditoria de fábrica. Solicitei ao Vincent sobre as amostras a serem enviadas para o BR (precisamos de 3, 2 para os testes + 1 para o relatório preliminar) e questionei sobre a previsão de finalização da MP. Aguardando definição | L82: Produto + Embalagem (INMETRO) | N82: Até o final do lote | O82: Sem auditoria - lote | P82: 6926/2021-ELE-1 | Q82: NA | R82: BRICS OCP 0098 | S82: FALSE | T82: =IFERROR(__xludf.DUMMYFUNCTION("IFERROR(VLOOKUP(C82,IMPORTRANGE(""https://docs.google.com/spreadsheets/d/1RmEXtNg60OGvqZjyMxiYNPJ6S_kcz01v57qrHugDWVc/edit#gid=0"",""Chegadas!E:AQ""),19,0),"""")"),44474.0) -> 44474 | U82: Encerrado | V82: Certificação INMETRO:Produto certificado por BRICS OCP 0098 Nº Certificado 6356/2020-ELE | W82: =N82 -> Até o final do lote
A83: IMAGINARIUM | B83: =HYPERLINK("https://imagens.imgnet.com.br/f/imaginarium/"&C83&";"&C83,image("https://imagens.imgnet.com.br/f/imaginarium/"&C83&"))")) | C83: PI5080Y | D83: 2021 - FAT11 | E83: 3Rd Eye | F83: LUMINARIA COM SPEAKER BLUETOOTH SORVETE | G83: TECH | H83: ANATEL CATEGORIA 2 - MÓDULO BLUETOOTH | I83: 2 Amostras completas + 1 Amostra teste lab (Placa PCB com entradas de cabo de RF e Software) | J83: 18/09/23 - Certificado suspenso. 25/05/23 - O certificado não será renovado. - 08/10 - Certificado de homologação Anatel emitido. 20/09 - Processo cadastrado na Anatel. 10/09 - Recebidos o laudo dos ensaios. Previsão de finalização da homologação: 17/10. Chegada CD: 12/11 02/09 - Ensaios finalizados sem ocorrências, aguardando laudo para finalização do processo. Previsão de finalização da homologação: 23/10. Previsão de chegada no CD: 08/11. 23/08 - Segundo Ibec, ensaios serão finalizados até 02/09, e relatório está previsto para 08/09. Previsão de finalização da homologação: 20/10. 18/08 - Amostra enviada para configuração, verificando agenda com os laboratórios. Previsão de finalização da homologação: 30/10. Produção em paralelo. 09/08 - Amostra enviada, AWB 774478000032. 02/08 - Solicitado amostras (previsão prontidão final de Julho). Previsão de finalização 30/09. | L83: Produto + Manual (ANATEL) | M83: Shenzhen Chenruixin Technology Co., Ltd | N83: 45186 | O83: =N83-90 -> 45096 | P83: MT-5613/2021 | Q83: 12071-21-10468 | R83: MASTER | S83: TRUE | T83: =IFERROR(__xludf.DUMMYFUNCTION("IFERROR(VLOOKUP(C83,IMPORTRANGE(""https://docs.google.com/spreadsheets/d/1RmEXtNg60OGvqZjyMxiYNPJ6S_kcz01v57qrHugDWVc/edit#gid=0"",""Chegadas!E:AQ""),19,0),"""")"),44505.0) -> 44505 | U83: Encerrado | V83: Este produto contém a placa AZ-F12 código de homologação ANATEL: 12071-21-10468 | W83: =N83 -> 45186
A84: IMAGINARIUM | B84: =HYPERLINK("https://imagens.imgnet.com.br/f/imaginarium/"&C84&";"&C84,image("https://imagens.imgnet.com.br/f/imaginarium/"&C84&"))")) | C84: PI5143Y | D84: 2022 - FAT01 | E84: Gain Belong | F84: MAQUINA DE WAFFLE 127V STRANGER THINGS | G84: COMES E BEBES | H84: INMETRO Eletrodomésticos | I84: 2 amostras para ensaios na China | J84: 10/08/22 - Certificado encerrado. - 20/09 - Certificado Inmetro emitido. 14/09 - Certificado está para assinatura. 18/08 - Finalização dos testes atualizada para 13/09 - Late FAT 01. 10/08 - Auditoria realizada em 03/08, relatório sob análise. Amostras chegaram ao laboratório no dia 06/08 e a previsão de finalização dos testes é 01/09. 28/07 - Serena informou que amostra deve estar ok para coleta dia 03/08. 05/07 - Recebidos os documentos, aguardando retorno da BRICS referente a data de auditoria. Serena informou que o item será Late FAT 01. 18/06 - Amostra deve estar pronta em 28/07 17/06 - Aguardando retorno do fornecedor sobre prontidão da amostra até 18/06 | L84: Produto + Embalagem (INMETRO) | N84: 44823 | O84: =N84-90 -> 44733 | P84: 6994/2021-ELE-1 | Q84: NA | R84: BRICS OCP 0098 | S84: TRUE | T84: =IFERROR(__xludf.DUMMYFUNCTION("IFERROR(VLOOKUP(C84,IMPORTRANGE(""https://docs.google.com/spreadsheets/d/1RmEXtNg60OGvqZjyMxiYNPJ6S_kcz01v57qrHugDWVc/edit#gid=0"",""Chegadas!E:AQ""),19,0),"""")"),44597.0) -> 44597 | U84: Encerrado | V84: Certificação INMETRO:Produto certificado por BRICS OCP 0098 Nº Certificado 6994/2021-ELE-1 | W84: =N84 -> 44823
A85: IMAGINARIUM | B85: =HYPERLINK("https://imagens.imgnet.com.br/f/imaginarium/"&C85&";"&C85,image("https://imagens.imgnet.com.br/f/imaginarium/"&C85&"))")) | C85: PI5144Y | D85: 2022 - FAT01 | E85: Gain Belong | F85: MAQUINA DE WAFFLE 220V STRANGER THINGS | G85: COMES E BEBES | H85: INMETRO Eletrodomésticos | I85: 2 amostras para ensaios na China | J85: 10/08/22 - Certificado encerrado. - 20/09 - Certificado Inmetro emitido. 14/09 - Certificado está para assinatura. 18/08 - Finalização dos testes atualizada para 13/09 - Late FAT 01. 10/08 - Auditoria realizada em 03/08, relatório sob análise. Amostras chegaram ao laboratório no dia 06/08 e a previsão de finalização dos testes é 01/09. 28/07 - Serena informou que amostra deve estar ok para coleta dia 03/08. 05/07 - Recebidos os documentos, aguardando retorno da BRICS referente a data de auditoria. Serena informou que o item será Late FAT 01. 18/06 - Amostra deve estar pronta em 28/07 17/06 - Aguardando retorno do fornecedor sobre prontidão da amostra até 18/06 | L85: Produto + Embalagem (INMETRO) | N85: 44823 | O85: =N85-90 -> 44733 | P85: 6994/2021-ELE-1 | Q85: NA | R85: BRICS OCP 0098 | S85: TRUE | T85: =IFERROR(__xludf.DUMMYFUNCTION("IFERROR(VLOOKUP(C85,IMPORTRANGE(""https://docs.google.com/spreadsheets/d/1RmEXtNg60OGvqZjyMxiYNPJ6S_kcz01v57qrHugDWVc/edit#gid=0"",""Chegadas!E:AQ""),19,0),"""")"),44597.0) -> 44597 | U85: Encerrado | V85: Certificação INMETRO:Produto certificado por BRICS OCP 0098 Nº Certificado 6994/2021-ELE-1 | W85: =N85 -> 44823
A86: IMAGINARIUM | B86: =HYPERLINK("https://imagens.imgnet.com.br/f/imaginarium/"&C86&";"&C86,image("https://imagens.imgnet.com.br/f/imaginarium/"&C86&"))")) | C86: PI5133Y | D86: 2021 - FAT12 | E86: Kayuan | F86: FAIXA SPEAKER BLUETOOTH FITDANCE PRETA | G86: TECH | H86: ANATEL CATEGORIA 2 - MÓDULO BLUETOOTH | I86: 2 Amostras completas + 1 Amostra teste lab (Placa PCB com entradas de cabo de RF e Software) | J86: 11/09/23 - Certificado suspenso. 20/03/23 - O certificado não será renovado. - 01/10 - Certificado de homologação Anatel emitido. 08/09 - Processo cadastrado na Anatel. 03/09 - Documentos completos enviados hoje (faltava o manual), previsão de finalização da homologação: 08/10. 18/08 - Recebemos os laudos do laboratório, estão sob análise. Previsão finalização: 23/10. 05/08 - Amostra entregue no laboratório. 02/08 - Amostra recebida semana passada, sendo configurada e verificando cotação com laboratórios. Previsão finalização 30/09. 12/06 - Previsão de envio das amostras: 16/07 - ainda não recebemos update. 17/06 - Previsão de envio das amostras: 30/06. | L86: Produto + Manual (ANATEL) | M86: Shenzhen Aita Technology Co., Ltd | N86: 45175 | O86: =N86-90 -> 45085 | P86: MT-5624/2021 | Q86: 12413-21-11617 | R86: MASTER | S86: TRUE | T86: =IFERROR(__xludf.DUMMYFUNCTION("IFERROR(VLOOKUP(C86,IMPORTRANGE(""https://docs.google.com/spreadsheets/d/1RmEXtNg60OGvqZjyMxiYNPJ6S_kcz01v57qrHugDWVc/edit#gid=0"",""Chegadas!E:AQ""),19,0),"""")"),44535.0) -> 44535 | U86: Encerrado | V86: Produto homologado pela Anatel: Nº Homologação 12413-21-11617 | W86: =N86 -> 45175
A87: IMAGINARIUM | B87: =HYPERLINK("https://imagens.imgnet.com.br/f/imaginarium/"&C87&";"&C87,image("https://imagens.imgnet.com.br/f/imaginarium/"&C87&"))")) | C87: PI5134Y | D87: 2021 - FAT12 | E87: 3Rd Eye | F87: GARRAFA COM AMPLIFICADOR FITDANCE PRETA | G87: TECH | H87: ANATEL CATEGORIA 2 - MÓDULO BLUETOOTH | I87: 2 Amostras completas + 1 Amostra teste lab (Placa PCB com entradas de cabo de RF e Software) | J87: 20/03/23 - O certificado não será renovado. - 01/10 - Certificado de homologação Anatel emitido. 27/08 - Processo cadastrado na Anatel. Em análise. Previsão de finalização da homologação: 26/09. 09/08 - Relatório recebido, sem ocorrências. Previsão de finalização: 15/09. 21/07 - Amostra configurada enviada ao laboratório hoje, ensaios serão finalizados dia 04/08, relatórios prontos dia 10/08, previsão finalização homologação: 15/09. 29/06 - Amostras recebidas (774060074627) e encaminhadas para configuração. Cotando com os laboratórios. 23/06 - Previsão de envio das amostras: 28/06. | L87: Produto + Manual (ANATEL) | N87: 45164 | O87: =N87-90 -> 45074 | P87: MT-5625/2021 | Q87: 12464-21-10468 | S87: TRUE | T87: =IFERROR(__xludf.DUMMYFUNCTION("IFERROR(VLOOKUP(C87,IMPORTRANGE(""https://docs.google.com/spreadsheets/d/1RmEXtNg60OGvqZjyMxiYNPJ6S_kcz01v57qrHugDWVc/edit#gid=0"",""Chegadas!E:AQ""),19,0),"""")"),44535.0) -> 44535 | U87: Encerrado | V87: Este produto contém a placa PI5134Y código de homologação ANATEL: 12464-21-10468 | W87: =N87 -> 45164
A88: IMAGINARIUM | B88: =HYPERLINK("https://imagens.imgnet.com.br/f/imaginarium/"&C88&";"&C88,image("https://imagens.imgnet.com.br/f/imaginarium/"&C88&"))")) | C88: PI5135Y | D88: 2021 - FAT12 | E88: Winwend | F88: SUPORTE INTELIGENTE PRA CELULAR FITDANCE | G88: TECH | H88: ANATEL CATEGORIA 2 - MÓDULO BLUETOOTH | I88: 2 Amostras completas + 1 Amostra teste lab (Placa PCB com entradas de cabo de RF e Software) | J88: 20/03/23 - O certificado não será renovado. - 01/10 - Certificado de homologação Anatel emitido. 09/09 - Processo cadastrado na Anatel. Em análise. 31/08 - Relatório recebido hoje. Previsão de finalização homologação: 08/10. Ready date estimado: 30/09, item chegaria no CD em 17/12 aprox. 11/08 - Finalização dos testes atrasou e está prevista para 23/08, sem impacto no schedule. Finalização da homologação: 28/09. 03/08 - Leadtime é de 35 dias, finalizando dia 16/08 item fica ok para FAT 12. 02/08 - Finalização dos ensaios: 10/08, entrega dos laudos: 16/08. Passei a data para a China, verificando sobre leadtime e schedule. 19/07 - Amostras sendo configuradas, previsão de finalização dos testes 12/08 e finalização da homologação: 22/09. 06/07 - Amostras enviadas via FEDEX 774177531052, previsão de chegada 13/07. | L88: Produto + Manual (ANATEL) | M88: Sunking Circuits Electronics Co., Ltd | N88: 45178 | O88: =N88-90 -> 45088 | P88: MT-5639/2021 | Q88: 12805-21-14180 | R88: MASTER | S88: TRUE | T88: =IFERROR(__xludf.DUMMYFUNCTION("IFERROR(VLOOKUP(C88,IMPORTRANGE(""https://docs.google.com/spreadsheets/d/1RmEXtNg60OGvqZjyMxiYNPJ6S_kcz01v57qrHugDWVc/edit#gid=0"",""Chegadas!E:AQ""),19,0),"""")"),44535.0) -> 44535 | U88: Encerrado | V88: Este produto contém a placa PI5135Y código de homologação ANATEL: 12412-21-10468 | W88: =N88 -> 45178
A89: IMAGINARIUM | B89: =HYPERLINK("https://imagens.imgnet.com.br/f/imaginarium/"&C89&";"&C89,image("https://imagens.imgnet.com.br/f/imaginarium/"&C89&"))")) | C89: PI5147Y | D89: 2022 - FAT01 | E89: Kayuan | F89: HEADPHONE BT STRANGER THINGS DUSTIN | G89: TECH | H89: ANATEL CATEGORIA 2 - MÓDULO BLUETOOTH | I89: 2 Amostras completas + 1 Amostra teste lab (Placa PCB com entradas de cabo de RF e Software) | J89: 14/03/23 - Certificado não será renovado. - 19/10 - Certificado de homologação Anatel emitido. 18/10 - Processo cadastrado na Anatel. Valor para inclusão acordado: R$ 900,00. Será o mesmo modelo dos headphones hogwarts. Vamos incluir na mesma família. 16/07 - Ainda sem atualização sobre as amostras. 24/06 - Envio das amostras: 10/07 17/06 - Previsão de envio das amostras: 30/06 | L89: Produto + Manual (ANATEL) | N89: 45093 | O89: =N89-90 -> 45003 | P89: MT-5295/2021 | Q89: 04730-21-11617 | S89: TRUE | T89: =IFERROR(__xludf.DUMMYFUNCTION("IFERROR(VLOOKUP(C89,IMPORTRANGE(""https://docs.google.com/spreadsheets/d/1RmEXtNg60OGvqZjyMxiYNPJ6S_kcz01v57qrHugDWVc/edit#gid=0"",""Chegadas!E:AQ""),19,0),"""")"),44566.0) -> 44566 | U89: Encerrado | V89: Produto homologado pela Anatel: Nº Homologação 04730-21-11617 | W89: =N89 -> 45093
A90: IMAGINARIUM | B90: =HYPERLINK("https://imagens.imgnet.com.br/f/imaginarium/"&C90&";"&C90,image("https://imagens.imgnet.com.br/f/imaginarium/"&C90&"))")) | C90: PI5139Y | D90: 2022 - FAT01 | E90: universe sound | F90: FONE DE OUVIDO SEM FIO BORA | G90: TECH | H90: ANATEL CATEGORIA 2 - MÓDULO BLUETOOTH | I90: 2 Amostras completas + 1 Amostra teste lab (Placa PCB com entradas de cabo de RF e Software) | J90: 01/06/2023 - Certificado suspenso. - 03/11 - Certificado de homologação Anatel emitido. 19/10 - Processo cadastrado na Anatel. Valor para inclusão acordado: R$ 900,00. Será utilizada a mesma certificação do earphone passado - mesmo formato, não precisa enviar amostra | L90: Produto + Manual (ANATEL) | N90: 45077 | O90: =N90-90 -> 44987 | P90: MT-5347/2021 | Q90: 06109-21-12418 | S90: TRUE | T90: =IFERROR(__xludf.DUMMYFUNCTION("IFERROR(VLOOKUP(C90,IMPORTRANGE(""https://docs.google.com/spreadsheets/d/1RmEXtNg60OGvqZjyMxiYNPJ6S_kcz01v57qrHugDWVc/edit#gid=0"",""Chegadas!E:AQ""),19,0),"""")"),44566.0) -> 44566 | U90: Encerrado | V90: Produto homologado pela Anatel: Nº Homologação 06109-21-12418 | W90: =N90 -> 45077
A91: IMAGINARIUM | B91: =HYPERLINK("https://imagens.imgnet.com.br/f/imaginarium/"&C91&";"&C91,image("https://imagens.imgnet.com.br/f/imaginarium/"&C91&"))")) | C91: PI5063Y | D91: 2021 - FAT10 | E91: Kyc | F91: CARREGADOR PORTATIL CAPIVARA | G91: TECH | H91: ANATEL CATEGORIA 1 - CELULARES | I91: 40 Amostras | J91: 27/10/23 - O certificado não será renovado. - 09/03 - Certificado de homologação emitido. 15/02 - Certificado cadastrado na Anatel, aguardando emissão do certificado de Homologação. 06/01 - Últimos laudos recebidos. 13/12 - Amostras chegaram na Eagle Tech para configuração. 10/12 - Recebida a agenda do Laboratório. Previsão de entrega dos relatórios: 30/12. 06/12 - Amostras chegaram no CD. Seguindo com o envio para São Paulo. Previsão permanece para FAT 6. Embarque postergado, chegada esperada no CD agora é 05/11. Item será FAT 6. 19/09 - Fred: Oi Isa, for now yes, but if there's any changes or delay, we need to update later because 13/12 is the real deadline to produce and deliver before CNY which is around end of Jan. if we missed that , then it'll be end of Mar, which is FAT05~06 already. Previsão de finalização dos testes: 13/12. Item será FAT 04 provavelmente. | L91: Produto + Manual (ANATEL) | M91: Shenzhen Kaiyue Century Technology Co., Ltd | N91: 45336 | O91: =N91-90 -> 45246 | P91: MT-5846/2022 | Q91: 00427-22-12562 | S91: TRUE | T91: =IFERROR(__xludf.DUMMYFUNCTION("IFERROR(VLOOKUP(C91,IMPORTRANGE(""https://docs.google.com/spreadsheets/d/1RmEXtNg60OGvqZjyMxiYNPJ6S_kcz01v57qrHugDWVc/edit#gid=0"",""Chegadas!E:AQ""),19,0),"""")"),44717.0) -> 44717 | U91: Encerrado | V91: Produto homologado pela Anatel: Nº Homologação 00427-22-12562 | W91: =N91 -> 45336
A92: IMAGINARIUM | B92: =HYPERLINK("https://imagens.imgnet.com.br/f/imaginarium/"&C92&";"&C92,image("https://imagens.imgnet.com.br/f/imaginarium/"&C92&"))")) | C92: PI5163Y | D92: 2022 - FAT02 | E92: Sinolink | F92: MAQUINA DE SORVETE 127V NUMA NICE | G92: COMES E BEBES | H92: INMETRO Eletrodomésticos | I92: 2 amostras para ensaios na China | J92: 20/09/22 - Certificado encerrado. - 20/09 - Brics: processos finalizados ontem, encaminhados para coordenação, liberação das cartas deve ocorrer entre hoje e amanhã. 06/09/22 - Item não será recomprado, seguiremos com o encerramento. 02/12 - Certificado de conformidade emitido. 30/11 - MP iniciou dia 18, mercadoria ficará pronta no dia 20/01 (uma semana antes do CNY). 10/11 - Fion informou que a fábrica mandou o interruptor revisado hoje. Aguardando confirmação do laboratório, mas considerando 4 dias de ensaios, se tivermos o ok no dia 19, segundo a China, o ready date será antes do CNY (20/01). 05/11 - O teste do interruptor foi realizado ontem e falhou, a fábrica está em contato com o laboratório e irá revisar a peça e deve enviar na próxima semana para ser testado, por este motivo haverá atraso na emissão do relatório. Os outros testes foram concluídos e aprovados, inclusive do conector. 20/10 - Precisou ser feita correção no conector e o lab está aguardando a fábrica enviar o item corrigido. O laboratório informou que consegue terminar dia 04/11, estamos cobrando a Jenny (fábrica) o envio do conector o mais breve possível e o laboratório para finalização dos testes. 23/09 - Auditoria e coleta das amostras agendadas para 29/09. Previsão de finalização dos testes 03/11, chegada CD: 11/03. 24/08 - Amostras finais estarão prontas dia 17/09. Chegada CD: 28/02. 18/08 - Amostra não será enviada para verificação da Qualidade. Artwork enviado em 16/08, considerando 30 dias para produção das amostras + 60 de leadtime chegaria dia 25/02 no CD. Verificar quando amostra será enviada ao BR e aprovação da Qualidade. | L92: Produto + Embalagem (INMETRO) | N92: 44895 | O92: =N92-90 -> 44805 | P92: 7197/2021-ELE-1 | Q92: NA | R92: BRICS OCP 0098 | S92: TRUE | T92: =IFERROR(__xludf.DUMMYFUNCTION("IFERROR(VLOOKUP(C92,IMPORTRANGE(""https://docs.google.com/spreadsheets/d/1RmEXtNg60OGvqZjyMxiYNPJ6S_kcz01v57qrHugDWVc/edit#gid=0"",""Chegadas!E:AQ""),19,0),"""")"),44656.0) -> 44656 | U92: Encerrado | V92: Certificação INMETRO:Produto certificado por BRICS OCP 0098 Nº Certificado 7197/2021-ELE-1 | W92: =N92 -> 44895
A93: IMAGINARIUM | B93: =HYPERLINK("https://imagens.imgnet.com.br/f/imaginarium/"&C93&";"&C93,image("https://imagens.imgnet.com.br/f/imaginarium/"&C93&"))")) | C93: PI5164Y | D93: 2022 - FAT02 | E93: Sinolink | F93: MAQUINA DE SORVETE 220V NUMA NICE | G93: COMES E BEBES | H93: INMETRO Eletrodomésticos | I93: 2 amostras para ensaios na China | J93: 20/09/22 - Certificado encerrado. - 20/09 - Brics: processos finalizados ontem, encaminhados para coordenação, liberação das cartas deve ocorrer entre hoje e amanhã. 06/09/22 - Item não será recomprado, seguiremos com o encerramento. 02/12 - Certificado de conformidade emitido. 30/11 - MP iniciou dia 18, mercadoria ficará pronta no dia 20/01 (uma semana antes do CNY). 10/11 - Fion informou que a fábrica mandou o interruptor revisado hoje. Aguardando confirmação do laboratório, mas considerando 4 dias de ensaios, se tivermos o ok no dia 19, segundo a China, o ready date será antes do CNY (20/01). 05/11 - O teste do interruptor foi realizado ontem e falhou, a fábrica está em contato com o laboratório e irá revisar a peça e deve enviar na próxima semana para ser testado, por este motivo haverá atraso na emissão do relatório. Os outros testes foram concluídos e aprovados, inclusive do conector. 20/10 - Precisou ser feita correção no conector e o lab está aguardando a fábrica enviar o item corrigido. O laboratório informou que consegue terminar dia 04/11, estamos cobrando a Jenny (fábrica) o envio do conector o mais breve possível e o laboratório para finalização dos testes. 23/09 - Auditoria e coleta das amostras agendadas para 29/09. Previsão de finalização dos testes 03/11, chegada CD: 11/03. 24/08 - Amostras finais estarão prontas dia 17/09. Chegada CD: 28/02. 18/08 - Amostra não será enviada para verificação da Qualidade. Artwork enviado em 16/08, considerando 30 dias para produção das amostras + 60 de leadtime chegaria dia 25/02 no CD. Verificar quando amostra será enviada ao BR e aprovação da Qualidade. | L93: Produto + Embalagem (INMETRO) | N93: 44895 | O93: =N93-90 -> 44805 | P93: 7197/2021-ELE-1 | Q93: NA | R93: BRICS OCP 0098 | S93: TRUE | T93: =IFERROR(__xludf.DUMMYFUNCTION("IFERROR(VLOOKUP(C93,IMPORTRANGE(""https://docs.google.com/spreadsheets/d/1RmEXtNg60OGvqZjyMxiYNPJ6S_kcz01v57qrHugDWVc/edit#gid=0"",""Chegadas!E:AQ""),19,0),"""")"),44656.0) -> 44656 | U93: Encerrado | V93: Certificação INMETRO:Produto certificado por BRICS OCP 0098 Nº Certificado 7197/2021-ELE-1 | W93: =N93 -> 44895
A94: IMAGINARIUM | B94: =HYPERLINK("https://imagens.imgnet.com.br/f/imaginarium/"&C94&";"&C94,image("https://imagens.imgnet.com.br/f/imaginarium/"&C94&"))")) | C94: PI5188Y | D94: 2022 - FAT03 | E94: Kyc | F94: CARREGADOR POR INDUCAO BOLACHA MAIZUMA | G94: TECH | H94: ANATEL CATEGORIA 1 - CELULARES | I94: 2 Amostras completas | J94: 20/03/23 - O certificado não será renovado. - 20/12 - Etiquetas entregues no fornecedor na China, tracking FedEx: 815660002845. 22/10 - Certificado de homologação emitido. 21/10 - Processo cadastrado na Anatel. 27/09 - Testes foram finalizados, em análise da OCD para submissão a Anatel. 20/09 - Amostra entregue no laboratório nesta data. 03/09 - Amostras chegam dia 08 via Fedex. Agenda do laboratório recebida: previsão de Início dos ensaios: 21/0, previsão de entrega dos relatórios: 27/09. Finalização prevista para 19/11. 31/08 - Amostras enviadas hoje para o Brasil, tracking 774680190808, previsão de chegada 08/09. Previsão de finalização da homologação: 22/11. 18/08 - Previsão de envio das amostras: 03/09. Produção em paralelo. Previsão finalização da homologação: 22/11. 13/08 - Vincent confirmou que não será a mesma placa do PI4461Y. Aguardando informação sobre prontidão das amostras. | L94: Produto + Manual (ANATEL) | M94: Shenzhen Kaiyue Century Technology Co., Ltd | N94: 45219 | O94: =N94-90 -> 45129 | P94: MT-5730/2021 | Q94: 14341-21-12562 | S94: TRUE | T94: =IFERROR(__xludf.DUMMYFUNCTION("IFERROR(VLOOKUP(C94,IMPORTRANGE(""https://docs.google.com/spreadsheets/d/1RmEXtNg60OGvqZjyMxiYNPJ6S_kcz01v57qrHugDWVc/edit#gid=0"",""Chegadas!E:AQ""),19,0),"""")"),44686.0) -> 44686 | U94: Encerrado | V94: Produto homologado pela Anatel: Nº Homologação 14341-21-12562 | W94: =N94 -> 45219
A95: IMAGINARIUM | B95: =HYPERLINK("https://imagens.imgnet.com.br/f/imaginarium/"&C95&";"&C95,image("https://imagens.imgnet.com.br/f/imaginarium/"&C95&"))")) | C95: PI5178Y | D95: 2022 - FAT03 | E95: Smarti-Tech | F95: AROMATIZADOR E UMIDIFICADOR MONTANHA | G95: CASA E DECORAÇÃO | H95: INMETRO Eletrodomésticos | I95: 2 amostras para ensaios na China | J95: 19/08/22 - Certificado encerrado. - 30/11 - Certificado de conformidade emitido. 28/10 - Vincent informou que a previsão de finalização da MP é 10/12. 27/10 - Testes ok, avisei que MP pode ser iniciada. 09/10 - Previsão de finalização dos testes laboratoriais: 20/10. 22/09 - Testes iniciados em 22/09, previsão de finalização: 25/10. Previsão de entrega no CD: 14/03. 14/09 - Auditoria e coleta agendadas para 17/09. Previsão de finalização da certificação: 19/11. Previsão de chegada no CD: 17/03. 03/09 - Leadtime: 45 dias, finalizando a análise dos testes no dia 15/10 (previsão), estaria no CD por volta de 8/3. 01/09 - Coleta das amostras será feita no dia 08/09. Aguardando confirmação de ready date, mas considerando 60 dias de leadtime, chegaria no CD dia 20/02. 24/08 - Previsão prontidão amostra final: 30/08, previsão de início de MP: 06/10. Questionado ao Vincent o ready date da carga. 18/08 - Amostras estarão prontas em 17/09, solicitei o contato na fábrica para agendarmos a auditoria e coleta dos itens. 16/08 - Fred informou que o fornecedor pode passar pela auditoria, vamos dar sequência na certificação. Verificar sobre processo de Qualidade do fornecedor | L95: Produto + Embalagem (INMETRO) | N95: 44894 | O95: =N95-90 -> 44804 | P95: 7141/2021-ELE-1 | Q95: NA | R95: BRICS OCP 0098 | S95: TRUE | T95: =IFERROR(__xludf.DUMMYFUNCTION("IFERROR(VLOOKUP(C95,IMPORTRANGE(""https://docs.google.com/spreadsheets/d/1RmEXtNg60OGvqZjyMxiYNPJ6S_kcz01v57qrHugDWVc/edit#gid=0"",""Chegadas!E:AQ""),19,0),"""")"),44625.0) -> 44625 | U95: Encerrado | V95: Certificação INMETRO:Produto certificado por BRICS OCP 0098 Nº Certificado 7141/2021-ELE-1 | W95: =N95 -> 44894
A96: IMAGINARIUM | B96: =HYPERLINK("https://imagens.imgnet.com.br/f/imaginarium/"&C96&";"&C96,image("https://imagens.imgnet.com.br/f/imaginarium/"&C96&"))")) | C96: PI5132Y | D96: 2021 - FAT12 | E96: Kayuan | F96: HEADPHONE BLUETOOTH FITDANCE HIT E BEAT | G96: TECH | H96: ANATEL CATEGORIA 2 - MÓDULO BLUETOOTH | I96: 2 Amostras completas + 1 Amostra teste lab (Placa PCB com entradas de cabo de RF e Software) | J96: 20/03/23 - O certificado não será renovado. - 05/11 - Certificado de Homologação emitido. 13/10 - Processo cadastrado na Anatel. 30/09 - Relatório dos ensaios recebido, sendo analisado pela OCD para submissão a Anatel. 21/09 - Amostra entregue no laboratório. 14/09 - Item será entregue no lab segunda-feira. Previsão de finalização da homologação: 20/11. 31/08 - O envio das amostras foi postergado, pois estavam com problemas de funcionamento. Aguardando previsão da China. Se enviadas semana que vem, previsão de finalização da homologação fica para 26/12. 16/08 - Confirmado que o modelo da placa não é o mesmo utilizado para os fones da Puket, ready date estimado das amostras:30/08. 30/08. Finalização homologação: 11/11. Produção em paralelo. | L96: Produto + Manual (ANATEL) | N96: 45212 | O96: =N96-90 -> 45122 | P96: MT-5689/2021 | Q96: 13472-21-11617 | S96: TRUE | T96: =IFERROR(__xludf.DUMMYFUNCTION("IFERROR(VLOOKUP(C96,IMPORTRANGE(""https://docs.google.com/spreadsheets/d/1RmEXtNg60OGvqZjyMxiYNPJ6S_kcz01v57qrHugDWVc/edit#gid=0"",""Chegadas!E:AQ""),19,0),"""")"),44535.0) -> 44535 | U96: Encerrado | V96: Produto homologado pela Anatel: Nº homologação 13472-21-11617 | W96: =N96 -> 45212
A97: IMAGINARIUM | B97: =HYPERLINK("https://imagens.imgnet.com.br/f/imaginarium/"&C97&";"&C97,image("https://imagens.imgnet.com.br/f/imaginarium/"&C97&"))")) | C97: PI5229Y | D97: 2022 - FAT04 | E97: Wantong | F97: FONTE DE CHOCOLATE 127V MINHAS FONTES | G97: COMES E BEBES | H97: INMETRO Eletrodomésticos | I97: 2 amostras para ensaios na China | J97: 20/09/22 - Certificado encerrado. - 17/08 - Planejamento: não teremos recompra do item, previsão finalização estoque rede e CD: maio/2023. 16/12 - Certificado de conformidade emitido. 06/12 - Finalização dos ensaios prevista para 15/12. 19/11 Inicio dos testes lab. 12/11 pagamento fatura STU, porem deu problema no banco com o envio. 11/11 - Auditoria e coleta serão feitas amanhã, 12/11. Amostras serão entregues no laboratório em 15/11. Recebemos a Invoice e colocamos para pagamento ainda esta semana. 10/11 - Auditoria e coleta das amostras prevista para dia 10/11. 04/11 - Amostras estarão ok para coleta dia 08/11. Brics está ciente. Aguardando documentos - amostras estarão prontas dia 25/10. Vamos seguir com a produção em paralelo aos testes. Ready sate SKU Schedule: 28/12 Ready date com certificação: 28/01 - QC Feriado chinês? Checar com Fred | L97: Produto + Embalagem (INMETRO) | N97: 44910 | O97: =N97-90 -> 44820 | P97: 7333-2021-ELE-1 | Q97: NA | R97: BRICS OCP 0098 | S97: TRUE | T97: =IFERROR(__xludf.DUMMYFUNCTION("IFERROR(VLOOKUP(C97,IMPORTRANGE(""https://docs.google.com/spreadsheets/d/1RmEXtNg60OGvqZjyMxiYNPJ6S_kcz01v57qrHugDWVc/edit#gid=0"",""Chegadas!E:AQ""),19,0),"""")"),44656.0) -> 44656 | U97: Encerrado | V97: Certificação INMETRO:Produto certificado por BRICS OCP 0098 Nº Certificado 7333-2021-ELE-1 | W97: =N97 -> 44910
A98: IMAGINARIUM | B98: =HYPERLINK("https://imagens.imgnet.com.br/f/imaginarium/"&C98&";"&C98,image("https://imagens.imgnet.com.br/f/imaginarium/"&C98&"))")) | C98: PI5230Y | D98: 2022 - FAT04 | E98: Wantong | F98: FONTE DE CHOCOLATE 220V MINHAS FONTES | G98: COMES E BEBES | H98: INMETRO Eletrodomésticos | I98: 2 amostras para ensaios na China | J98: 20/09/22 - Certificado encerrado. - 17/08 - Planejamento: não teremos recompra do item, previsão finalização estoque rede e CD: maio/2023. 16/12 - Certificado de conformidade emitido. 06/12 - Finalização dos ensaios prevista para 15/12. 19/11 Inicio dos testes lab. 12/11 pagamento fatura STU, porem deu problema no banco com o envio. 11/11 - Auditoria e coleta serão feitas amanhã, 12/11. Amostras serão entregues no laboratório em 15/11. Recebemos a Invoice e colocamos para pagamento ainda esta semana. 10/11 - Auditoria e coleta das amostras prevista para dia 10/11. 04/11 - Amostras estarão ok para coleta dia 08/11. Brics está ciente. Aguardando documentos - amostras estarão prontas dia 25/10. Vamos seguir com a produção em paralelo aos testes. Ready sate SKU Schedule: 28/12 Ready date com certificação: 28/01 - QC Feriado chinês? Checar com Fred | L98: Produto + Embalagem (INMETRO) | N98: 44910 | O98: =N98-90 -> 44820 | P98: 7333-2021-ELE-1 | Q98: NA | R98: BRICS OCP 0098 | S98: TRUE | T98: =IFERROR(__xludf.DUMMYFUNCTION("IFERROR(VLOOKUP(C98,IMPORTRANGE(""https://docs.google.com/spreadsheets/d/1RmEXtNg60OGvqZjyMxiYNPJ6S_kcz01v57qrHugDWVc/edit#gid=0"",""Chegadas!E:AQ""),19,0),"""")"),44656.0) -> 44656 | U98: Encerrado | V98: Certificação INMETRO:Produto certificado por BRICS OCP 0098 Nº Certificado 7333-2021-ELE-1 | W98: =N98 -> 44910
A99: IMAGINARIUM | B99: =HYPERLINK("https://imagens.imgnet.com.br/f/imaginarium/"&C99&";"&C99,image("https://imagens.imgnet.com.br/f/imaginarium/"&C99&"))")) | C99: PI5231Y | D99: 2022 - FAT04 | E99: Wantong | F99: FONDUE ELETRICO COM JOGO SE JOGA | G99: COMES E BEBES | H99: INMETRO Eletrodomésticos | I99: 2 amostras para ensaios na China | J99: 20/09/22 - Certificado encerrado. - 20/09 - Brics: processos finalizados ontem, encaminhados para coordenação, liberação das cartas deve ocorrer entre hoje e amanhã. 06/09/22 - Item não será recomprado, seguiremos com o encerramento. 16/12 - Certificado de conformidade emitido. 06/12 - Finalização do ensaios prevista para 15/12. 11/11 - Auditoria e coleta serão feitas amanhã, 12/11. Amostras serão entregues no laboratório em 15/11. Recebemos a Invoice e colocamos para pagamento ainda esta semana. 10/11 - Auditoria e coleta das amostras prevista para dia 10/11. 04/11 - Amostras estarão ok para coleta dia 08/11. Brics está ciente. Aguardando documentos - amostras estarão prontas dia 25/10. Vamos seguir com a produção em paralelo aos testes. Ready sate SKU Schedule: 28/12 Ready date com certificação: 28/01 - QC Feriado chinês? Checar com Fred | L99: Produto + Embalagem (INMETRO) | N99: 44910 | O99: =N99-90 -> 44820 | P99: 7333-2021-ELE-2 | Q99: NA | R99: BRICS OCP 0098 | S99: TRUE | T99: =IFERROR(__xludf.DUMMYFUNCTION("IFERROR(VLOOKUP(C99,IMPORTRANGE(""https://docs.google.com/spreadsheets/d/1RmEXtNg60OGvqZjyMxiYNPJ6S_kcz01v57qrHugDWVc/edit#gid=0"",""Chegadas!E:AQ""),19,0),"""")"),44656.0) -> 44656 | U99: Encerrado | V99: Certificação INMETRO:Produto certificado por BRICS OCP 0098 Nº Certificado 7333-2021-ELE-2 | W99: =N99 -> 44910
A100: IMAGINARIUM | B100: =HYPERLINK("https://imagens.imgnet.com.br/f/imaginarium/"&C100&";"&C100,image("https://imagens.imgnet.com.br/f/imaginarium/"&C100&"))")) | C100: PI5269Y | D100: 2022 - FAT04 | E100: Eastar | F100: TORRADEIRA 127V BEATLES ALL YOU NEED | G100: COMES E BEBES | H100: INMETRO Eletrodomésticos | I100: 2 amostras para ensaios na China | J100: 20/09/22 - Certificado encerrado. - 20/09 - Brics: processos finalizados ontem, encaminhados para coordenação, liberação das cartas deve ocorrer entre hoje e amanhã. 06/09/22 - Item não será recomprado, seguiremos com o encerramento. 02/12 - Certificado de conformidade emitido. 09/11 - Brics conversou com o laboratório, e vão finalizar os testes antes do dia 25 (mas não especificaram data). 05/11 - Fion informou que, iniciando os testes no dia 30/11, mp finalizaria em 20/01 no mínimo (e fábrica fecha para CNY no dia 22/01) 04/11 - Testes iniciaram ontem (03/11) e previsão de finalização é 25/11. 29/09 - Auditoria ocorreu bem e as amostras já estão no laboratório. Faremos o pagamento para a STU hoje. Aguardando previsão de finalização. | L100: Produto + Embalagem (INMETRO) | N100: 44910 | O100: =N100-90 -> 44820 | P100: 7285/2021-ELE-1 | Q100: NA | R100: BRICS OCP 0098 | S100: TRUE | T100: =IFERROR(__xludf.DUMMYFUNCTION("IFERROR(VLOOKUP(C100,IMPORTRANGE(""https://docs.google.com/spreadsheets/d/1RmEXtNg60OGvqZjyMxiYNPJ6S_kcz01v57qrHugDWVc/edit#gid=0"",""Chegadas!E:AQ""),19,0),"""")"),44656.0) -> 44656 | U100: Encerrado | V100: Certificação INMETRO:Produto certificado por BRICS OCP 0098 Nº Certificado 7285/2021-ELE-1 | W100: =N100 -> 44910
...

Sheet Puket
A1: MARCA | B1: IMAGEM | C1: CÓDIGO | D1: COLEÇÃO | E1: Fornecedor | F1: NOME | G1: NEGÓCIO | H1: TIPO DE CERTIFICAÇÃO | I1: AMOSTRAS NECESSÁRIAS | J1: STATUS | K1: DATA ÚLTIMA ATUALIZAÇÃO (INICIAL, MANUTENÇÃO OU ENCERRAMENTO) | L1: ROTULAGEM | M1: FABRICANTE | N1: Validade da Certificação | O1: Início Manutenção | P1: Número Certificado | Q1: Número Registro / Homologação | R1: Possui ISO 9001? | S1: CHEGADA CD | T1: SITUAÇÃO | U1: Descrição E-commerce | V1: Prazo Final Venda
A2: PUKET | C2: 100400403 | D2: 2023 HIGH SUMMER | E2: TOYLAND | F2: ALMOFADA PELUCIA UNICORNIO | G2: AÇÃO PROMOCIONAL | H2: INMETRO BRINQUEDOS SISTEMA 5 (FÁBRICA) - PORTARIA 302 | I2: 9 Amostras | J2: 26/10/23 - Isabela: De acordo com os emails da Isadora, essa certificação foi encerrada. 22/06 - Número de Registro concedido. 13/06 - Número de Registro solicitado nesta data. 08/06 - Certificado de Conformidade emitido. 06/05 - Coleta confirmada, auditoria da fábrica prevista para 12/05. | L2: Produto (selo Inmetro + advertências) | N2: 45085 | O2: =N2-90 -> 44995 | P2: 7796/2022-BRI-1 | Q2: 006561/2022 | R2: TRUE | S2: =IFERROR(__xludf.DUMMYFUNCTION("VLOOKUP(C2,importrange(""https://docs.google.com/spreadsheets/d/1fN1Q8KwrSYW55JpWNgQQ61JbS3zg1Ft2OqML6ziwN_Q/edit#gid=1174286835"",""PreCons!J:V""),13,0)"),"#N/A") -> #N/A | T2: Encerrado | U2: Certificação INMETRO: Produto certificado por BRICS OCP 0098 Nº Registro 006561/2022 | V2: =IFERROR(IF(T2="Ativo","Ativo",IF(T2="SKU excluído","Vencido",VLOOKUP(C2,Encerramentos!B:G,6,0))),"") -> 45869
A3: PUKET | C3: 100400402 | D3: 2023 HIGH SUMMER | E3: TOYLAND | F3: ALMOFADA PELUCIA DINOSSAURO | G3: AÇÃO PROMOCIONAL | H3: INMETRO BRINQUEDOS SISTEMA 5 (FÁBRICA) - PORTARIA 302 | I3: 9 Amostras | J3: 26/10/23 - Isabela: De acordo com os emails da Isadora, essa certificação foi encerrada. 22/06 - Número de Registro concedido. 13/06 - Número de Registro solicitado nesta data. 08/06 - Certificado de Conformidade emitido. 06/05 - Coleta confirmada, auditoria da fábrica prevista para 12/05. | L3: Produto (selo Inmetro + advertências) | N3: 45085 | O3: =N3-90 -> 44995 | P3: 7796/2022-BRI-1 | Q3: 006561/2022 | R3: TRUE | S3: =IFERROR(__xludf.DUMMYFUNCTION("VLOOKUP(C3,importrange(""https://docs.google.com/spreadsheets/d/1fN1Q8KwrSYW55JpWNgQQ61JbS3zg1Ft2OqML6ziwN_Q/edit#gid=1174286835"",""PreCons!J:V""),13,0)"),"#N/A") -> #N/A | T3: Encerrado | U3: Certificação INMETRO: Produto certificado por BRICS OCP 0098 Nº Registro 006561/2022 | V3: =IFERROR(IF(T3="Ativo","Ativo",IF(T3="SKU excluído","Vencido",VLOOKUP(C3,Encerramentos!B:G,6,0))),"") -> 45869
A4: PUKET | C4: 100400416 | D4: 2023 HIGH SUMMER | E4: Kayuan | F4: HEADPHONE BLUETOOTH GIRLS - COLOR BLOCK | G4: AÇÃO PROMOCIONAL | H4: ANATEL CATEGORIA 2 - MÓDULO BLUETOOTH | I4: 0 Amostras | J4: 30/08 - Certificado de Homologação emitido. Chegada CD: 07/10. 29/08 - Status na Anatel: Em análise - RE. 26/08 - Efetuado o upload dos arquivos na Anatel e solicitado retorno quanto à inclusão dos novos modelos. 26/07 - Enviados documentos para Master, aguardando retorno referente a inclusão. 15/06 - Solicitadas fotos internas e externas dos modelos para enviar ao OCD. | L4: Produto + Manual (ANATEL) | N4: 45151 | O4: =N4-90 -> 45061 | P4: MT-5533/2021 | Q4: 09550-21-11617 | R4: TRUE | S4: =IFERROR(__xludf.DUMMYFUNCTION("VLOOKUP(C4,importrange(""https://docs.google.com/spreadsheets/d/1fN1Q8KwrSYW55JpWNgQQ61JbS3zg1Ft2OqML6ziwN_Q/edit#gid=1174286835"",""PreCons!J:V""),13,0)"),"#N/A") -> #N/A | T4: Encerrado | U4: Este produto está homologado pela Anatel de acordo com os procedimentos regulamentados para avaliação da conformidade de produtos para telecomunicações e atende aos requisitos técnicos aplicados, sendo referenciado pelo código de homologação Anatel: 09550-21-11617. Para maiores informações, consulte o site da ANATEL em www.anatel.gov.br | V4: =N4 -> 45151
A5: PUKET | C5: 100400417 | D5: 2023 HIGH SUMMER | E5: Kayuan | F5: HEADPHONE BLUETOOTH BOYS - COLOR BLOCK | G5: AÇÃO PROMOCIONAL | H5: ANATEL CATEGORIA 2 - MÓDULO BLUETOOTH | I5: 0 Amostras | J5: 30/08 - Certificado de Homologação emitido. Chegada CD: 07/10. 29/08 - Status na Anatel: Em análise - RE. 26/08 - Efetuado o upload dos arquivos na Anatel e solicitado retorno quanto à inclusão dos novos modelos. 26/07 - Enviados documentos para Master, aguardando retorno referente a inclusão. 15/06 - Solicitadas fotos internas e externas dos modelos para enviar ao OCD. | L5: Produto + Manual (ANATEL) | N5: 45151 | O5: =N5-90 -> 45061 | P5: MT-5533/2021 | Q5: 09550-21-11617 | R5: TRUE | S5: =IFERROR(__xludf.DUMMYFUNCTION("VLOOKUP(C5,importrange(""https://docs.google.com/spreadsheets/d/1fN1Q8KwrSYW55JpWNgQQ61JbS3zg1Ft2OqML6ziwN_Q/edit#gid=1174286835"",""PreCons!J:V""),13,0)"),"#N/A") -> #N/A | T5: Encerrado | U5: Este produto está homologado pela Anatel de acordo com os procedimentos regulamentados para avaliação da conformidade de produtos para telecomunicações e atende aos requisitos técnicos aplicados, sendo referenciado pelo código de homologação Anatel: 09550-21-11617. Para maiores informações, consulte o site da ANATEL em www.anatel.gov.br | V5: =N5 -> 45151
A6: PUKET | B6: =HYPERLINK("https://imagens.imgnet.com.br/f/imaginarium/"&C6&";"&C6,image("https://imagens.imgnet.com.br/f/imaginarium/"&C6&"))")) | E6: Joy Rain | F6: JoyRain Familia 01 - Lápis Grafite JoyRain Familia 02 - Caneta Esferográfica (LED) JoyRain Familia 03 - Borracha | G6: ACESSÓRIOS | H6: INMETRO SISTEMA 5 (FABRICA) - PORTARIA 481 | L6: Embalagem (INMETRO) | N6: 45198 | O6: =N6-90 -> 45108 | P6: IP-AESC-3488/2020-01 IP-AESC-3488/2020-02 IP-AESC-3488/2020-03 | Q6: 006914/2020 006680/2020 006682/2020 | R6: FALSE | S6: =IFERROR(__xludf.DUMMYFUNCTION("VLOOKUP(C6,importrange(""https://docs.google.com/spreadsheets/d/1fN1Q8KwrSYW55JpWNgQQ61JbS3zg1Ft2OqML6ziwN_Q/edit#gid=1174286835"",""PreCons!J:V""),13,0)"),"#N/A") -> #N/A | T6: Encerrado | V6: =N6 -> 45198
A7: PUKET | C7: 100400422 | D7: 2023 WINTER | E7: TOYLAND | F7: PELUCIA VACA COM LED | G7: AÇÃO PROMOCIONAL | H7: INMETRO BRINQUEDOS SISTEMA 5 (FÁBRICA) - PORTARIA 302 | I7: 9 Amostras | J7: 08/12 - Recebido o número de registro 012531/2022 e enviado a arte para a China realizar a impressão e etiquetagem. Chegada CD 01/03 + uma parte após CNY - PKT-W2320-SZ. 01/12 - Solicitado o Registro no sistema Orquestra. 25/11 - Certificado de conformidade emitido. 23/11 - Draft do certificado aprovado. 24/10 - Ensaios finalizados, liberação do laudo aguarda o retorno das Tags. 18/10 - Previsão de finalização dos ensaios: 24/10. 13/10 - Amostras enviadas ao laboratório. Previsão de chegada CD: 20/02/23 (produção após os testes). 05/09 - Amostras finais ainda não foram enviadas pois a fábrica estava priorizando as amostras da Imaginarium. 20/09 - Amostras finais serão enviadas dia 29/09. 07/09 - Arte final será enviada até o final da semana que vem, para amostras estarem prontas antes do dia 30/09 (feriado nacional chinês 1/10 a 7/10). | L7: Produto (selo Inmetro + advertências) | N7: 45254 | O7: =N7-90 -> 45164 | P7: 8338/2022-BRI-1 | Q7: 005580/2023 | R7: TRUE | S7: =IFERROR(__xludf.DUMMYFUNCTION("VLOOKUP(C7,importrange(""https://docs.google.com/spreadsheets/d/1fN1Q8KwrSYW55JpWNgQQ61JbS3zg1Ft2OqML6ziwN_Q/edit#gid=1174286835"",""PreCons!J:V""),13,0)"),"#N/A") -> #N/A | T7: Encerrado | V7: =IFERROR(IF(T7="Ativo","Ativo",IF(T7="SKU excluído","Vencido",VLOOKUP(C7,Encerramentos!B:G,6,0))),"") -> 46116
A8: PUKET | C8: 100400423 | D8: 2023 WINTER | E8: TOYLAND | F8: PELUCIA TUBARAO COM LED | G8: AÇÃO PROMOCIONAL | H8: INMETRO BRINQUEDOS SISTEMA 5 (FÁBRICA) - PORTARIA 302 | I8: 0 Amostras | J8: 08/12 - Recebido o número de registro 012531/2022 e enviado a arte para a China realizar a impressão e etiquetagem. Chegada CD 01/03 - PKT-W2320-SZ. 01/12 - Solicitado o Registro no sistema Orquestra. 25/11 - Certificado de conformidade emitido. 23/11 - Draft do certificado aprovado. 24/10 - Ensaios finalizados, liberação do laudo aguarda o retorno das Tags. 18/10 - Previsão de finalização dos ensaios: 24/10. 13/10 - Amostras enviadas ao laboratório. Previsão de chegada CD: 20/02/23 (produção após os testes). 05/09 - Amostras finais ainda não foram enviadas pois a fábrica estava priorizando as amostras da Imaginarium. 20/09 - Amostras finais serão enviadas dia 29/09. 07/09 - Arte final será enviada até o final da semana que vem, para amostras estarem prontas antes do dia 30/09 (feriado nacional chinês 1/10 a 7/10). | L8: Produto (selo Inmetro + advertências) | N8: 45254 | O8: =N8-90 -> 45164 | P8: 8338/2022-BRI-1 | Q8: 005580/2023 | R8: TRUE | S8: =IFERROR(__xludf.DUMMYFUNCTION("VLOOKUP(C8,importrange(""https://docs.google.com/spreadsheets/d/1fN1Q8KwrSYW55JpWNgQQ61JbS3zg1Ft2OqML6ziwN_Q/edit#gid=1174286835"",""PreCons!J:V""),13,0)"),"#N/A") -> #N/A | T8: Encerrado | V8: =IFERROR(IF(T8="Ativo","Ativo",IF(T8="SKU excluído","Vencido",VLOOKUP(C8,Encerramentos!B:G,6,0))),"") -> 46116
